{
  "conversion_date": "2025-07-18T10:36:09.159425",
  "total_tables": 88,
  "conversion_stats": {
    "total_tables": 88,
    "converted_tables": 88,
    "total_text_length": 99826
  },
  "table_texts": [
    {
      "table_id": "table_1_Camelot_Table_13_1",
      "content": "表格標題: Camelot_Table_13_1\n表格類型: comparison\n來源頁面: 第13頁\n資料提取方法: camelot\n信心度: 100.0%\n表格欄位: Overall Top 10 Risky Events\n表格內容:\n  Overall Top 10 Risky Events: 1\n  Overall Top 10 Risky Events: 2\n  Overall Top 10 Risky Events: 3\n  Overall Top 10 Risky Events: 4\n  Overall Top 10 Risky Events: 5\n搜尋關鍵字: 比較, 對比, 分析, Overall Top 10 Risky Events",
      "metadata": {
        "original_table_data": {
          "title": "Camelot_Table_13_1",
          "headers": [
            "Overall Top 10 Risky Events",
            ""
          ],
          "rows": [
            [
              "1",
              "Risky Cloud App Access"
            ],
            [
              "2",
              "Stale Microsoft Entra ID Account"
            ],
            [
              "3",
              "Sandbox Detected Email Threat"
            ],
            [
              "4",
              "On-Premises AD Account with Weak Sign-In Security Policy - Password Expiration Disabled"
            ],
            [
              "5",
              "Advanced Spam Protection - Policy Violation"
            ]
          ],
          "source_page": 13,
          "source_file": "data/source/Research-Risk-Report-2025.pdf",
          "table_type": "comparison",
          "confidence": 100.00000000000001,
          "extractor_method": "camelot",
          "metadata": {
            "whitespace": 8.333333333333332,
            "order": 1,
            "flavor": "lattice"
          }
        },
        "source_page": 13,
        "source_file": "data/source/Research-Risk-Report-2025.pdf",
        "table_type": "comparison",
        "confidence": 100.00000000000001,
        "extractor_method": "camelot",
        "conversion_date": "2025-07-18T10:36:09.156447"
      }
    },
    {
      "table_id": "table_2_Camelot_Table_14_2",
      "content": "表格標題: Camelot_Table_14_2\n表格類型: comparison\n來源頁面: 第14頁\n資料提取方法: camelot\n信心度: 100.0%\n表格欄位: Overall Top 10 Risky Events\n表格內容:\n  Overall Top 10 Risky Events: 6\n  Overall Top 10 Risky Events: 7\n  Overall Top 10 Risky Events: 8\n  Overall Top 10 Risky Events: 9\n  Overall Top 10 Risky Events: 10\n搜尋關鍵字: 比較, 對比, 分析, Overall Top 10 Risky Events",
      "metadata": {
        "original_table_data": {
          "title": "Camelot_Table_14_2",
          "headers": [
            "Overall Top 10 Risky Events",
            ""
          ],
          "rows": [
            [
              "6",
              "Data Loss Prevention - Email Violation"
            ],
            [
              "7",
              "Microsoft Entra ID Account with Weak Sign-In Security Policy - MFA Disabled"
            ],
            [
              "8",
              "Microsoft Entra ID Account with Weak Sign-In Security Policy - Password Expiration Disabled"
            ],
            [
              "9",
              "Stale On-Premises AD Account"
            ],
            [
              "10",
              "On-Premises AD Account with Weak Sign-In Security Policy - Password Not Required"
            ]
          ],
          "source_page": 14,
          "source_file": "data/source/Research-Risk-Report-2025.pdf",
          "table_type": "comparison",
          "confidence": 100.00000000000001,
          "extractor_method": "camelot",
          "metadata": {
            "whitespace": 8.333333333333332,
            "order": 1,
            "flavor": "lattice"
          }
        },
        "source_page": 14,
        "source_file": "data/source/Research-Risk-Report-2025.pdf",
        "table_type": "comparison",
        "confidence": 100.00000000000001,
        "extractor_method": "camelot",
        "conversion_date": "2025-07-18T10:36:09.156497"
      }
    },
    {
      "table_id": "table_3_Camelot_Table_15_3",
      "content": "表格標題: Camelot_Table_15_3\n表格類型: comparison\n來源頁面: 第15頁\n資料提取方法: camelot\n信心度: 100.0%\n表格欄位: Total Event \nRisk Event Counts on Weak Authentication\nCount\n表格內容:\n  Total Event \nRisk Event Counts on Weak Authentication\nCount: Microsoft Entra ID Account with Weak Sign-In Security Policy - MFA Disabled\n  Total Event \nRisk Event Counts on Weak Authentication\nCount: Microsoft Entra ID Account with Weak Sign-In Security Policy - Password Expiration Disabled\n  Total Event \nRisk Event Counts on Weak Authentication\nCount: On-Premises AD Account with Weak Sign-In Security Policy - Password Not Required\n  Total Event \nRisk Event Counts on Weak Authentication\nCount: Microsoft Entra ID Account with Weak Sign-In Security Policy - Strong Password Disabled\n搜尋關鍵字: 比較, 對比, 分析, Total Event \nRisk Event Counts on Weak Authentication\nCount, 1,011,628,400, 606,548,251, 413,916,224",
      "metadata": {
        "original_table_data": {
          "title": "Camelot_Table_15_3",
          "headers": [
            "Total Event \nRisk Event Counts on Weak Authentication\nCount",
            ""
          ],
          "rows": [
            [
              "Microsoft Entra ID Account with Weak Sign-In Security Policy - MFA Disabled",
              "1,011,628,400"
            ],
            [
              "Microsoft Entra ID Account with Weak Sign-In Security Policy - Password Expiration Disabled",
              "606,548,251"
            ],
            [
              "On-Premises AD Account with Weak Sign-In Security Policy - Password Not Required",
              "413,916,224"
            ],
            [
              "Microsoft Entra ID Account with Weak Sign-In Security Policy - Strong Password Disabled",
              "389,998,623"
            ]
          ],
          "source_page": 15,
          "source_file": "data/source/Research-Risk-Report-2025.pdf",
          "table_type": "comparison",
          "confidence": 100.00000000000001,
          "extractor_method": "camelot",
          "metadata": {
            "whitespace": 10.0,
            "order": 1,
            "flavor": "lattice"
          }
        },
        "source_page": 15,
        "source_file": "data/source/Research-Risk-Report-2025.pdf",
        "table_type": "comparison",
        "confidence": 100.00000000000001,
        "extractor_method": "camelot",
        "conversion_date": "2025-07-18T10:36:09.156529"
      }
    },
    {
      "table_id": "table_4_Camelot_Table_15_4",
      "content": "表格標題: Camelot_Table_15_4\n表格類型: comparison\n來源頁面: 第15頁\n資料提取方法: camelot\n信心度: 100.0%\n表格欄位: Top Detected XDR Model Hits\n表格內容:\n  Top Detected XDR Model Hits: 1\n  Top Detected XDR Model Hits: 2\n  Top Detected XDR Model Hits: 3\n  Top Detected XDR Model Hits: 4\n  Top Detected XDR Model Hits: 5\n搜尋關鍵字: 比較, 對比, 分析, Top Detected XDR Model Hits",
      "metadata": {
        "original_table_data": {
          "title": "Camelot_Table_15_4",
          "headers": [
            "Top Detected XDR Model Hits",
            ""
          ],
          "rows": [
            [
              "1",
              "Possible OS Credential Dumping*"
            ],
            [
              "2",
              "Possible Data Encrypted for Impact*"
            ],
            [
              "3",
              "Behavior Monitoring Detection for Built-in Windows Tools"
            ],
            [
              "4",
              "Impair Defenses*"
            ],
            [
              "5",
              "Hacking Tool Detection"
            ]
          ],
          "source_page": 15,
          "source_file": "data/source/Research-Risk-Report-2025.pdf",
          "table_type": "comparison",
          "confidence": 100.00000000000001,
          "extractor_method": "camelot",
          "metadata": {
            "whitespace": 8.333333333333332,
            "order": 2,
            "flavor": "lattice"
          }
        },
        "source_page": 15,
        "source_file": "data/source/Research-Risk-Report-2025.pdf",
        "table_type": "comparison",
        "confidence": 100.00000000000001,
        "extractor_method": "camelot",
        "conversion_date": "2025-07-18T10:36:09.156555"
      }
    },
    {
      "table_id": "table_5_Camelot_Table_16_5",
      "content": "表格標題: Camelot_Table_16_5\n表格類型: comparison\n來源頁面: 第16頁\n資料提取方法: camelot\n信心度: 100.0%\n表格欄位: Top Detected XDR Model Hits\n表格內容:\n  Top Detected XDR Model Hits: 6\n  Top Detected XDR Model Hits: 7\n  Top Detected XDR Model Hits: 8\n  Top Detected XDR Model Hits: 9\n  Top Detected XDR Model Hits: 10\n搜尋關鍵字: 比較, 對比, 分析, Top Detected XDR Model Hits",
      "metadata": {
        "original_table_data": {
          "title": "Camelot_Table_16_5",
          "headers": [
            "Top Detected XDR Model Hits",
            ""
          ],
          "rows": [
            [
              "6",
              "Targeted Attack Detection"
            ],
            [
              "7",
              "Remote Code Execution via HTTP"
            ],
            [
              "8",
              "Possible Malicious Activity via System Services*"
            ],
            [
              "9",
              "System Binary Proxy Execution*"
            ],
            [
              "10",
              "Webshell Detection"
            ]
          ],
          "source_page": 16,
          "source_file": "data/source/Research-Risk-Report-2025.pdf",
          "table_type": "comparison",
          "confidence": 100.00000000000001,
          "extractor_method": "camelot",
          "metadata": {
            "whitespace": 8.333333333333332,
            "order": 1,
            "flavor": "lattice"
          }
        },
        "source_page": 16,
        "source_file": "data/source/Research-Risk-Report-2025.pdf",
        "table_type": "comparison",
        "confidence": 100.00000000000001,
        "extractor_method": "camelot",
        "conversion_date": "2025-07-18T10:36:09.156577"
      }
    },
    {
      "table_id": "table_6_Camelot_Table_17_6",
      "content": "表格標題: Camelot_Table_17_6\n表格類型: comparison\n來源頁面: 第17頁\n資料提取方法: camelot\n信心度: 100.0%\n表格欄位: Maximum \nOverall Top Vision One Misconfigurations\nRisk Score\n表格內容:\n  Maximum \nOverall Top Vision One Misconfigurations\nRisk Score: 1\n  Maximum \nOverall Top Vision One Misconfigurations\nRisk Score: 2\n  Maximum \nOverall Top Vision One Misconfigurations\nRisk Score: 3\n  Maximum \nOverall Top Vision One Misconfigurations\nRisk Score: 4\n  Maximum \nOverall Top Vision One Misconfigurations\nRisk Score: 5\n  Maximum \nOverall Top Vision One Misconfigurations\nRisk Score: 6\n  Maximum \nOverall Top Vision One Misconfigurations\nRisk Score: 7\n  Maximum \nOverall Top Vision One Misconfigurations\nRisk Score: 8\n  Maximum \nOverall Top Vision One Misconfigurations\nRisk Score: 9\n  Maximum \nOverall Top Vision One Misconfigurations\nRisk Score: 10\n搜尋關鍵字: 比較, 對比, 分析, Maximum \nOverall Top Vision One Misconfigurations\nRisk Score, 69, 65, 56",
      "metadata": {
        "original_table_data": {
          "title": "Camelot_Table_17_6",
          "headers": [
            "Maximum \nOverall Top Vision One Misconfigurations\nRisk Score",
            "",
            ""
          ],
          "rows": [
            [
              "1",
              "Web Reputation Settings in Trend Vision One™ - Endpoint Security Not Optimized",
              "69"
            ],
            [
              "2",
              "Device Control Settings in Endpoint Security Not Optimized",
              "65"
            ],
            [
              "3",
              "Endpoint Security Not Supported",
              "56"
            ],
            [
              "4",
              "Predictive Machine Learning Settings in Endpoint Security Not Optimized",
              "69"
            ],
            [
              "5",
              "Smart Feedback Settings in Endpoint Security Not Optimized",
              "65"
            ],
            [
              "6",
              "Anti-Malware Scanning Settings in Endpoint Security Not Optimized",
              "68"
            ],
            [
              "7",
              "Firewall Settings in Endpoint Security Not Optimized",
              "59"
            ],
            [
              "8",
              "Behavior Monitoring Settings in Endpoint Security Not Optimized",
              "69"
            ],
            [
              "9",
              "Application Control Settings in Endpoint Security Not Optimized",
              "59"
            ],
            [
              "10",
              "Vulnerability Protection Settings in Endpoint Security Not Optimized",
              "65"
            ]
          ],
          "source_page": 17,
          "source_file": "data/source/Research-Risk-Report-2025.pdf",
          "table_type": "comparison",
          "confidence": 100.00000000000001,
          "extractor_method": "camelot",
          "metadata": {
            "whitespace": 6.0606060606060606,
            "order": 1,
            "flavor": "lattice"
          }
        },
        "source_page": 17,
        "source_file": "data/source/Research-Risk-Report-2025.pdf",
        "table_type": "comparison",
        "confidence": 100.00000000000001,
        "extractor_method": "camelot",
        "conversion_date": "2025-07-18T10:36:09.156610"
      }
    },
    {
      "table_id": "table_7_Camelot_Table_18_7",
      "content": "表格標題: Camelot_Table_18_7\n表格類型: comparison\n來源頁面: 第18頁\n資料提取方法: camelot\n信心度: 100.0%\n表格欄位: Overall Top Cloud Misconfigurations\n表格內容:\n  Overall Top Cloud Misconfigurations: 1\n  Overall Top Cloud Misconfigurations: 2\n  Overall Top Cloud Misconfigurations: 3\n  Overall Top Cloud Misconfigurations: 4\n  Overall Top Cloud Misconfigurations: 5\n  Overall Top Cloud Misconfigurations: 6\n  Overall Top Cloud Misconfigurations: 7\n  Overall Top Cloud Misconfigurations: 8\n  Overall Top Cloud Misconfigurations: 9\n搜尋關鍵字: 比較, 對比, 分析, Overall Top Cloud Misconfigurations",
      "metadata": {
        "original_table_data": {
          "title": "Camelot_Table_18_7",
          "headers": [
            "Overall Top Cloud Misconfigurations",
            ""
          ],
          "rows": [
            [
              "1",
              "Non-Compliant AWS Infrastructure Configuration"
            ],
            [
              "2",
              "Non-Compliant Azure Infrastructure Configuration"
            ],
            [
              "3",
              "Non-Compliant Amazon S3 Infrastructure Configuration (Access Control)"
            ],
            [
              "4",
              "Non-Compliant Amazon S3 Infrastructure Configuration (Common \nConfiguration)"
            ],
            [
              "5",
              "Non-Compliant Amazon S3 Infrastructure Configuration (Security \nConfiguration)"
            ],
            [
              "6",
              "Non-Compliant GCP Infrastructure Configuration"
            ],
            [
              "7",
              "Non-Compliant AWS Infrastructure Configuration Revealed by Amazon \nInspector Findings"
            ],
            [
              "8",
              "Non-Compliant Amazon S3 Infrastructure Configuration (Amazon Macie \nFindings)"
            ],
            [
              "9",
              "Non-Compliant Amazon S3 Infrastructure Configuration"
            ]
          ],
          "source_page": 18,
          "source_file": "data/source/Research-Risk-Report-2025.pdf",
          "table_type": "comparison",
          "confidence": 99.99999999999997,
          "extractor_method": "camelot",
          "metadata": {
            "whitespace": 5.0,
            "order": 1,
            "flavor": "lattice"
          }
        },
        "source_page": 18,
        "source_file": "data/source/Research-Risk-Report-2025.pdf",
        "table_type": "comparison",
        "confidence": 99.99999999999997,
        "extractor_method": "camelot",
        "conversion_date": "2025-07-18T10:36:09.156637"
      }
    },
    {
      "table_id": "table_8_Camelot_Table_20_8",
      "content": "表格標題: Camelot_Table_20_8\n表格類型: comparison\n來源頁面: 第20頁\n資料提取方法: camelot\n信心度: 100.0%\n表格欄位: Top Vision One \nTop Cloud Misconfigurations \nTop Risky Events in Europe \nTop XDR Model Hits in Europe \nmisconfigurations in Europe \nin Europe\n表格內容:\n  Top Vision One \nTop Cloud Misconfigurations \nTop Risky Events in Europe \nTop XDR Model Hits in Europe \nmisconfigurations in Europe \nin Europe: 1\n  Top Vision One \nTop Cloud Misconfigurations \nTop Risky Events in Europe \nTop XDR Model Hits in Europe \nmisconfigurations in Europe \nin Europe: 2\n  Top Vision One \nTop Cloud Misconfigurations \nTop Risky Events in Europe \nTop XDR Model Hits in Europe \nmisconfigurations in Europe \nin Europe: 3\n  Top Vision One \nTop Cloud Misconfigurations \nTop Risky Events in Europe \nTop XDR Model Hits in Europe \nmisconfigurations in Europe \nin Europe: 4\n  Top Vision One \nTop Cloud Misconfigurations \nTop Risky Events in Europe \nTop XDR Model Hits in Europe \nmisconfigurations in Europe \nin Europe: 5\n搜尋關鍵字: 比較, 對比, 分析, Top Vision One \nTop Cloud Misconfigurations \nTop Risky Events in Europe \nTop XDR Model Hits in Europe \nmisconfigurations in Europe \nin Europe",
      "metadata": {
        "original_table_data": {
          "title": "Camelot_Table_20_8",
          "headers": [
            "Top Vision One \nTop Cloud Misconfigurations \nTop Risky Events in Europe \nTop XDR Model Hits in Europe \nmisconfigurations in Europe \nin Europe",
            "",
            "",
            "",
            ""
          ],
          "rows": [
            [
              "1",
              "Risky Cloud App Access",
              "Possible Disabling of Antivirus \nSoftware",
              "Application Control Settings in \nTrend Vision One™ - Endpoint \nSecurity Not Optimized",
              "Non-Compliant AWS Infrastructure \nConfiguration"
            ],
            [
              "2",
              "Sandbox Detected Email Threat",
              "Hacking Tool Detection - Blocked",
              "Device Control Settings in \nEndpoint Security Not Optimized",
              "Non-Compliant Azure \nInfrastructure Configuration"
            ],
            [
              "3",
              "Stale Microsoft Entra ID Account",
              "Threat Intelligence Sweeping",
              "File Integrity Monitoring (FIM) \nSettings in Endpoint Security Not \nOptimized",
              "Non-Compliant Amazon S3 \nInfrastructure Configuration \n(Access Control)"
            ],
            [
              "4",
              "Advanced Spam Protection - \nPolicy Violation",
              "Possible Spear Phishing Attack via \nLink",
              "Log Inspection Settings in \nEndpoint Security Not Optimized",
              "Non-Compliant Amazon S3 \nInfrastructure Configuration \n(Common Configuration)"
            ],
            [
              "5",
              "On-Premises AD Account with \nWeak Sign-In Security Policy - \nPassword Expiration Disabled",
              "Suspicious Multiple Failed Logons \nvia Windows Event",
              "Firewall Settings in Endpoint \nSecurity Not Optimized",
              "Non-Compliant Amazon S3 \nInfrastructure Configuration \n(Security Configuration)"
            ]
          ],
          "source_page": 20,
          "source_file": "data/source/Research-Risk-Report-2025.pdf",
          "table_type": "comparison",
          "confidence": 99.99999999999989,
          "extractor_method": "camelot",
          "metadata": {
            "whitespace": 13.333333333333334,
            "order": 1,
            "flavor": "lattice"
          }
        },
        "source_page": 20,
        "source_file": "data/source/Research-Risk-Report-2025.pdf",
        "table_type": "comparison",
        "confidence": 99.99999999999989,
        "extractor_method": "camelot",
        "conversion_date": "2025-07-18T10:36:09.156666"
      }
    },
    {
      "table_id": "table_9_Camelot_Table_21_9",
      "content": "表格標題: Camelot_Table_21_9\n表格類型: comparison\n來源頁面: 第21頁\n資料提取方法: camelot\n信心度: 100.0%\n表格欄位: Top Vision One \nTop Cloud Misconfigurations \nTop Risky Events in AMEA \nTop XDR Model Hits in AMEA \nmisconfigurations in AMEA \nin AMEA\n表格內容:\n  Top Vision One \nTop Cloud Misconfigurations \nTop Risky Events in AMEA \nTop XDR Model Hits in AMEA \nmisconfigurations in AMEA \nin AMEA: 1\n  Top Vision One \nTop Cloud Misconfigurations \nTop Risky Events in AMEA \nTop XDR Model Hits in AMEA \nmisconfigurations in AMEA \nin AMEA: 2\n  Top Vision One \nTop Cloud Misconfigurations \nTop Risky Events in AMEA \nTop XDR Model Hits in AMEA \nmisconfigurations in AMEA \nin AMEA: 3\n  Top Vision One \nTop Cloud Misconfigurations \nTop Risky Events in AMEA \nTop XDR Model Hits in AMEA \nmisconfigurations in AMEA \nin AMEA: 4\n  Top Vision One \nTop Cloud Misconfigurations \nTop Risky Events in AMEA \nTop XDR Model Hits in AMEA \nmisconfigurations in AMEA \nin AMEA: 5\n搜尋關鍵字: 比較, 對比, 分析, Top Vision One \nTop Cloud Misconfigurations \nTop Risky Events in AMEA \nTop XDR Model Hits in AMEA \nmisconfigurations in AMEA \nin AMEA",
      "metadata": {
        "original_table_data": {
          "title": "Camelot_Table_21_9",
          "headers": [
            "Top Vision One \nTop Cloud Misconfigurations \nTop Risky Events in AMEA \nTop XDR Model Hits in AMEA \nmisconfigurations in AMEA \nin AMEA",
            "",
            "",
            "",
            ""
          ],
          "rows": [
            [
              "1",
              "Risky Cloud App Access",
              "Hacking Tool Detection - Blocked",
              "Web Reputation Settings in Trend \nVision One™ - Endpoint Security \nNot Optimized",
              "Non-Compliant AWS Infrastructure \nConfiguration"
            ],
            [
              "2",
              "Stale Microsoft Entra ID Account",
              "Possible Disabling of Antivirus \nSoftware",
              "Device Control Settings in \nEndpoint Security Not Optimized",
              "Non-Compliant Amazon S3 \nInfrastructure Configuration \n(Access Control)"
            ],
            [
              "3",
              "Sandbox Detected Email Threat",
              "Threat Intelligence Sweeping",
              "Behavior Monitoring Settings in \nEndpoint Security Not Optimized",
              "Non-Compliant Azure \nInfrastructure Configuration"
            ],
            [
              "4",
              "Microsoft Entra ID Account with \nWeak Sign-In Security Policy - \nMFA Disabled",
              "[Heuristic Attribute] Backdoor File \nDetection",
              "Predictive Machine Learning \nSettings in Endpoint Security Not \nOptimized",
              "Non-Compliant Amazon S3 \nInfrastructure Configuration \n(Common Configuration)"
            ],
            [
              "5",
              "Data Loss Prevention - Email \nViolation",
              "Unknown Threat Detection and \nMitigation via Predictive Machine \nLearning",
              "Endpoint Security Agent Not \nSupported",
              "Non-Compliant Amazon S3 \nInfrastructure Configuration \n(Security Configuration)"
            ]
          ],
          "source_page": 21,
          "source_file": "data/source/Research-Risk-Report-2025.pdf",
          "table_type": "comparison",
          "confidence": 100.00000000000003,
          "extractor_method": "camelot",
          "metadata": {
            "whitespace": 13.333333333333334,
            "order": 1,
            "flavor": "lattice"
          }
        },
        "source_page": 21,
        "source_file": "data/source/Research-Risk-Report-2025.pdf",
        "table_type": "comparison",
        "confidence": 100.00000000000003,
        "extractor_method": "camelot",
        "conversion_date": "2025-07-18T10:36:09.156694"
      }
    },
    {
      "table_id": "table_10_Camelot_Table_22_10",
      "content": "表格標題: Camelot_Table_22_10\n表格類型: comparison\n來源頁面: 第22頁\n資料提取方法: camelot\n信心度: 100.0%\n表格欄位: Top XDR Model Hits in \nTop Vision One \nTop Cloud Misconfigurations \nTop Risky Events in Americas \nAmericas \nmisconfigurations in Americas \nin Americas\n表格內容:\n  Top XDR Model Hits in \nTop Vision One \nTop Cloud Misconfigurations \nTop Risky Events in Americas \nAmericas \nmisconfigurations in Americas \nin Americas: 1\n  Top XDR Model Hits in \nTop Vision One \nTop Cloud Misconfigurations \nTop Risky Events in Americas \nAmericas \nmisconfigurations in Americas \nin Americas: 2\n  Top XDR Model Hits in \nTop Vision One \nTop Cloud Misconfigurations \nTop Risky Events in Americas \nAmericas \nmisconfigurations in Americas \nin Americas: 3\n  Top XDR Model Hits in \nTop Vision One \nTop Cloud Misconfigurations \nTop Risky Events in Americas \nAmericas \nmisconfigurations in Americas \nin Americas: 4\n  Top XDR Model Hits in \nTop Vision One \nTop Cloud Misconfigurations \nTop Risky Events in Americas \nAmericas \nmisconfigurations in Americas \nin Americas: 5\n搜尋關鍵字: 比較, 對比, 分析, Top XDR Model Hits in \nTop Vision One \nTop Cloud Misconfigurations \nTop Risky Events in Americas \nAmericas \nmisconfigurations in Americas \nin Americas",
      "metadata": {
        "original_table_data": {
          "title": "Camelot_Table_22_10",
          "headers": [
            "Top XDR Model Hits in \nTop Vision One \nTop Cloud Misconfigurations \nTop Risky Events in Americas \nAmericas \nmisconfigurations in Americas \nin Americas",
            "",
            "",
            "",
            ""
          ],
          "rows": [
            [
              "1",
              "Risky Cloud App Access",
              "Threat Intelligence Sweeping",
              "Web Reputation Settings in Trend \nVision One™ - Endpoint Security \nNot Optimized",
              "Non-Compliant AWS Infrastructure \nConfiguration"
            ],
            [
              "2",
              "Stale Microsoft Entra ID Account",
              "Possible Disabling of Antivirus \nSoftware",
              "Endpoint Security Agent Not \nSupported",
              "Non-Compliant Azure \nInfrastructure Configuration"
            ],
            [
              "3",
              "Sandbox Detected Email Threat",
              "Hacking Tool Detection - Blocked",
              "Device Control Settings in \nEndpoint Security Not Optimized",
              "Non-Compliant Amazon S3 \nInfrastructure Configuration \n(Access Control)"
            ],
            [
              "4",
              "Microsoft Entra ID Account with \nWeak Sign-In Security Policy - \nPassword Expiration Disabled",
              "Unknown Threat Detection and \nMitigation via Predictive Machine \nLearning",
              "Predictive Machine Learning \nSettings in Endpoint Security Not \nOptimized",
              "Non-Compliant Amazon S3 \nInfrastructure Configuration \n(Common Configuration)"
            ],
            [
              "5",
              "Advanced Spam Protection - \nPolicy Violation",
              "Possible Spear Phishing Attack via \nLink",
              "Smart Feedback Settings in \nEndpoint Security Not Optimized",
              "Non-Compliant Amazon S3 \nInfrastructure Configuration \n(Security Configuration)"
            ]
          ],
          "source_page": 22,
          "source_file": "data/source/Research-Risk-Report-2025.pdf",
          "table_type": "comparison",
          "confidence": 99.99999999999996,
          "extractor_method": "camelot",
          "metadata": {
            "whitespace": 13.333333333333334,
            "order": 1,
            "flavor": "lattice"
          }
        },
        "source_page": 22,
        "source_file": "data/source/Research-Risk-Report-2025.pdf",
        "table_type": "comparison",
        "confidence": 99.99999999999996,
        "extractor_method": "camelot",
        "conversion_date": "2025-07-18T10:36:09.156728"
      }
    },
    {
      "table_id": "table_11_Camelot_Table_23_11",
      "content": "表格標題: Camelot_Table_23_11\n表格類型: comparison\n來源頁面: 第23頁\n資料提取方法: camelot\n信心度: 100.0%\n表格欄位: Top Vision One \nTop Cloud Misconfigurations \nTop Risky Events in the \nTop XDR Model Hits in the \nmisconfigurations in the \nin the Agriculture Sector\nAgriculture sector \nAgriculture Sector \nAgriculture Sector\n表格內容:\n  Top Vision One \nTop Cloud Misconfigurations \nTop Risky Events in the \nTop XDR Model Hits in the \nmisconfigurations in the \nin the Agriculture Sector\nAgriculture sector \nAgriculture Sector \nAgriculture Sector: 1\n  Top Vision One \nTop Cloud Misconfigurations \nTop Risky Events in the \nTop XDR Model Hits in the \nmisconfigurations in the \nin the Agriculture Sector\nAgriculture sector \nAgriculture Sector \nAgriculture Sector: 2\n  Top Vision One \nTop Cloud Misconfigurations \nTop Risky Events in the \nTop XDR Model Hits in the \nmisconfigurations in the \nin the Agriculture Sector\nAgriculture sector \nAgriculture Sector \nAgriculture Sector: 3\n  Top Vision One \nTop Cloud Misconfigurations \nTop Risky Events in the \nTop XDR Model Hits in the \nmisconfigurations in the \nin the Agriculture Sector\nAgriculture sector \nAgriculture Sector \nAgriculture Sector: 4\n  Top Vision One \nTop Cloud Misconfigurations \nTop Risky Events in the \nTop XDR Model Hits in the \nmisconfigurations in the \nin the Agriculture Sector\nAgriculture sector \nAgriculture Sector \nAgriculture Sector: 5\n搜尋關鍵字: 比較, 對比, 分析, Top Vision One \nTop Cloud Misconfigurations \nTop Risky Events in the \nTop XDR Model Hits in the \nmisconfigurations in the \nin the Agriculture Sector\nAgriculture sector \nAgriculture Sector \nAgriculture Sector",
      "metadata": {
        "original_table_data": {
          "title": "Camelot_Table_23_11",
          "headers": [
            "Top Vision One \nTop Cloud Misconfigurations \nTop Risky Events in the \nTop XDR Model Hits in the \nmisconfigurations in the \nin the Agriculture Sector\nAgriculture sector \nAgriculture Sector \nAgriculture Sector",
            "",
            "",
            "",
            ""
          ],
          "rows": [
            [
              "1",
              "Risky Cloud App Access",
              "Threat Intelligence Sweeping",
              "Web Reputation Settings in Trend \nVision One™ - Endpoint Security \nNot Optimized",
              "Non-Compliant AWS Infrastructure \nConfiguration"
            ],
            [
              "2",
              "Data Loss Prevention - Email \nViolation",
              "Hacking Tool Detection - Blocked",
              "Intrusion Prevention System (IPS) \nSettings in Endpoint Security Not \nOptimized",
              "Non-Compliant Azure \nInfrastructure Configuration"
            ],
            [
              "3",
              "Advanced Spam Protection - \nPolicy Violation",
              "Cybercrime Malware Mitigation",
              "Anti-Malware Settings in Endpoint \nSecurity Not Optimized",
              "Non-Compliant Amazon S3 \nInfrastructure Configuration \n(Access Control)"
            ],
            [
              "4",
              "Stale Microsoft Entra ID Account",
              "Possible Disabling of Antivirus \nSoftware",
              "Web Reputation Settings in \nEndpoint Security Not Optimized",
              "Non-Compliant Amazon S3 \nInfrastructure Configuration \n(Common Configuration)"
            ],
            [
              "5",
              "Microsoft Entra ID Account with \nWeak Sign-In Security Policy - \nMFA Disabled",
              "Possible Spear Phishing Attack via \nLink",
              "Agent Self-Protection Settings in \nEndpoint Security Not Optimized",
              "Non-Compliant Amazon S3 \nInfrastructure Configuration \n(Security Configuration)"
            ]
          ],
          "source_page": 23,
          "source_file": "data/source/Research-Risk-Report-2025.pdf",
          "table_type": "comparison",
          "confidence": 99.99999999999991,
          "extractor_method": "camelot",
          "metadata": {
            "whitespace": 13.333333333333334,
            "order": 1,
            "flavor": "lattice"
          }
        },
        "source_page": 23,
        "source_file": "data/source/Research-Risk-Report-2025.pdf",
        "table_type": "comparison",
        "confidence": 99.99999999999991,
        "extractor_method": "camelot",
        "conversion_date": "2025-07-18T10:36:09.156755"
      }
    },
    {
      "table_id": "table_12_Camelot_Table_24_12",
      "content": "表格標題: Camelot_Table_24_12\n表格類型: comparison\n來源頁面: 第24頁\n資料提取方法: camelot\n信心度: 100.0%\n表格欄位: Top Cloud Misconfigurations \nTop Vision One \nTop Risky Events in the \nTop XDR Model Hits in the \nin the Communications \nmisconfigurations in the \nCommunications Industry \nCommunication Industry \nIndustry\nCommunication Industry\n表格內容:\n  Top Cloud Misconfigurations \nTop Vision One \nTop Risky Events in the \nTop XDR Model Hits in the \nin the Communications \nmisconfigurations in the \nCommunications Industry \nCommunication Industry \nIndustry\nCommunication Industry: 1\n  Top Cloud Misconfigurations \nTop Vision One \nTop Risky Events in the \nTop XDR Model Hits in the \nin the Communications \nmisconfigurations in the \nCommunications Industry \nCommunication Industry \nIndustry\nCommunication Industry: 2\n  Top Cloud Misconfigurations \nTop Vision One \nTop Risky Events in the \nTop XDR Model Hits in the \nin the Communications \nmisconfigurations in the \nCommunications Industry \nCommunication Industry \nIndustry\nCommunication Industry: 3\n  Top Cloud Misconfigurations \nTop Vision One \nTop Risky Events in the \nTop XDR Model Hits in the \nin the Communications \nmisconfigurations in the \nCommunications Industry \nCommunication Industry \nIndustry\nCommunication Industry: 4\n  Top Cloud Misconfigurations \nTop Vision One \nTop Risky Events in the \nTop XDR Model Hits in the \nin the Communications \nmisconfigurations in the \nCommunications Industry \nCommunication Industry \nIndustry\nCommunication Industry: 5\n搜尋關鍵字: 比較, 對比, 分析, Top Cloud Misconfigurations \nTop Vision One \nTop Risky Events in the \nTop XDR Model Hits in the \nin the Communications \nmisconfigurations in the \nCommunications Industry \nCommunication Industry \nIndustry\nCommunication Industry",
      "metadata": {
        "original_table_data": {
          "title": "Camelot_Table_24_12",
          "headers": [
            "Top Cloud Misconfigurations \nTop Vision One \nTop Risky Events in the \nTop XDR Model Hits in the \nin the Communications \nmisconfigurations in the \nCommunications Industry \nCommunication Industry \nIndustry\nCommunication Industry",
            "",
            "",
            "",
            ""
          ],
          "rows": [
            [
              "1",
              "Sandbox Detected Email Threat",
              "Possible Disabling of Antivirus \nSoftware",
              "Application Control Settings in \nTrend Vision One™ - Endpoint \nSecurity Not Optimized",
              "Non-Compliant AWS Infrastructure \nConfiguration"
            ],
            [
              "2",
              "Risky Cloud App Access",
              "Hacking Tool Detection - Blocked",
              "Intrusion Prevention System (IPS) \nSettings in Endpoint Security Not \nOptimized",
              "Non-Compliant Azure \nInfrastructure Configuration"
            ],
            [
              "3",
              "Data Loss Prevention - Email \nViolation",
              "Threat Intelligence Sweeping",
              "Log Inspection Settings in \nEndpoint Security Not Optimized",
              "Non-Compliant Amazon S3 \nInfrastructure Configuration \n(Access Control)"
            ],
            [
              "4",
              "Stale Microsoft Entra ID Account",
              "Unknown Threat Detection and \nMitigation via Predictive Machine \nLearning",
              "Activity Monitoring Settings in \nEndpoint Security Not Optimized",
              "Non-Compliant Amazon S3 \nInfrastructure Configuration \n(Common Configuration)"
            ],
            [
              "5",
              "Advanced Spam Protection - \nPolicy Violation",
              "[Heuristic Attribute] Possible Data \nEncrypted for Impact",
              "Web Reputation Settings in \nEndpoint Security Not Optimized",
              "Non-Compliant Amazon S3 \nInfrastructure Configuration \n(Security Configuration)"
            ]
          ],
          "source_page": 24,
          "source_file": "data/source/Research-Risk-Report-2025.pdf",
          "table_type": "comparison",
          "confidence": 100.0000000000001,
          "extractor_method": "camelot",
          "metadata": {
            "whitespace": 13.333333333333334,
            "order": 1,
            "flavor": "lattice"
          }
        },
        "source_page": 24,
        "source_file": "data/source/Research-Risk-Report-2025.pdf",
        "table_type": "comparison",
        "confidence": 100.0000000000001,
        "extractor_method": "camelot",
        "conversion_date": "2025-07-18T10:36:09.156784"
      }
    },
    {
      "table_id": "table_13_Camelot_Table_25_13",
      "content": "表格標題: Camelot_Table_25_13\n表格類型: comparison\n來源頁面: 第25頁\n資料提取方法: camelot\n信心度: 100.0%\n表格欄位: Top Vision One \nTop Cloud Misconfigurations \nTop Risky Events in the \nTop XDR Model Hits in the \nmisconfigurations in the \nin the Education Sector \nEducation Sector \nEducation Sector \nEducation Sector\n表格內容:\n  Top Vision One \nTop Cloud Misconfigurations \nTop Risky Events in the \nTop XDR Model Hits in the \nmisconfigurations in the \nin the Education Sector \nEducation Sector \nEducation Sector \nEducation Sector: 1\n  Top Vision One \nTop Cloud Misconfigurations \nTop Risky Events in the \nTop XDR Model Hits in the \nmisconfigurations in the \nin the Education Sector \nEducation Sector \nEducation Sector \nEducation Sector: 2\n  Top Vision One \nTop Cloud Misconfigurations \nTop Risky Events in the \nTop XDR Model Hits in the \nmisconfigurations in the \nin the Education Sector \nEducation Sector \nEducation Sector \nEducation Sector: 3\n  Top Vision One \nTop Cloud Misconfigurations \nTop Risky Events in the \nTop XDR Model Hits in the \nmisconfigurations in the \nin the Education Sector \nEducation Sector \nEducation Sector \nEducation Sector: 4\n  Top Vision One \nTop Cloud Misconfigurations \nTop Risky Events in the \nTop XDR Model Hits in the \nmisconfigurations in the \nin the Education Sector \nEducation Sector \nEducation Sector \nEducation Sector: 5\n搜尋關鍵字: 比較, 對比, 分析, Top Vision One \nTop Cloud Misconfigurations \nTop Risky Events in the \nTop XDR Model Hits in the \nmisconfigurations in the \nin the Education Sector \nEducation Sector \nEducation Sector \nEducation Sector",
      "metadata": {
        "original_table_data": {
          "title": "Camelot_Table_25_13",
          "headers": [
            "Top Vision One \nTop Cloud Misconfigurations \nTop Risky Events in the \nTop XDR Model Hits in the \nmisconfigurations in the \nin the Education Sector \nEducation Sector \nEducation Sector \nEducation Sector",
            "",
            "",
            "",
            ""
          ],
          "rows": [
            [
              "1",
              "Stale Microsoft Entra ID Account",
              "Threat Intelligence Sweeping",
              "Endpoint Sensor Settings in Trend \nVision One™ - Endpoint Security \nNot Optimized",
              "Non-Compliant AWS Infrastructure \nConfiguration"
            ],
            [
              "2",
              "Risky Cloud App Access",
              "Hacking Tool Detection - Blocked",
              "Anti-Malware Scanning Settings in \nEndpoint Security Not Optimized",
              "Non-Compliant Azure \nInfrastructure Configuration"
            ],
            [
              "3",
              "Microsoft Entra ID Account with \nWeak Sign-In Security Policy - \nPassword Expiration Disabled",
              "Possible Disabling of Antivirus \nSoftware",
              "Endpoint Security Agent Not \nSupported",
              "Non-Compliant Amazon S3 \nInfrastructure Configuration \n(Access Control)"
            ],
            [
              "4",
              "Microsoft Entra ID Account with \nWeak Sign-In Security Policy - \nStrong Password Disabled",
              "[Heuristic Attribute] Backdoor File \nDetection",
              "Web Reputation Settings in \nEndpoint Security Not Optimized",
              "Non-Compliant Amazon S3 \nInfrastructure Configuration \n(Common Configuration)"
            ],
            [
              "5",
              "On-Premises AD Account with \nWeak Sign-In Security Policy - \nPassword Expiration Disabled",
              "Cybercrime Malware Mitigation",
              "Predictive Machine Learning \nSettings in Endpoint Security Not \nOptimized",
              "Non-Compliant Amazon S3 \nInfrastructure Configuration \n(Security Configuration)"
            ]
          ],
          "source_page": 25,
          "source_file": "data/source/Research-Risk-Report-2025.pdf",
          "table_type": "comparison",
          "confidence": 99.99999999999986,
          "extractor_method": "camelot",
          "metadata": {
            "whitespace": 13.333333333333334,
            "order": 1,
            "flavor": "lattice"
          }
        },
        "source_page": 25,
        "source_file": "data/source/Research-Risk-Report-2025.pdf",
        "table_type": "comparison",
        "confidence": 99.99999999999986,
        "extractor_method": "camelot",
        "conversion_date": "2025-07-18T10:36:09.156810"
      }
    },
    {
      "table_id": "table_14_Camelot_Table_26_14",
      "content": "表格標題: Camelot_Table_26_14\n表格類型: comparison\n來源頁面: 第26頁\n資料提取方法: camelot\n信心度: 100.0%\n表格欄位: Top Vision One \nTop Cloud Misconfigurations \nTop Risky Events in the \nTop XDR Model Hits in the \nmisconfigurations in the \nin the Energy Sector \nEnergy Sector \nEnergy Sector \nEnergy Sector\n表格內容:\n  Top Vision One \nTop Cloud Misconfigurations \nTop Risky Events in the \nTop XDR Model Hits in the \nmisconfigurations in the \nin the Energy Sector \nEnergy Sector \nEnergy Sector \nEnergy Sector: 1\n  Top Vision One \nTop Cloud Misconfigurations \nTop Risky Events in the \nTop XDR Model Hits in the \nmisconfigurations in the \nin the Energy Sector \nEnergy Sector \nEnergy Sector \nEnergy Sector: 2\n  Top Vision One \nTop Cloud Misconfigurations \nTop Risky Events in the \nTop XDR Model Hits in the \nmisconfigurations in the \nin the Energy Sector \nEnergy Sector \nEnergy Sector \nEnergy Sector: 3\n  Top Vision One \nTop Cloud Misconfigurations \nTop Risky Events in the \nTop XDR Model Hits in the \nmisconfigurations in the \nin the Energy Sector \nEnergy Sector \nEnergy Sector \nEnergy Sector: 4\n  Top Vision One \nTop Cloud Misconfigurations \nTop Risky Events in the \nTop XDR Model Hits in the \nmisconfigurations in the \nin the Energy Sector \nEnergy Sector \nEnergy Sector \nEnergy Sector: 5\n搜尋關鍵字: 比較, 對比, 分析, Top Vision One \nTop Cloud Misconfigurations \nTop Risky Events in the \nTop XDR Model Hits in the \nmisconfigurations in the \nin the Energy Sector \nEnergy Sector \nEnergy Sector \nEnergy Sector",
      "metadata": {
        "original_table_data": {
          "title": "Camelot_Table_26_14",
          "headers": [
            "Top Vision One \nTop Cloud Misconfigurations \nTop Risky Events in the \nTop XDR Model Hits in the \nmisconfigurations in the \nin the Energy Sector \nEnergy Sector \nEnergy Sector \nEnergy Sector",
            "",
            "",
            "",
            ""
          ],
          "rows": [
            [
              "1",
              "Sandbox Detected Email Threat",
              "Hacking Tool Detection - Blocked",
              "Behavior Monitoring Settings in \nTrend Vision One™ - Endpoint \nSecurity Not Optimized",
              "Non-Compliant AWS Infrastructure \nConfiguration"
            ],
            [
              "2",
              "Risky Cloud App Access",
              "Possible Disabling of Antivirus \nSoftware",
              "Predictive Machine Learning \nSettings in Endpoint Security Not \nOptimized",
              "Non-Compliant Azure \nInfrastructure Configuration"
            ],
            [
              "3",
              "Stale Microsoft Entra ID Account",
              "[Heuristic Attribute] Trojan Spy \nFile Detection",
              "Firewall Settings in Endpoint \nSecurity Not Optimized",
              "Non-Compliant Amazon S3 \nInfrastructure Configuration \n(Access Control)"
            ],
            [
              "4",
              "Sandbox Detected Cloud App Risk",
              "Unknown Threat Detection and \nMitigation via Predictive Machine \nLearning",
              "Suspicious Connection Service \nSettings in Endpoint Security Not \nOptimized",
              "Non-Compliant Amazon S3 \nInfrastructure Configuration \n(Common Configuration)"
            ],
            [
              "5",
              "Advanced Spam Protection - \nPolicy Violation",
              "Threat Intelligence Sweeping",
              "Smart Feedback Settings in \nEndpoint Security Not Optimized",
              "Non-Compliant Amazon S3 \nInfrastructure Configuration \n(Security Configuration)"
            ]
          ],
          "source_page": 26,
          "source_file": "data/source/Research-Risk-Report-2025.pdf",
          "table_type": "comparison",
          "confidence": 99.99999999999991,
          "extractor_method": "camelot",
          "metadata": {
            "whitespace": 13.333333333333334,
            "order": 1,
            "flavor": "lattice"
          }
        },
        "source_page": 26,
        "source_file": "data/source/Research-Risk-Report-2025.pdf",
        "table_type": "comparison",
        "confidence": 99.99999999999991,
        "extractor_method": "camelot",
        "conversion_date": "2025-07-18T10:36:09.156843"
      }
    },
    {
      "table_id": "table_15_Camelot_Table_27_15",
      "content": "表格標題: Camelot_Table_27_15\n表格類型: comparison\n來源頁面: 第27頁\n資料提取方法: camelot\n信心度: 100.0%\n表格欄位: Top Vision One \nTop Cloud Misconfigurations \nTop Risky Events in the \n \nTop XDR Model Hits in the \nmisconfigurations in the \nin the Insurance Industry \nInsurance Industry \nInsurance Industry \nInsurance Industry\n表格內容:\n  Top Vision One \nTop Cloud Misconfigurations \nTop Risky Events in the \n \nTop XDR Model Hits in the \nmisconfigurations in the \nin the Insurance Industry \nInsurance Industry \nInsurance Industry \nInsurance Industry: 1\n  Top Vision One \nTop Cloud Misconfigurations \nTop Risky Events in the \n \nTop XDR Model Hits in the \nmisconfigurations in the \nin the Insurance Industry \nInsurance Industry \nInsurance Industry \nInsurance Industry: 2\n  Top Vision One \nTop Cloud Misconfigurations \nTop Risky Events in the \n \nTop XDR Model Hits in the \nmisconfigurations in the \nin the Insurance Industry \nInsurance Industry \nInsurance Industry \nInsurance Industry: 3\n  Top Vision One \nTop Cloud Misconfigurations \nTop Risky Events in the \n \nTop XDR Model Hits in the \nmisconfigurations in the \nin the Insurance Industry \nInsurance Industry \nInsurance Industry \nInsurance Industry: 4\n  Top Vision One \nTop Cloud Misconfigurations \nTop Risky Events in the \n \nTop XDR Model Hits in the \nmisconfigurations in the \nin the Insurance Industry \nInsurance Industry \nInsurance Industry \nInsurance Industry: 5\n搜尋關鍵字: 比較, 對比, 分析, Top Vision One \nTop Cloud Misconfigurations \nTop Risky Events in the \n \nTop XDR Model Hits in the \nmisconfigurations in the \nin the Insurance Industry \nInsurance Industry \nInsurance Industry \nInsurance Industry",
      "metadata": {
        "original_table_data": {
          "title": "Camelot_Table_27_15",
          "headers": [
            "Top Vision One \nTop Cloud Misconfigurations \nTop Risky Events in the \n \nTop XDR Model Hits in the \nmisconfigurations in the \nin the Insurance Industry \nInsurance Industry \nInsurance Industry \nInsurance Industry",
            "",
            "",
            "",
            ""
          ],
          "rows": [
            [
              "1",
              "Risky Cloud App Access",
              "Possible Disabling of Antivirus \nSoftware",
              "Anti-Malware Scanning Settings \nin Trend Vision One™ - Endpoint \nSecurity Not Optimized",
              "Non-Compliant AWS Infrastructure \nConfiguration"
            ],
            [
              "2",
              "Microsoft Entra ID Account with \nWeak Sign-In Security Policy - \nMFA Disabled",
              "Hacking Tool Detection",
              "Application Control Settings in \nEndpoint Security Not Optimized",
              "Non-Compliant Azure \nInfrastructure Configuration"
            ],
            [
              "3",
              "Sandbox Detected Email Threat",
              "Threat Intelligence Sweeping",
              "Device Control Settings in \nEndpoint Security Not Optimized",
              "Non-Compliant Amazon S3 \nInfrastructure Configuration \n(Access Control)"
            ],
            [
              "4",
              "On-Premises AD Account with \nWeak Sign-In Security Policy - \nPassword Not Required",
              "Unknown Threat Detection and \nMitigation via Predictive Machine \nLearning",
              "Smart Feedback Settings in \nEndpoint Security Not Optimized",
              "Non-Compliant Amazon S3 \nInfrastructure Configuration \n(Common Configuration)"
            ],
            [
              "5",
              "Stale Microsoft Entra ID Account",
              "Possible Spear Phishing Attack via \nLink",
              "Suspicious Connection Service \nSettings in Endpoint Security Not \nOptimized",
              "Non-Compliant GCP Infrastructure \nConfiguration"
            ]
          ],
          "source_page": 27,
          "source_file": "data/source/Research-Risk-Report-2025.pdf",
          "table_type": "comparison",
          "confidence": 99.99999999999986,
          "extractor_method": "camelot",
          "metadata": {
            "whitespace": 13.333333333333334,
            "order": 1,
            "flavor": "lattice"
          }
        },
        "source_page": 27,
        "source_file": "data/source/Research-Risk-Report-2025.pdf",
        "table_type": "comparison",
        "confidence": 99.99999999999986,
        "extractor_method": "camelot",
        "conversion_date": "2025-07-18T10:36:09.156869"
      }
    },
    {
      "table_id": "table_16_Camelot_Table_28_16",
      "content": "表格標題: Camelot_Table_28_16\n表格類型: comparison\n來源頁面: 第28頁\n資料提取方法: camelot\n信心度: 100.0%\n表格欄位: Rule name\nRule ID\n表格內容:\n  Rule name\nRule ID: RDP Brute Force Login\n  Rule name\nRule ID: MISC Bitcoin/LiteCoin/Dogecoin Mining Activity -1\n  Rule name\nRule ID: WEB Hikvision Product Web Server Command Injection -1.1 (CVE-2021-36260)\n  Rule name\nRule ID: TELNET Default Password Login -6\n  Rule name\nRule ID: WEB HTTP Invalid Content-Length -2\n  Rule name\nRule ID: MISC Cryptocurrency Monero Mining Activity -1\n  Rule name\nRule ID: SSH Brute Force Login\n  Rule name\nRule ID: WEB Remote Command Execution via Shell Script -1.h\n  Rule name\nRule ID: SMB Microsoft Windows SMB Server SMBv1 CVE-2017-0147 Information Disclosure -1\n  Rule name\nRule ID: MALWARE Suspicious IoT Worm TELNET Activity -1\n搜尋關鍵字: 比較, 對比, 分析, Rule name\nRule ID, 1059803, 1059684, 1139937",
      "metadata": {
        "original_table_data": {
          "title": "Camelot_Table_28_16",
          "headers": [
            "Rule name\nRule ID",
            ""
          ],
          "rows": [
            [
              "RDP Brute Force Login",
              "1059803"
            ],
            [
              "MISC Bitcoin/LiteCoin/Dogecoin Mining Activity -1",
              "1059684"
            ],
            [
              "WEB Hikvision Product Web Server Command Injection -1.1 (CVE-2021-36260)",
              "1139937"
            ],
            [
              "TELNET Default Password Login -6",
              "1133113"
            ],
            [
              "WEB HTTP Invalid Content-Length -2",
              "1139797"
            ],
            [
              "MISC Cryptocurrency Monero Mining Activity -1",
              "1134390"
            ],
            [
              "SSH Brute Force Login",
              "1059418"
            ],
            [
              "WEB Remote Command Execution via Shell Script -1.h",
              "1133253"
            ],
            [
              "SMB Microsoft Windows SMB Server SMBv1 CVE-2017-0147 Information Disclosure -1",
              "1133710"
            ],
            [
              "MALWARE Suspicious IoT Worm TELNET Activity -1",
              "1133148"
            ]
          ],
          "source_page": 28,
          "source_file": "data/source/Research-Risk-Report-2025.pdf",
          "table_type": "comparison",
          "confidence": 100.00000000000001,
          "extractor_method": "camelot",
          "metadata": {
            "whitespace": 4.545454545454546,
            "order": 1,
            "flavor": "lattice"
          }
        },
        "source_page": 28,
        "source_file": "data/source/Research-Risk-Report-2025.pdf",
        "table_type": "comparison",
        "confidence": 100.00000000000001,
        "extractor_method": "camelot",
        "conversion_date": "2025-07-18T10:36:09.156911"
      }
    },
    {
      "table_id": "table_17_Camelot_Table_31_17",
      "content": "表格標題: Camelot_Table_31_17\n表格類型: comparison\n來源頁面: 第31頁\n資料提取方法: camelot\n信心度: 100.0%\n表格欄位: Top riskiest CVEs, most \nNIST Severity \ndetected and unpatched\nScore\n表格內容:\n  Top riskiest CVEs, most \nNIST Severity \ndetected and unpatched\nScore: 1\n  Top riskiest CVEs, most \nNIST Severity \ndetected and unpatched\nScore: 2\n  Top riskiest CVEs, most \nNIST Severity \ndetected and unpatched\nScore: 3\n  Top riskiest CVEs, most \nNIST Severity \ndetected and unpatched\nScore: 4\n  Top riskiest CVEs, most \nNIST Severity \ndetected and unpatched\nScore: 5\n  Top riskiest CVEs, most \nNIST Severity \ndetected and unpatched\nScore: 6\n  Top riskiest CVEs, most \nNIST Severity \ndetected and unpatched\nScore: 7\n  Top riskiest CVEs, most \nNIST Severity \ndetected and unpatched\nScore: 8\n  Top riskiest CVEs, most \nNIST Severity \ndetected and unpatched\nScore: 9\n  Top riskiest CVEs, most \nNIST Severity \ndetected and unpatched\nScore: 10\n搜尋關鍵字: 比較, 對比, 分析, Top riskiest CVEs, most \nNIST Severity \ndetected and unpatched\nScore, CVE-2024-2135715, 8.1 High, CVE-2024-3008616, 7\n.8 High, CVE-2024-3008217, 7\n.8 High",
      "metadata": {
        "original_table_data": {
          "title": "Camelot_Table_31_17",
          "headers": [
            "Top riskiest CVEs, most \nNIST Severity \ndetected and unpatched\nScore",
            "",
            ""
          ],
          "rows": [
            [
              "1",
              "CVE-2024-2135715",
              "8.1 High"
            ],
            [
              "2",
              "CVE-2024-3008616",
              "7\n.8 High"
            ],
            [
              "3",
              "CVE-2024-3008217",
              "7\n.8 High"
            ],
            [
              "4",
              "CVE-2024-3008718",
              "7\n.8 High"
            ],
            [
              "5",
              "CVE-2024-3525019",
              "7\n.8 High"
            ],
            [
              "6",
              "CVE-2024-3009120",
              "7\n.8 High"
            ],
            [
              "7",
              "CVE-2024-3004921",
              "7\n.8 High"
            ],
            [
              "8",
              "CVE-2024-3008422",
              "7\n.0 High"
            ],
            [
              "9",
              "CVE-2024-3005023",
              "5.4 Medium"
            ],
            [
              "10",
              "CVE-2024-3003724",
              "5.5 Medium"
            ]
          ],
          "source_page": 31,
          "source_file": "data/source/Research-Risk-Report-2025.pdf",
          "table_type": "comparison",
          "confidence": 99.99999999999996,
          "extractor_method": "camelot",
          "metadata": {
            "whitespace": 6.0606060606060606,
            "order": 1,
            "flavor": "lattice"
          }
        },
        "source_page": 31,
        "source_file": "data/source/Research-Risk-Report-2025.pdf",
        "table_type": "comparison",
        "confidence": 99.99999999999996,
        "extractor_method": "camelot",
        "conversion_date": "2025-07-18T10:36:09.156951"
      }
    },
    {
      "table_id": "table_18_Camelot_Table_35_18",
      "content": "表格標題: Camelot_Table_35_18\n表格類型: comparison\n來源頁面: 第35頁\n資料提取方法: camelot\n信心度: 100.0%\n表格欄位: 1, Automated Response Playbook\n表格內容:\n  1: 2, Automated Response Playbook: Custom\n  1: 3, Automated Response Playbook: CVEs with Global Exploit Activity - Internal Assets\n  1: 4, Automated Response Playbook: CVEs with High or Medium Global Exploit Activity\n  1: 5, Automated Response Playbook: Risk Event Response\n  1: 6, Automated Response Playbook: Account Response\n  1: 7, Automated Response Playbook: CVEs with High or Medium Global Exploit Activity - Internet-Facing Assets\n  1: 8, Automated Response Playbook: CVEs with Global Exploit Activity - Internet-Facing Assets\n  1: 9, Automated Response Playbook: Account Exposure - Weak Sign-in Policies, Excessive Admin Accounts, and Stale Accounts\n  1: 10, Automated Response Playbook: Endpoint Response\n搜尋關鍵字: 比較, 對比, 分析, Automated Response Playbook, Custom",
      "metadata": {
        "original_table_data": {
          "title": "Camelot_Table_35_18",
          "headers": [
            "1",
            "Automated Response Playbook"
          ],
          "rows": [
            [
              "2",
              "Custom"
            ],
            [
              "3",
              "CVEs with Global Exploit Activity - Internal Assets"
            ],
            [
              "4",
              "CVEs with High or Medium Global Exploit Activity"
            ],
            [
              "5",
              "Risk Event Response"
            ],
            [
              "6",
              "Account Response"
            ],
            [
              "7",
              "CVEs with High or Medium Global Exploit Activity - Internet-Facing Assets"
            ],
            [
              "8",
              "CVEs with Global Exploit Activity - Internet-Facing Assets"
            ],
            [
              "9",
              "Account Exposure - Weak Sign-in Policies, Excessive Admin Accounts, and Stale Accounts"
            ],
            [
              "10",
              "Endpoint Response"
            ]
          ],
          "source_page": 35,
          "source_file": "data/source/Research-Risk-Report-2025.pdf",
          "table_type": "comparison",
          "confidence": 100.0,
          "extractor_method": "camelot",
          "metadata": {
            "whitespace": 0.0,
            "order": 1,
            "flavor": "lattice"
          }
        },
        "source_page": 35,
        "source_file": "data/source/Research-Risk-Report-2025.pdf",
        "table_type": "comparison",
        "confidence": 100.0,
        "extractor_method": "camelot",
        "conversion_date": "2025-07-18T10:36:09.156986"
      }
    },
    {
      "table_id": "table_19_Camelot_Table_1_1",
      "content": "表格標題: Camelot_Table_1_1\n表格類型: time_series\n來源頁面: 第1頁\n資料提取方法: camelot\n信心度: 100.0%\n表格欄位: TREND 2025\n表格內容:\n  TREND 2025: CYBER RISK\n  TREND 2025: REPORT\n搜尋關鍵字: TREND 2025, CYBER RISK, REPORT",
      "metadata": {
        "original_table_data": {
          "title": "Camelot_Table_1_1",
          "headers": [
            "TREND 2025"
          ],
          "rows": [
            [
              "CYBER RISK"
            ],
            [
              "REPORT"
            ]
          ],
          "source_page": 1,
          "source_file": "data/source/Research-Risk-Report-2025.pdf",
          "table_type": "time_series",
          "confidence": 100.0,
          "extractor_method": "camelot",
          "metadata": {
            "whitespace": 0.0,
            "order": 1,
            "flavor": "stream"
          }
        },
        "source_page": 1,
        "source_file": "data/source/Research-Risk-Report-2025.pdf",
        "table_type": "time_series",
        "confidence": 100.0,
        "extractor_method": "camelot",
        "conversion_date": "2025-07-18T10:36:09.157004"
      }
    },
    {
      "table_id": "table_20_Camelot_Table_2_2",
      "content": "表格標題: Camelot_Table_2_2\n表格類型: general\n來源頁面: 第2頁\n資料提取方法: camelot\n信心度: 100.0%\n表格欄位: Outpacing the adversary\n表格內容:\n  Outpacing the adversary: The Trend 2025 Cyber Risk Report sustains our shift towards proactive security. Protecting enterprises is\n  Outpacing the adversary: no longer about stopping breaches but is now about staying ahead, making cybersecurity a business enabler.\n  Outpacing the adversary: This report looks at our telemetry from 2024: by looking at last year’s risk landscape, we recognize exposures\n  Outpacing the adversary: and understand attacker behavior to be able to implement countermeasures for the year ahead. This way, we\n  Outpacing the adversary: transform security from a challenge to a catalyst for innovation and business growth.\n  Outpacing the adversary: This report harnesses data from the Cyber Risk Exposure Management1 (CREM) solution of our flagship\n  Outpacing the adversary: cybersecurity platform Trend Vision One™2. Telemetry from this solution identifies exposures across attack surfaces\n  Outpacing the adversary: to help prioritize and address risk areas. Combined with data from our native eXtended Detection and Response3\n  Outpacing the adversary: (XDR) tools and threat intelligence, this report primes enterprises with information on adversaries along with risk\n  Outpacing the adversary: insights to reduce their Cyber Risk Index and stay ahead of the curve.\n搜尋關鍵字: Outpacing the adversary",
      "metadata": {
        "original_table_data": {
          "title": "Camelot_Table_2_2",
          "headers": [
            "Outpacing the adversary"
          ],
          "rows": [
            [
              "The Trend 2025 Cyber Risk Report sustains our shift towards proactive security. Protecting enterprises is"
            ],
            [
              "no longer about stopping breaches but is now about staying ahead, making cybersecurity a business enabler."
            ],
            [
              "This report looks at our telemetry from 2024: by looking at last year’s risk landscape, we recognize exposures"
            ],
            [
              "and understand attacker behavior to be able to implement countermeasures for the year ahead. This way, we"
            ],
            [
              "transform security from a challenge to a catalyst for innovation and business growth."
            ],
            [
              "This report harnesses data from the Cyber Risk Exposure Management1 (CREM) solution of our flagship"
            ],
            [
              "cybersecurity platform Trend Vision One™2. Telemetry from this solution identifies exposures across attack surfaces"
            ],
            [
              "to help prioritize and address risk areas. Combined with data from our native eXtended Detection and Response3"
            ],
            [
              "(XDR) tools and threat intelligence, this report primes enterprises with information on adversaries along with risk"
            ],
            [
              "insights to reduce their Cyber Risk Index and stay ahead of the curve."
            ]
          ],
          "source_page": 2,
          "source_file": "data/source/Research-Risk-Report-2025.pdf",
          "table_type": "general",
          "confidence": 100.00000000000001,
          "extractor_method": "camelot",
          "metadata": {
            "whitespace": 0.0,
            "order": 1,
            "flavor": "stream"
          }
        },
        "source_page": 2,
        "source_file": "data/source/Research-Risk-Report-2025.pdf",
        "table_type": "general",
        "confidence": 100.00000000000001,
        "extractor_method": "camelot",
        "conversion_date": "2025-07-18T10:36:09.157031"
      }
    },
    {
      "table_id": "table_21_Camelot_Table_3_3",
      "content": "表格標題: Camelot_Table_3_3\n表格類型: general\n來源頁面: 第3頁\n資料提取方法: camelot\n信心度: 100.0%\n表格欄位: The Cyber\n表格內容:\n  The Cyber: Risk Index\n搜尋關鍵字: The Cyber, Risk Index",
      "metadata": {
        "original_table_data": {
          "title": "Camelot_Table_3_3",
          "headers": [
            "The Cyber"
          ],
          "rows": [
            [
              "Risk Index"
            ]
          ],
          "source_page": 3,
          "source_file": "data/source/Research-Risk-Report-2025.pdf",
          "table_type": "general",
          "confidence": 100.0,
          "extractor_method": "camelot",
          "metadata": {
            "whitespace": 0.0,
            "order": 1,
            "flavor": "stream"
          }
        },
        "source_page": 3,
        "source_file": "data/source/Research-Risk-Report-2025.pdf",
        "table_type": "general",
        "confidence": 100.0,
        "extractor_method": "camelot",
        "conversion_date": "2025-07-18T10:36:09.157046"
      }
    },
    {
      "table_id": "table_22_Camelot_Table_4_4",
      "content": "表格標題: Camelot_Table_4_4\n表格類型: statistical\n來源頁面: 第4頁\n資料提取方法: camelot\n信心度: 74.9%\n表格欄位: To achieve a proactive approach to cybersecurity, we capitalize on data from our Cyber Risk Exposure Management solution, which\n表格內容:\n  To achieve a proactive approach to cybersecurity, we capitalize on data from our Cyber Risk Exposure Management solution, which: 4\n搜尋關鍵字: 統計, 數據, 數字, To achieve a proactive approach to cybersecurity, we capitalize on data from our Cyber Risk Exposure Management solution, which",
      "metadata": {
        "original_table_data": {
          "title": "Camelot_Table_4_4",
          "headers": [
            "",
            "To achieve a proactive approach to cybersecurity, we capitalize on data from our Cyber Risk Exposure Management solution, which"
          ],
          "rows": [
            [
              "is designed to protect organizations’ digital assets from attacks by evaluating risks across the attack surface, prioritizing them,",
              ""
            ],
            [
              "and implementing appropriate countermeasures.",
              ""
            ],
            [
              "CREM calculates an enterprise’s Cyber Risk Index (CRI), a metric that quantifies the overall security risk of an organization based on a",
              ""
            ],
            [
              "consolidation of individual assets and risk factor scores. Our research4 has found that organizations with a CRI above the average have",
              ""
            ],
            [
              "a greater likelihood to suffer from attacks than those with a lower CRI. Like how preventive health check-ups reveal the overall state of",
              ""
            ],
            [
              "health, analyze risks the body might be exposed to, and creates an action plan on how to prevent these risks, CREM works to identify",
              ""
            ],
            [
              "the CRI and creates a strategy to reduce them and therefore improve an organization’s security posture.",
              ""
            ],
            [
              "While risk is evaluated qualitatively, the CRI quantifies it by using a scale from 0-100 to represent and give a clearer picture of where",
              ""
            ],
            [
              "enterprises or sectors stand in terms of security and risk.",
              ""
            ],
            [
              "CREM uses the risk event catalog to formulate a risk score for each asset type and an index for organizations by multiplying an asset’s",
              ""
            ],
            [
              "attack, exposure, and security configuration by the asset criticality. The risk scores are calculated individually for every asset, with",
              ""
            ],
            [
              "each score considering asset type and criticality. The result is an integer between zero and 100 that falls into one of three levels.",
              ""
            ],
            [
              "•  Low Risk (0-30):",
              ""
            ],
            [
              "° Organizations in this category are considered relatively secure",
              ""
            ],
            [
              "° Immediate significant measures are generally not necessary",
              ""
            ],
            [
              "Trend 2025 Cyber Risk Report",
              "4"
            ]
          ],
          "source_page": 4,
          "source_file": "data/source/Research-Risk-Report-2025.pdf",
          "table_type": "statistical",
          "confidence": 74.94620904919734,
          "extractor_method": "camelot",
          "metadata": {
            "whitespace": 47.05882352941176,
            "order": 1,
            "flavor": "stream"
          }
        },
        "source_page": 4,
        "source_file": "data/source/Research-Risk-Report-2025.pdf",
        "table_type": "statistical",
        "confidence": 74.94620904919734,
        "extractor_method": "camelot",
        "conversion_date": "2025-07-18T10:36:09.157074"
      }
    },
    {
      "table_id": "table_23_Camelot_Table_5_5",
      "content": "表格標題: Camelot_Table_5_5\n表格類型: statistical\n來源頁面: 第5頁\n資料提取方法: camelot\n信心度: 85.1%\n表格欄位: •  Medium Risk (31-69):\n表格內容:\n  •  Medium Risk (31-69):: ° Organizations in this category have several risk factors that need to be addressed\n  •  Medium Risk (31-69):: ° It is advisable to consider and implement appropriate countermeasures\n  •  Medium Risk (31-69):: •  High Risk (70-100):\n  •  Medium Risk (31-69):: ° Organizations in this category are exposed to severe risks\n  •  Medium Risk (31-69):: ° Prompt and robust security measures are essential to mitigate potential threats\n  •  Medium Risk (31-69):: Learn more with our Cyber Risk Index Overview5 and our technical report on how to understand risk score calculations6.\n  •  Medium Risk (31-69):: This report covers telemetry from February to December 2024; it excludes data from January as the CREM dashboard algorithm\n  •  Medium Risk (31-69):: was updated at the end of that month with a weight summation method that affects CRI computation. Telemetry from February to\n  •  Medium Risk (31-69):: December 2024 was computed with the same algorithm and provides a more accurate average CRI. Future improvements to CREM\n  •  Medium Risk (31-69):: computation will be disclosed accordingly. Also note that industry CRI data do not include industries with a sample size too small to be\n  •  Medium Risk (31-69):: statistically relevant.\n  •  Medium Risk (31-69):: Trend 2025 Cyber Risk Report\n搜尋關鍵字: 統計, 數據, 數字, •  Medium Risk (31-69):",
      "metadata": {
        "original_table_data": {
          "title": "Camelot_Table_5_5",
          "headers": [
            "•  Medium Risk (31-69):",
            ""
          ],
          "rows": [
            [
              "° Organizations in this category have several risk factors that need to be addressed",
              ""
            ],
            [
              "° It is advisable to consider and implement appropriate countermeasures",
              ""
            ],
            [
              "•  High Risk (70-100):",
              ""
            ],
            [
              "° Organizations in this category are exposed to severe risks",
              ""
            ],
            [
              "° Prompt and robust security measures are essential to mitigate potential threats",
              ""
            ],
            [
              "Learn more with our Cyber Risk Index Overview5 and our technical report on how to understand risk score calculations6.",
              ""
            ],
            [
              "This report covers telemetry from February to December 2024; it excludes data from January as the CREM dashboard algorithm",
              ""
            ],
            [
              "was updated at the end of that month with a weight summation method that affects CRI computation. Telemetry from February to",
              ""
            ],
            [
              "December 2024 was computed with the same algorithm and provides a more accurate average CRI. Future improvements to CREM",
              ""
            ],
            [
              "computation will be disclosed accordingly. Also note that industry CRI data do not include industries with a sample size too small to be",
              ""
            ],
            [
              "statistically relevant.",
              ""
            ],
            [
              "Trend 2025 Cyber Risk Report",
              "5"
            ]
          ],
          "source_page": 5,
          "source_file": "data/source/Research-Risk-Report-2025.pdf",
          "table_type": "statistical",
          "confidence": 85.05874119793837,
          "extractor_method": "camelot",
          "metadata": {
            "whitespace": 46.15384615384615,
            "order": 1,
            "flavor": "stream"
          }
        },
        "source_page": 5,
        "source_file": "data/source/Research-Risk-Report-2025.pdf",
        "table_type": "statistical",
        "confidence": 85.05874119793837,
        "extractor_method": "camelot",
        "conversion_date": "2025-07-18T10:36:09.157128"
      }
    },
    {
      "table_id": "table_24_Camelot_Table_6_6",
      "content": "表格標題: Camelot_Table_6_6\n表格類型: general\n來源頁面: 第6頁\n資料提取方法: camelot\n信心度: 100.0%\n表格欄位: Cyber Risk\n表格內容:\n  Cyber Risk: Index Data\n搜尋關鍵字: Cyber Risk, Index Data",
      "metadata": {
        "original_table_data": {
          "title": "Camelot_Table_6_6",
          "headers": [
            "Cyber Risk"
          ],
          "rows": [
            [
              "Index Data"
            ]
          ],
          "source_page": 6,
          "source_file": "data/source/Research-Risk-Report-2025.pdf",
          "table_type": "general",
          "confidence": 100.0,
          "extractor_method": "camelot",
          "metadata": {
            "whitespace": 0.0,
            "order": 1,
            "flavor": "stream"
          }
        },
        "source_page": 6,
        "source_file": "data/source/Research-Risk-Report-2025.pdf",
        "table_type": "general",
        "confidence": 100.0,
        "extractor_method": "camelot",
        "conversion_date": "2025-07-18T10:36:09.157146"
      }
    },
    {
      "table_id": "table_25_Camelot_Table_7_7",
      "content": "表格標題: Camelot_Table_7_7\n表格類型: statistical\n來源頁面: 第7頁\n資料提取方法: camelot\n信心度: 86.1%\n表格欄位: Overall average CRI\n表格內容:\n  Overall average CRI: 50\n  Overall average CRI: 40\n  Overall average CRI: 30\n  Overall average CRI: 20\n  Overall average CRI: 10\n  Overall average CRI: 0\n  Overall average CRI: The overall average CRI in 2024 improved consistently per month, with a 6.2-point difference from the overall average in February to\n  Overall average CRI: December. While this improvement suggests that enterprises have been successfully operationalizing cyber risk management, a 36.3\n  Overall average CRI: overall CRI still falls within medium risk, an average indicative that organizations still have several risk factors that need addressing.\n  Overall average CRI: This emphasizes the need for continuous monitoring of the attack surface risk life cycle, which includes discovery, assessment, and\n  Overall average CRI: risk mitigation through necessary countermeasures.\n  Overall average CRI: Trend 2025 Cyber Risk Report\n搜尋關鍵字: 統計, 數據, 數字, Overall average CRI, 50, 42.5",
      "metadata": {
        "original_table_data": {
          "title": "Camelot_Table_7_7",
          "headers": [
            "Overall average CRI",
            "",
            "",
            "",
            "",
            "",
            "",
            "",
            "",
            "",
            "",
            "",
            ""
          ],
          "rows": [
            [
              "",
              "",
              "",
              "",
              "",
              "",
              "",
              "",
              "",
              "Average CRI for 2024: 38.4",
              "",
              "",
              ""
            ],
            [
              "50",
              "",
              "",
              "",
              "",
              "",
              "",
              "",
              "",
              "",
              "",
              "",
              ""
            ],
            [
              "",
              "42.5",
              "",
              "",
              "",
              "",
              "",
              "",
              "",
              "",
              "",
              "",
              ""
            ],
            [
              "",
              "",
              "39.9",
              "39.2",
              "39.3",
              "39.0",
              "38.4",
              "",
              "",
              "",
              "",
              "",
              ""
            ],
            [
              "",
              "",
              "",
              "",
              "",
              "",
              "",
              "37.6",
              "37.3",
              "",
              "",
              "",
              ""
            ],
            [
              "",
              "",
              "",
              "",
              "",
              "",
              "",
              "",
              "",
              "36.7",
              "36.9",
              "36.3",
              ""
            ],
            [
              "40",
              "",
              "",
              "",
              "",
              "",
              "",
              "",
              "",
              "",
              "",
              "",
              ""
            ],
            [
              "30",
              "",
              "",
              "",
              "",
              "",
              "",
              "",
              "",
              "",
              "",
              "",
              ""
            ],
            [
              "20",
              "",
              "",
              "",
              "",
              "",
              "",
              "",
              "",
              "",
              "",
              "",
              ""
            ],
            [
              "10",
              "",
              "",
              "",
              "",
              "",
              "",
              "",
              "",
              "",
              "",
              "",
              ""
            ],
            [
              "0",
              "",
              "",
              "",
              "",
              "",
              "",
              "",
              "",
              "",
              "",
              "",
              ""
            ],
            [
              "",
              "FEB",
              "MAR",
              "APR",
              "MAY",
              "JUN",
              "JUL",
              "AUG",
              "SEP",
              "OCT",
              "NOV",
              "DEC",
              ""
            ],
            [
              "",
              "",
              "",
              "",
              "",
              "",
              "",
              "",
              "",
              "(February 2024 - December 2024)",
              "",
              "",
              ""
            ],
            [
              "The overall average CRI in 2024 improved consistently per month, with a 6.2-point difference from the overall average in February to",
              "",
              "",
              "",
              "",
              "",
              "",
              "",
              "",
              "",
              "",
              "",
              ""
            ],
            [
              "December. While this improvement suggests that enterprises have been successfully operationalizing cyber risk management, a 36.3",
              "",
              "",
              "",
              "",
              "",
              "",
              "",
              "",
              "",
              "",
              "",
              ""
            ],
            [
              "overall CRI still falls within medium risk, an average indicative that organizations still have several risk factors that need addressing.",
              "",
              "",
              "",
              "",
              "",
              "",
              "",
              "",
              "",
              "",
              "",
              ""
            ],
            [
              "This emphasizes the need for continuous monitoring of the attack surface risk life cycle, which includes discovery, assessment, and",
              "",
              "",
              "",
              "",
              "",
              "",
              "",
              "",
              "",
              "",
              "",
              ""
            ],
            [
              "risk mitigation through necessary countermeasures.",
              "",
              "",
              "",
              "",
              "",
              "",
              "",
              "",
              "",
              "",
              "",
              ""
            ],
            [
              "Trend 2025 Cyber Risk Report",
              "",
              "",
              "",
              "",
              "",
              "",
              "",
              "",
              "",
              "",
              "",
              "7"
            ]
          ],
          "source_page": 7,
          "source_file": "data/source/Research-Risk-Report-2025.pdf",
          "table_type": "statistical",
          "confidence": 86.0895023878943,
          "extractor_method": "camelot",
          "metadata": {
            "whitespace": 85.38461538461539,
            "order": 1,
            "flavor": "stream"
          }
        },
        "source_page": 7,
        "source_file": "data/source/Research-Risk-Report-2025.pdf",
        "table_type": "statistical",
        "confidence": 86.0895023878943,
        "extractor_method": "camelot",
        "conversion_date": "2025-07-18T10:36:09.157205"
      }
    },
    {
      "table_id": "table_26_Camelot_Table_8_8",
      "content": "表格標題: Camelot_Table_8_8\n表格類型: statistical\n來源頁面: 第8頁\n資料提取方法: camelot\n信心度: 89.1%\n表格欄位: Regional Average CRI per month(February 2024 - December 2024)\n表格內容:\n  Regional Average CRI per month(February 2024 - December 2024): Americas\n  Regional Average CRI per month(February 2024 - December 2024): Our regional telemetry is consistent to the overall average CRI data. There is a general downtrend in risk indices among the regions;\n  Regional Average CRI per month(February 2024 - December 2024): Europe exhibiting the biggest improvement from February to December with a 7-point difference. The region is pushing for increased\n  Regional Average CRI per month(February 2024 - December 2024): cyber hygiene and resilience with the Digital Operational Resilience Act7 and the Cyber Resilience Act8, which could influence\n  Regional Average CRI per month(February 2024 - December 2024): Trend 2025 Cyber Risk Report\n搜尋關鍵字: 統計, 數據, 數字, Regional Average CRI per month(February 2024 - December 2024), 50, Europe:  37.9, AMEA:  37.9",
      "metadata": {
        "original_table_data": {
          "title": "Camelot_Table_8_8",
          "headers": [
            "Regional Average CRI per month(February 2024 - December 2024)",
            "",
            "",
            "",
            "",
            "",
            "",
            "",
            "",
            "",
            "",
            ""
          ],
          "rows": [
            [
              "",
              "50",
              "",
              "",
              "",
              "",
              "",
              "",
              "",
              "",
              "",
              ""
            ],
            [
              "",
              "",
              "",
              "",
              "",
              "",
              "",
              "",
              "",
              "Regional Average CRI for 2024",
              "",
              ""
            ],
            [
              "",
              "",
              "",
              "",
              "",
              "",
              "",
              "",
              "",
              "Europe:  37.9",
              "AMEA:  37.9",
              ""
            ],
            [
              "",
              "",
              "43.7",
              "",
              "",
              "",
              "",
              "",
              "",
              "",
              "",
              ""
            ],
            [
              "Americas",
              "",
              "",
              "",
              "",
              "",
              "",
              "",
              "",
              "Americas:  39.8",
              "Japan:  34.3",
              ""
            ],
            [
              "",
              "",
              "",
              "41.6",
              "",
              "",
              "",
              "",
              "",
              "",
              "",
              ""
            ],
            [
              "",
              "",
              "",
              "",
              "41.2",
              "40.7",
              "40.4",
              "",
              "",
              "",
              "",
              ""
            ],
            [
              "",
              "",
              "",
              "",
              "",
              "",
              "",
              "39.7",
              "",
              "",
              "",
              ""
            ],
            [
              "",
              "",
              "42.6",
              "",
              "",
              "",
              "",
              "",
              "38.8",
              "38.8",
              "",
              ""
            ],
            [
              "",
              "40",
              "",
              "",
              "",
              "",
              "",
              "",
              "",
              "",
              "",
              ""
            ],
            [
              "",
              "",
              "",
              "",
              "",
              "",
              "",
              "",
              "",
              "38.0",
              "36.8",
              ""
            ],
            [
              "",
              "",
              "",
              "",
              "",
              "",
              "",
              "",
              "",
              "",
              "37.8",
              ""
            ],
            [
              "",
              "",
              "41.8",
              "",
              "",
              "",
              "",
              "",
              "",
              "",
              "",
              ""
            ],
            [
              "",
              "",
              "",
              "",
              "",
              "",
              "",
              "",
              "37.3",
              "",
              "36.6",
              ""
            ],
            [
              "",
              "",
              "",
              "39.4",
              "",
              "",
              "",
              "",
              "",
              "37.0",
              "",
              ""
            ],
            [
              "",
              "",
              "",
              "",
              "",
              "38.9",
              "38.3",
              "",
              "",
              "",
              "",
              ""
            ],
            [
              "",
              "",
              "",
              "",
              "",
              "",
              "",
              "",
              "",
              "36.1",
              "",
              ""
            ],
            [
              "",
              "",
              "",
              "",
              "38.9",
              "",
              "",
              "37.8",
              "",
              "",
              "",
              ""
            ],
            [
              "",
              "",
              "",
              "39.0",
              "",
              "",
              "38.5",
              "",
              "",
              "",
              "",
              ""
            ],
            [
              "",
              "",
              "",
              "",
              "",
              "38.6",
              "",
              "",
              "36.6",
              "",
              "",
              ""
            ],
            [
              "",
              "",
              "37.5",
              "",
              "",
              "",
              "",
              "",
              "",
              "37.0",
              "",
              ""
            ],
            [
              "",
              "",
              "",
              "",
              "38.1",
              "",
              "",
              "",
              "",
              "",
              "36.2",
              ""
            ],
            [
              "",
              "",
              "",
              "",
              "",
              "",
              "",
              "38.2",
              "",
              "36.3",
              "36.7",
              ""
            ],
            [
              "",
              "",
              "",
              "",
              "",
              "",
              "",
              "",
              "",
              "",
              "35.6",
              ""
            ],
            [
              "",
              "",
              "",
              "",
              "",
              "",
              "35.1",
              "",
              "",
              "",
              "",
              ""
            ],
            [
              "",
              "",
              "",
              "34.7",
              "",
              "",
              "",
              "",
              "34.8",
              "",
              "",
              ""
            ],
            [
              "",
              "",
              "",
              "",
              "",
              "",
              "",
              "",
              "",
              "34.6",
              "",
              ""
            ],
            [
              "",
              "",
              "",
              "",
              "",
              "",
              "",
              "",
              "",
              "34.0",
              "34.2",
              ""
            ],
            [
              "",
              "",
              "",
              "",
              "",
              "",
              "",
              "33.9",
              "",
              "",
              "",
              ""
            ],
            [
              "",
              "",
              "",
              "",
              "33.4",
              "",
              "",
              "",
              "",
              "",
              "",
              ""
            ],
            [
              "",
              "",
              "",
              "",
              "",
              "",
              "",
              "",
              "",
              "",
              "33.2",
              ""
            ],
            [
              "",
              "",
              "",
              "",
              "",
              "32.0",
              "",
              "",
              "",
              "",
              "",
              ""
            ],
            [
              "",
              "30",
              "",
              "",
              "",
              "",
              "",
              "",
              "",
              "",
              "",
              ""
            ],
            [
              "",
              "",
              "FEB",
              "MAR",
              "APR",
              "MAY",
              "JUN",
              "JUL",
              "AUG",
              "SEP\nOCT",
              "NOV\nDEC",
              ""
            ],
            [
              "",
              "",
              "",
              "",
              "",
              "",
              "",
              "",
              "",
              "(February 2024 - December 2024)",
              "",
              ""
            ],
            [
              "Our regional telemetry is consistent to the overall average CRI data. There is a general downtrend in risk indices among the regions;",
              "",
              "",
              "",
              "",
              "",
              "",
              "",
              "",
              "",
              "",
              ""
            ],
            [
              "Europe exhibiting the biggest improvement from February to December with a 7-point difference. The region is pushing for increased",
              "",
              "",
              "",
              "",
              "",
              "",
              "",
              "",
              "",
              "",
              ""
            ],
            [
              "cyber hygiene and resilience with the Digital Operational Resilience Act7 and the Cyber Resilience Act8, which could influence",
              "",
              "",
              "",
              "",
              "",
              "",
              "",
              "",
              "",
              "",
              ""
            ],
            [
              "",
              "enterprises to take a more proactive approach in cybersecurity through patching, fixing configurations, and refining user access and",
              "",
              "",
              "",
              "",
              "",
              "",
              "",
              "",
              "",
              ""
            ],
            [
              "",
              "permissions, among others.",
              "",
              "",
              "",
              "",
              "",
              "",
              "",
              "",
              "",
              ""
            ],
            [
              "",
              "While CRI among regions improved in the past year, each region’s risk index is still within the medium risk level: enterprises from each",
              "",
              "",
              "",
              "",
              "",
              "",
              "",
              "",
              "",
              ""
            ],
            [
              "",
              "region still have unsecure assets that might expose the organization to threats.",
              "",
              "",
              "",
              "",
              "",
              "",
              "",
              "",
              "",
              ""
            ],
            [
              "Trend 2025 Cyber Risk Report",
              "",
              "",
              "",
              "",
              "",
              "",
              "",
              "",
              "",
              "",
              "8"
            ]
          ],
          "source_page": 8,
          "source_file": "data/source/Research-Risk-Report-2025.pdf",
          "table_type": "statistical",
          "confidence": 89.06071052505649,
          "extractor_method": "camelot",
          "metadata": {
            "whitespace": 86.48148148148148,
            "order": 1,
            "flavor": "stream"
          }
        },
        "source_page": 8,
        "source_file": "data/source/Research-Risk-Report-2025.pdf",
        "table_type": "statistical",
        "confidence": 89.06071052505649,
        "extractor_method": "camelot",
        "conversion_date": "2025-07-18T10:36:09.157297"
      }
    },
    {
      "table_id": "table_27_Camelot_Table_9_9",
      "content": "表格標題: Camelot_Table_9_9\n表格類型: general\n來源頁面: 第9頁\n資料提取方法: camelot\n信心度: 100.0%\n表格欄位: Communications, 44.5, 42.6, 41.0, 39.3\n表格內容:\n  Communications: Construction, 44.5: 43.9, 42.6: 41.3, 41.0: 40.0, 39.3: 38.5\n  Communications: Education, 44.5: 45.1, 42.6: 43.1, 41.0: 41.1, 39.3: 39.8\n  Communications: Energy, 44.5: 43.7, 42.6: 41.6, 41.0: 41.2, 39.3: 39.6\n  Communications: Financial Services, 44.5: 42.6, 42.6: 40.7, 41.0: 38.8, 39.3: 37.9\n  Communications: Government and\n  44.5: 42.9, 42.6: 40.7, 41.0: 39.5, 39.3: 39.1\n  Communications: Public Services\n  Communications: Healthcare, 44.5: 43.7, 42.6: 41.4, 41.0: 40.3, 39.3: 39.4\n  Communications: Insurance, 44.5: 43.7, 42.6: 41.4, 41.0: 40.3, 39.3: 39.7\n  Communications: Transportation, 44.5: 42.6, 42.6: 40.8, 41.0: 39.4, 39.3: 37.8\n搜尋關鍵字: Communications, 44.5, 42.6, 41.0, 39.3, 41.6, Construction, 43.9, 41.3, 40.0",
      "metadata": {
        "original_table_data": {
          "title": "Camelot_Table_9_9",
          "headers": [
            "",
            "",
            "Communications",
            "44.5",
            "42.6",
            "41.0",
            "39.3"
          ],
          "rows": [
            [
              "",
              "41.6",
              "",
              "",
              "",
              "",
              ""
            ],
            [
              "",
              "",
              "Construction",
              "43.9",
              "41.3",
              "40.0",
              "38.5"
            ],
            [
              "",
              "40.6",
              "",
              "",
              "",
              "",
              ""
            ],
            [
              "",
              "",
              "Education",
              "45.1",
              "43.1",
              "41.1",
              "39.8"
            ],
            [
              "Apr-Jun",
              "42.0",
              "",
              "",
              "",
              "",
              ""
            ],
            [
              "",
              "",
              "Energy",
              "43.7",
              "41.6",
              "41.2",
              "39.6"
            ],
            [
              "",
              "41.3",
              "",
              "",
              "",
              "",
              ""
            ],
            [
              "Feb-Mar",
              "",
              "",
              "",
              "",
              "",
              ""
            ],
            [
              "",
              "",
              "Financial Services",
              "42.6",
              "40.7",
              "38.8",
              "37.9"
            ],
            [
              "",
              "39.7",
              "",
              "",
              "",
              "",
              ""
            ],
            [
              "",
              "",
              "Government and",
              "",
              "",
              "",
              ""
            ],
            [
              "",
              "",
              "",
              "42.9",
              "40.7",
              "39.5",
              "39.1"
            ],
            [
              "",
              "40.3",
              "",
              "",
              "",
              "",
              ""
            ],
            [
              "",
              "",
              "Public Services",
              "",
              "",
              "",
              ""
            ],
            [
              "",
              "",
              "Healthcare",
              "43.7",
              "41.4",
              "40.3",
              "39.4"
            ],
            [
              "",
              "41.0",
              "",
              "",
              "",
              "",
              ""
            ],
            [
              "",
              "",
              "Insurance",
              "43.7",
              "41.4",
              "40.3",
              "39.7"
            ],
            [
              "",
              "41.0",
              "",
              "",
              "",
              "",
              ""
            ],
            [
              "",
              "",
              "Transportation",
              "42.6",
              "40.8",
              "39.4",
              "37.8"
            ],
            [
              "",
              "39.9",
              "",
              "",
              "",
              "",
              ""
            ]
          ],
          "source_page": 9,
          "source_file": "data/source/Research-Risk-Report-2025.pdf",
          "table_type": "general",
          "confidence": 99.99999999999986,
          "extractor_method": "camelot",
          "metadata": {
            "whitespace": 61.224489795918366,
            "order": 1,
            "flavor": "stream"
          }
        },
        "source_page": 9,
        "source_file": "data/source/Research-Risk-Report-2025.pdf",
        "table_type": "general",
        "confidence": 99.99999999999986,
        "extractor_method": "camelot",
        "conversion_date": "2025-07-18T10:36:09.157359"
      }
    },
    {
      "table_id": "table_28_Camelot_Table_10_10",
      "content": "表格標題: Camelot_Table_10_10\n表格類型: general\n來源頁面: 第10頁\n資料提取方法: camelot\n信心度: 100.0%\n表格欄位: Factors that affect the education sector’s CRI could include legacy systems with outdated hardware and software and unpatched\n表格內容:\n  Factors that affect the education sector’s CRI could include legacy systems with outdated hardware and software and unpatched: applications. The sector’s diverse group of users who create a larger attack surface with the adoption of remote learning environments\n  Factors that affect the education sector’s CRI could include legacy systems with outdated hardware and software and unpatched: also increases the likelihood of human error that result in security misconfigurations or exposure to phishing attacks. Educational\n  Factors that affect the education sector’s CRI could include legacy systems with outdated hardware and software and unpatched: institutions, especially public ones, also grapple with limited resources that could affect how much they are able to secure their\n  Factors that affect the education sector’s CRI could include legacy systems with outdated hardware and software and unpatched: systems and networks.\n搜尋關鍵字: Factors that affect the education sector’s CRI could include legacy systems with outdated hardware and software and unpatched",
      "metadata": {
        "original_table_data": {
          "title": "Camelot_Table_10_10",
          "headers": [
            "Factors that affect the education sector’s CRI could include legacy systems with outdated hardware and software and unpatched"
          ],
          "rows": [
            [
              "applications. The sector’s diverse group of users who create a larger attack surface with the adoption of remote learning environments"
            ],
            [
              "also increases the likelihood of human error that result in security misconfigurations or exposure to phishing attacks. Educational"
            ],
            [
              "institutions, especially public ones, also grapple with limited resources that could affect how much they are able to secure their"
            ],
            [
              "systems and networks."
            ]
          ],
          "source_page": 10,
          "source_file": "data/source/Research-Risk-Report-2025.pdf",
          "table_type": "general",
          "confidence": 100.0,
          "extractor_method": "camelot",
          "metadata": {
            "whitespace": 0.0,
            "order": 1,
            "flavor": "stream"
          }
        },
        "source_page": 10,
        "source_file": "data/source/Research-Risk-Report-2025.pdf",
        "table_type": "general",
        "confidence": 100.0,
        "extractor_method": "camelot",
        "conversion_date": "2025-07-18T10:36:09.157382"
      }
    },
    {
      "table_id": "table_29_Camelot_Table_11_11",
      "content": "表格標題: Camelot_Table_11_11\n表格類型: statistical\n來源頁面: 第11頁\n資料提取方法: camelot\n信心度: 92.5%\n表格欄位: Average risk index by company size\n表格內容:\n  Average risk index by company size: Larger enterprises typically have more complex networks; with more\n  Average risk index by company size: employees comes a larger attack surface, and so their respective\n  Average risk index by company size: security operations centers face a more challenging task of patching\n  Average risk index by company size: vulnerabilities, maintaining proper security configurations, and\n  Average risk index by company size: securing endpoints.\n  Average risk index by company size: But any enterprise, regardless of size, has a complex attack surface\n  Average risk index by company size: as businesses globalize and expand. Attackers thrive on this\n  Average risk index by company size: complexity, and complex defense can be an expensive — but worthy —\n  Average risk index by company size: investment. Trend Vision One simplifies defense by centralizing cyber\n  Average risk index by company size: risk exposure management, security operations, and a robust layered\n  Average risk index by company size: protection to help security operations centers predict and prevent\n  Average risk index by company size: threats, thereby accelerating proactive security outcomes. At the\n  Average risk index by company size: center of the capabilities that Vision One provides is a risk-informed\n  Average risk index by company size: approach that allows enterprises to stay ahead of threats.\n  Average risk index by company size: Trend 2025 Cyber Risk Report\n搜尋關鍵字: 統計, 數據, 數字, Average risk index by company size, More than 10,000, 44.2",
      "metadata": {
        "original_table_data": {
          "title": "Camelot_Table_11_11",
          "headers": [
            "Average risk index by company size",
            "",
            "",
            "",
            "",
            "",
            "",
            "",
            ""
          ],
          "rows": [
            [
              "Larger enterprises typically have more complex networks; with more",
              "",
              "",
              "",
              "",
              "",
              "",
              "",
              ""
            ],
            [
              "",
              "More than 10,000",
              "",
              "",
              "",
              "",
              "",
              "",
              ""
            ],
            [
              "",
              "",
              "",
              "",
              "",
              "",
              "",
              "44.2",
              ""
            ],
            [
              "employees comes a larger attack surface, and so their respective",
              "",
              "",
              "",
              "",
              "",
              "",
              "",
              ""
            ],
            [
              "security operations centers face a more challenging task of patching",
              "",
              "",
              "",
              "",
              "",
              "",
              "",
              ""
            ],
            [
              "",
              "5,001 - 10,000",
              "",
              "",
              "",
              "",
              "",
              "",
              ""
            ],
            [
              "",
              "",
              "",
              "",
              "",
              "",
              "",
              "44.0",
              ""
            ],
            [
              "vulnerabilities, maintaining proper security configurations, and",
              "",
              "",
              "",
              "",
              "",
              "",
              "",
              ""
            ],
            [
              "securing endpoints.",
              "2,001 - 5,000",
              "",
              "",
              "",
              "",
              "",
              "",
              ""
            ],
            [
              "",
              "",
              "",
              "",
              "",
              "",
              "",
              "43.9",
              ""
            ],
            [
              "But any enterprise, regardless of size, has a complex attack surface",
              "",
              "",
              "",
              "",
              "",
              "",
              "",
              ""
            ],
            [
              "",
              "1,001 - 2,000",
              "",
              "",
              "",
              "",
              "",
              "",
              ""
            ],
            [
              "",
              "",
              "",
              "",
              "",
              "",
              "42.3",
              "",
              ""
            ],
            [
              "as businesses globalize and expand. Attackers thrive on this",
              "",
              "",
              "",
              "",
              "",
              "",
              "",
              ""
            ],
            [
              "",
              "501 - 1,000",
              "",
              "",
              "",
              "",
              "",
              "",
              ""
            ],
            [
              "complexity, and complex defense can be an expensive — but worthy —",
              "",
              "",
              "",
              "",
              "",
              "39.6",
              "",
              ""
            ],
            [
              "investment. Trend Vision One simplifies defense by centralizing cyber",
              "",
              "",
              "",
              "",
              "",
              "",
              "",
              ""
            ],
            [
              "",
              "101 - 500",
              "",
              "",
              "",
              "",
              "",
              "",
              ""
            ],
            [
              "",
              "",
              "",
              "",
              "",
              "",
              "35.8",
              "",
              ""
            ],
            [
              "risk exposure management, security operations, and a robust layered",
              "",
              "",
              "",
              "",
              "",
              "",
              "",
              ""
            ],
            [
              "protection to help security operations centers predict and prevent",
              "",
              "",
              "",
              "",
              "",
              "",
              "",
              ""
            ],
            [
              "",
              "1 - 100",
              "",
              "",
              "",
              "",
              "",
              "",
              ""
            ],
            [
              "",
              "",
              "",
              "",
              "",
              "31.7",
              "",
              "",
              ""
            ],
            [
              "threats, thereby accelerating proactive security outcomes. At the",
              "",
              "",
              "",
              "",
              "",
              "",
              "",
              ""
            ],
            [
              "",
              "0",
              "10",
              "20",
              "30",
              "40",
              "",
              "50",
              ""
            ],
            [
              "center of the capabilities that Vision One provides is a risk-informed",
              "",
              "",
              "",
              "",
              "",
              "",
              "",
              ""
            ],
            [
              "",
              "",
              "",
              "",
              "(February 2024 - December 2024)",
              "",
              "",
              "",
              ""
            ],
            [
              "approach that allows enterprises to stay ahead of threats.",
              "",
              "",
              "",
              "",
              "",
              "",
              "",
              ""
            ],
            [
              "Trend 2025 Cyber Risk Report",
              "",
              "",
              "",
              "",
              "",
              "",
              "",
              "11"
            ]
          ],
          "source_page": 11,
          "source_file": "data/source/Research-Risk-Report-2025.pdf",
          "table_type": "statistical",
          "confidence": 92.47749965941023,
          "extractor_method": "camelot",
          "metadata": {
            "whitespace": 86.37992831541219,
            "order": 1,
            "flavor": "stream"
          }
        },
        "source_page": 11,
        "source_file": "data/source/Research-Risk-Report-2025.pdf",
        "table_type": "statistical",
        "confidence": 92.47749965941023,
        "extractor_method": "camelot",
        "conversion_date": "2025-07-18T10:36:09.157449"
      }
    },
    {
      "table_id": "table_30_Camelot_Table_12_12",
      "content": "表格標題: Camelot_Table_12_12\n表格類型: general\n來源頁面: 第12頁\n資料提取方法: camelot\n信心度: 100.0%\n表格欄位: Risk Events\n表格內容:\n  Risk Events: and Detections\n搜尋關鍵字: Risk Events, and Detections",
      "metadata": {
        "original_table_data": {
          "title": "Camelot_Table_12_12",
          "headers": [
            "Risk Events"
          ],
          "rows": [
            [
              "and Detections"
            ]
          ],
          "source_page": 12,
          "source_file": "data/source/Research-Risk-Report-2025.pdf",
          "table_type": "general",
          "confidence": 100.0,
          "extractor_method": "camelot",
          "metadata": {
            "whitespace": 0.0,
            "order": 1,
            "flavor": "stream"
          }
        },
        "source_page": 12,
        "source_file": "data/source/Research-Risk-Report-2025.pdf",
        "table_type": "general",
        "confidence": 100.0,
        "extractor_method": "camelot",
        "conversion_date": "2025-07-18T10:36:09.157470"
      }
    },
    {
      "table_id": "table_31_Camelot_Table_13_13",
      "content": "表格標題: Camelot_Table_13_13\n表格類型: comparison\n來源頁面: 第13頁\n資料提取方法: camelot\n信心度: 93.2%\n表格欄位: provide clear actionable guidance so security teams can focus on what matters most, in the context of their organization.\n表格內容:\n  provide clear actionable guidance so security teams can focus on what matters most, in the context of their organization.: 1\n  provide clear actionable guidance so security teams can focus on what matters most, in the context of their organization.: 2\n  provide clear actionable guidance so security teams can focus on what matters most, in the context of their organization.: 3\n  provide clear actionable guidance so security teams can focus on what matters most, in the context of their organization.: 4\n  provide clear actionable guidance so security teams can focus on what matters most, in the context of their organization.: 5\n搜尋關鍵字: 比較, 對比, 分析, provide clear actionable guidance so security teams can focus on what matters most, in the context of their organization.",
      "metadata": {
        "original_table_data": {
          "title": "Camelot_Table_13_13",
          "headers": [
            "provide clear actionable guidance so security teams can focus on what matters most, in the context of their organization.",
            ""
          ],
          "rows": [
            [
              "",
              "Overall Top 10 Risky Events"
            ],
            [
              "1",
              "Risky Cloud App Access"
            ],
            [
              "2",
              "Stale Microsoft Entra ID Account"
            ],
            [
              "3",
              "Sandbox Detected Email Threat"
            ],
            [
              "4",
              "On-Premises AD Account with Weak Sign-In Security Policy - Password Expiration Disabled"
            ],
            [
              "5",
              "Advanced Spam Protection - Policy Violation"
            ]
          ],
          "source_page": 13,
          "source_file": "data/source/Research-Risk-Report-2025.pdf",
          "table_type": "comparison",
          "confidence": 93.15156532076425,
          "extractor_method": "camelot",
          "metadata": {
            "whitespace": 14.285714285714285,
            "order": 1,
            "flavor": "stream"
          }
        },
        "source_page": 13,
        "source_file": "data/source/Research-Risk-Report-2025.pdf",
        "table_type": "comparison",
        "confidence": 93.15156532076425,
        "extractor_method": "camelot",
        "conversion_date": "2025-07-18T10:36:09.157493"
      }
    },
    {
      "table_id": "table_32_Camelot_Table_15_15",
      "content": "表格標題: Camelot_Table_15_15\n表格類型: general\n來源頁面: 第15頁\n資料提取方法: camelot\n信心度: 83.8%\n表格欄位: On-Premises AD Account with Weak Sign-In Security Policy - Password Not Required, 413,916,224\n表格內容:\n  On-Premises AD Account with Weak Sign-In Security Policy - Password Not Required: Microsoft Entra ID Account with Weak Sign-In Security Policy - Strong Password Disabled, 413,916,224: 389,998,623\n  On-Premises AD Account with Weak Sign-In Security Policy - Password Not Required: Risky events related to user accounts and credential security suggest that protecting, strengthening, and updating user passwords\n  On-Premises AD Account with Weak Sign-In Security Policy - Password Not Required: is not a high priority for a number of enterprises. Enterprises need to prioritize and automate mitigation of identity risk to eliminate\n  413,916,224: breaches in today’s boundaryless workplace. Trend Vision One™ - Identity Security10 can help organizations do some spring cleaning on\n  On-Premises AD Account with Weak Sign-In Security Policy - Password Not Required: stale user accounts, which can be exploited by attackers, former employees, or insiders for unauthorized access to sensitive data and\n  On-Premises AD Account with Weak Sign-In Security Policy - Password Not Required: the enterprise’s network.\n搜尋關鍵字: On-Premises AD Account with Weak Sign-In Security Policy - Password Not Required, 413,916,224, 389,998,623",
      "metadata": {
        "original_table_data": {
          "title": "Camelot_Table_15_15",
          "headers": [
            "On-Premises AD Account with Weak Sign-In Security Policy - Password Not Required",
            "413,916,224"
          ],
          "rows": [
            [
              "Microsoft Entra ID Account with Weak Sign-In Security Policy - Strong Password Disabled",
              "389,998,623"
            ],
            [
              "Risky events related to user accounts and credential security suggest that protecting, strengthening, and updating user passwords",
              ""
            ],
            [
              "is not a high priority for a number of enterprises. Enterprises need to prioritize and automate mitigation of identity risk to eliminate",
              ""
            ],
            [
              "",
              "breaches in today’s boundaryless workplace. Trend Vision One™ - Identity Security10 can help organizations do some spring cleaning on"
            ],
            [
              "stale user accounts, which can be exploited by attackers, former employees, or insiders for unauthorized access to sensitive data and",
              ""
            ],
            [
              "the enterprise’s network.",
              ""
            ]
          ],
          "source_page": 15,
          "source_file": "data/source/Research-Risk-Report-2025.pdf",
          "table_type": "general",
          "confidence": 83.8278495563446,
          "extractor_method": "camelot",
          "metadata": {
            "whitespace": 35.714285714285715,
            "order": 1,
            "flavor": "stream"
          }
        },
        "source_page": 15,
        "source_file": "data/source/Research-Risk-Report-2025.pdf",
        "table_type": "general",
        "confidence": 83.8278495563446,
        "extractor_method": "camelot",
        "conversion_date": "2025-07-18T10:36:09.157522"
      }
    },
    {
      "table_id": "table_33_Camelot_Table_17_18",
      "content": "表格標題: Camelot_Table_17_18\n表格類型: comparison\n來源頁面: 第17頁\n資料提取方法: camelot\n信心度: 100.0%\n表格欄位: Maximum\n表格內容:\n  Maximum: Risk Score\n  Maximum: 69\n  Maximum: 65\n  Maximum: 56\n  Maximum: 69\n  Maximum: 65\n  Maximum: 68\n  Maximum: 59\n  Maximum: 69\n  Maximum: 59\n  Maximum: 65\n搜尋關鍵字: 比較, 對比, 分析, Maximum, Risk Score, 69",
      "metadata": {
        "original_table_data": {
          "title": "Camelot_Table_17_18",
          "headers": [
            "",
            "",
            "Maximum"
          ],
          "rows": [
            [
              "",
              "Overall Top Vision One Misconfigurations",
              ""
            ],
            [
              "",
              "",
              "Risk Score"
            ],
            [
              "1",
              "Web Reputation Settings in Trend Vision One™ - Endpoint Security Not Optimized",
              "69"
            ],
            [
              "2",
              "Device Control Settings in Endpoint Security Not Optimized",
              "65"
            ],
            [
              "3",
              "Endpoint Security Not Supported",
              "56"
            ],
            [
              "4",
              "Predictive Machine Learning Settings in Endpoint Security Not Optimized",
              "69"
            ],
            [
              "5",
              "Smart Feedback Settings in Endpoint Security Not Optimized",
              "65"
            ],
            [
              "6",
              "Anti-Malware Scanning Settings in Endpoint Security Not Optimized",
              "68"
            ],
            [
              "7",
              "Firewall Settings in Endpoint Security Not Optimized",
              "59"
            ],
            [
              "8",
              "Behavior Monitoring Settings in Endpoint Security Not Optimized",
              "69"
            ],
            [
              "9",
              "Application Control Settings in Endpoint Security Not Optimized",
              "59"
            ],
            [
              "10",
              "Vulnerability Protection Settings in Endpoint Security Not Optimized",
              "65"
            ]
          ],
          "source_page": 17,
          "source_file": "data/source/Research-Risk-Report-2025.pdf",
          "table_type": "comparison",
          "confidence": 100.00000000000001,
          "extractor_method": "camelot",
          "metadata": {
            "whitespace": 15.384615384615385,
            "order": 1,
            "flavor": "stream"
          }
        },
        "source_page": 17,
        "source_file": "data/source/Research-Risk-Report-2025.pdf",
        "table_type": "comparison",
        "confidence": 100.00000000000001,
        "extractor_method": "camelot",
        "conversion_date": "2025-07-18T10:36:09.157555"
      }
    },
    {
      "table_id": "table_34_Camelot_Table_17_19",
      "content": "表格標題: Camelot_Table_17_19\n表格類型: general\n來源頁面: 第17頁\n資料提取方法: camelot\n信心度: 56.9%\n表格欄位: 10, Vulnerability Protection Settings in Endpoint Security Not Optimized, 65\n表格內容:\n  65: (Sorted by most detections, July 2024 - December 2024)\n搜尋關鍵字: 10, Vulnerability Protection Settings in Endpoint Security Not Optimized, 65",
      "metadata": {
        "original_table_data": {
          "title": "Camelot_Table_17_19",
          "headers": [
            "",
            "10",
            "Vulnerability Protection Settings in Endpoint Security Not Optimized",
            "65"
          ],
          "rows": [
            [
              "",
              "",
              "",
              "(Sorted by most detections, July 2024 - December 2024)"
            ],
            [
              "In listing the top detected misconfigurations among Trend Vision One customer environments, we also provide their corresponding",
              "",
              "",
              ""
            ],
            [
              "maximum risk score, which shows they are on the higher end of medium-risk level. These configuration issues emphasize the need for",
              "",
              "",
              ""
            ],
            [
              "organizations to enable advanced detection capabilities and behavior monitoring AI and ML technology to improve the ability to detect",
              "",
              "",
              ""
            ],
            [
              "new threats. Enterprises should maximize tools that provide visibility and help eliminate blind spots with a zero-trust approach to",
              "",
              "",
              ""
            ],
            [
              "minimize their CRI.",
              "",
              "",
              ""
            ]
          ],
          "source_page": 17,
          "source_file": "data/source/Research-Risk-Report-2025.pdf",
          "table_type": "general",
          "confidence": 56.86868921964353,
          "extractor_method": "camelot",
          "metadata": {
            "whitespace": 67.85714285714286,
            "order": 2,
            "flavor": "stream"
          }
        },
        "source_page": 17,
        "source_file": "data/source/Research-Risk-Report-2025.pdf",
        "table_type": "general",
        "confidence": 56.86868921964353,
        "extractor_method": "camelot",
        "conversion_date": "2025-07-18T10:36:09.157578"
      }
    },
    {
      "table_id": "table_35_Camelot_Table_18_20",
      "content": "表格標題: Camelot_Table_18_20\n表格類型: comparison\n來源頁面: 第18頁\n資料提取方法: camelot\n信心度: 100.0%\n表格欄位: Overall Top Cloud Misconfigurations\n表格內容:\n  Overall Top Cloud Misconfigurations: Non-Compliant AWS Infrastructure Configuration\n  Overall Top Cloud Misconfigurations: Non-Compliant Azure Infrastructure Configuration\n  Overall Top Cloud Misconfigurations: Non-Compliant Amazon S3 Infrastructure Configuration (Access Control)\n  Overall Top Cloud Misconfigurations: Non-Compliant Amazon S3 Infrastructure Configuration (Common\n  Overall Top Cloud Misconfigurations: Configuration)\n  Overall Top Cloud Misconfigurations: Non-Compliant Amazon S3 Infrastructure Configuration (Security\n  Overall Top Cloud Misconfigurations: Configuration)\n  Overall Top Cloud Misconfigurations: Non-Compliant GCP Infrastructure Configuration\n  Overall Top Cloud Misconfigurations: Non-Compliant AWS Infrastructure Configuration Revealed by Amazon\n  Overall Top Cloud Misconfigurations: Inspector Findings\n  Overall Top Cloud Misconfigurations: Non-Compliant Amazon S3 Infrastructure Configuration (Amazon Macie\n  Overall Top Cloud Misconfigurations: Findings)\n  Overall Top Cloud Misconfigurations: Non-Compliant Amazon S3 Infrastructure Configuration\n搜尋關鍵字: 比較, 對比, 分析, Overall Top Cloud Misconfigurations",
      "metadata": {
        "original_table_data": {
          "title": "Camelot_Table_18_20",
          "headers": [
            "",
            "Overall Top Cloud Misconfigurations"
          ],
          "rows": [
            [
              "1",
              "Non-Compliant AWS Infrastructure Configuration"
            ],
            [
              "2",
              "Non-Compliant Azure Infrastructure Configuration"
            ],
            [
              "3",
              "Non-Compliant Amazon S3 Infrastructure Configuration (Access Control)"
            ],
            [
              "4",
              "Non-Compliant Amazon S3 Infrastructure Configuration (Common"
            ],
            [
              "",
              "Configuration)"
            ],
            [
              "5",
              "Non-Compliant Amazon S3 Infrastructure Configuration (Security"
            ],
            [
              "",
              "Configuration)"
            ],
            [
              "6",
              "Non-Compliant GCP Infrastructure Configuration"
            ],
            [
              "7",
              "Non-Compliant AWS Infrastructure Configuration Revealed by Amazon"
            ],
            [
              "",
              "Inspector Findings"
            ],
            [
              "8",
              "Non-Compliant Amazon S3 Infrastructure Configuration (Amazon Macie"
            ],
            [
              "",
              "Findings)"
            ],
            [
              "9",
              "Non-Compliant Amazon S3 Infrastructure Configuration"
            ]
          ],
          "source_page": 18,
          "source_file": "data/source/Research-Risk-Report-2025.pdf",
          "table_type": "comparison",
          "confidence": 99.99999999999997,
          "extractor_method": "camelot",
          "metadata": {
            "whitespace": 17.857142857142858,
            "order": 1,
            "flavor": "stream"
          }
        },
        "source_page": 18,
        "source_file": "data/source/Research-Risk-Report-2025.pdf",
        "table_type": "comparison",
        "confidence": 99.99999999999997,
        "extractor_method": "camelot",
        "conversion_date": "2025-07-18T10:36:09.157611"
      }
    },
    {
      "table_id": "table_36_Camelot_Table_19_21",
      "content": "表格標題: Camelot_Table_19_21\n表格類型: statistical\n來源頁面: 第19頁\n資料提取方法: camelot\n信心度: 72.2%\n表格欄位: non-compliance issues on access control, common configuration, and security configuration could be related to public read/write\n表格內容:\n  non-compliance issues on access control, common configuration, and security configuration could be related to public read/write: settings, overly permissive bucket policies, and lack of encryption and versioning. Enterprises using GCP might also be facing problems\n  non-compliance issues on access control, common configuration, and security configuration could be related to public read/write: with IAM policies and insufficient network security configurations. Meanwhile, Amazon Inspector Findings could mean security issues\n  non-compliance issues on access control, common configuration, and security configuration could be related to public read/write: in workloads and insufficient security assessments.\n  non-compliance issues on access control, common configuration, and security configuration could be related to public read/write: Regular audits and updates to IAM policies, security groups, and network access controls are essential to prevent unauthorized access.\n  non-compliance issues on access control, common configuration, and security configuration could be related to public read/write: Enterprises should also avoid public access settings, implement strict bucket policies, enable server-side encryption and versioning,\n  non-compliance issues on access control, common configuration, and security configuration could be related to public read/write: and review lifecycle policies and logging mechanisms. Organizations should maximize solutions that enhance visibility on their cloud\n  non-compliance issues on access control, common configuration, and security configuration could be related to public read/write: environments for more effective cloud risk management. Trend Vision One™ - Cloud Security12 supports operational efficiency by\n  non-compliance issues on access control, common configuration, and security configuration could be related to public read/write: protecting an enterprise’s cloud environment from development to deployment, and during operations.\n  non-compliance issues on access control, common configuration, and security configuration could be related to public read/write: Risk Events and Detections by Region and by Industry\n  non-compliance issues on access control, common configuration, and security configuration could be related to public read/write: In breaking down the top risk events and detections, we provide a more recent overview by presenting data from July to December\n  non-compliance issues on access control, common configuration, and security configuration could be related to public read/write: 2024. The following section lists the most detected risky events, XDR model hits, and Vision One misconfigurations from Europe,\n  non-compliance issues on access control, common configuration, and security configuration could be related to public read/write: AMEA, the Americas, and the top five industries with the highest trending average CRI.\n  non-compliance issues on access control, common configuration, and security configuration could be related to public read/write: Trend 2025 Cyber Risk Report\n搜尋關鍵字: 統計, 數據, 數字, non-compliance issues on access control, common configuration, and security configuration could be related to public read/write",
      "metadata": {
        "original_table_data": {
          "title": "Camelot_Table_19_21",
          "headers": [
            "non-compliance issues on access control, common configuration, and security configuration could be related to public read/write",
            ""
          ],
          "rows": [
            [
              "settings, overly permissive bucket policies, and lack of encryption and versioning. Enterprises using GCP might also be facing problems",
              ""
            ],
            [
              "with IAM policies and insufficient network security configurations. Meanwhile, Amazon Inspector Findings could mean security issues",
              ""
            ],
            [
              "in workloads and insufficient security assessments.",
              ""
            ],
            [
              "Regular audits and updates to IAM policies, security groups, and network access controls are essential to prevent unauthorized access.",
              ""
            ],
            [
              "Enterprises should also avoid public access settings, implement strict bucket policies, enable server-side encryption and versioning,",
              ""
            ],
            [
              "and review lifecycle policies and logging mechanisms. Organizations should maximize solutions that enhance visibility on their cloud",
              ""
            ],
            [
              "environments for more effective cloud risk management. Trend Vision One™ - Cloud Security12 supports operational efficiency by",
              ""
            ],
            [
              "protecting an enterprise’s cloud environment from development to deployment, and during operations.",
              ""
            ],
            [
              "Risk Events and Detections by Region and by Industry",
              ""
            ],
            [
              "In breaking down the top risk events and detections, we provide a more recent overview by presenting data from July to December",
              ""
            ],
            [
              "2024. The following section lists the most detected risky events, XDR model hits, and Vision One misconfigurations from Europe,",
              ""
            ],
            [
              "AMEA, the Americas, and the top five industries with the highest trending average CRI.",
              ""
            ],
            [
              "Trend 2025 Cyber Risk Report",
              "19"
            ]
          ],
          "source_page": 19,
          "source_file": "data/source/Research-Risk-Report-2025.pdf",
          "table_type": "statistical",
          "confidence": 72.185527028453,
          "extractor_method": "camelot",
          "metadata": {
            "whitespace": 46.42857142857143,
            "order": 1,
            "flavor": "stream"
          }
        },
        "source_page": 19,
        "source_file": "data/source/Research-Risk-Report-2025.pdf",
        "table_type": "statistical",
        "confidence": 72.185527028453,
        "extractor_method": "camelot",
        "conversion_date": "2025-07-18T10:36:09.157648"
      }
    },
    {
      "table_id": "table_37_Camelot_Table_20_22",
      "content": "表格標題: Camelot_Table_20_22\n表格類型: comparison\n來源頁面: 第20頁\n資料提取方法: camelot\n信心度: 100.0%\n表格欄位: Top Vision One, Top Cloud Misconfigurations\n表格內容:\n  Top Vision One: misconfigurations in Europe, Top Cloud Misconfigurations: in Europe\n  Top Vision One: Application Control Settings in, Top Cloud Misconfigurations: Non-Compliant AWS Infrastructure\n  Top Vision One: Trend Vision One™ - Endpoint, Top Cloud Misconfigurations: Configuration\n  Top Vision One: Security Not Optimized\n  Top Vision One: Device Control Settings in, Top Cloud Misconfigurations: Non-Compliant Azure\n  Top Vision One: Endpoint Security Not Optimized, Top Cloud Misconfigurations: Infrastructure Configuration\n  Top Vision One: File Integrity Monitoring (FIM), Top Cloud Misconfigurations: Non-Compliant Amazon S3\n  Top Vision One: Settings in Endpoint Security Not, Top Cloud Misconfigurations: Infrastructure Configuration\n  Top Vision One: Optimized, Top Cloud Misconfigurations: (Access Control)\n  Top Vision One: Log Inspection Settings in, Top Cloud Misconfigurations: Non-Compliant Amazon S3\n  Top Vision One: Endpoint Security Not Optimized, Top Cloud Misconfigurations: Infrastructure Configuration\n搜尋關鍵字: 比較, 對比, 分析, Top Vision One, Top Cloud Misconfigurations, in Europe",
      "metadata": {
        "original_table_data": {
          "title": "Camelot_Table_20_22",
          "headers": [
            "",
            "",
            "",
            "Top Vision One",
            "Top Cloud Misconfigurations"
          ],
          "rows": [
            [
              "",
              "Top Risky Events in Europe",
              "Top XDR Model Hits in Europe",
              "",
              ""
            ],
            [
              "",
              "",
              "",
              "misconfigurations in Europe",
              "in Europe"
            ],
            [
              "1",
              "Risky Cloud App Access",
              "Possible Disabling of Antivirus",
              "Application Control Settings in",
              "Non-Compliant AWS Infrastructure"
            ],
            [
              "",
              "",
              "Software",
              "Trend Vision One™ - Endpoint",
              "Configuration"
            ],
            [
              "",
              "",
              "",
              "Security Not Optimized",
              ""
            ],
            [
              "2",
              "Sandbox Detected Email Threat",
              "Hacking Tool Detection - Blocked",
              "Device Control Settings in",
              "Non-Compliant Azure"
            ],
            [
              "",
              "",
              "",
              "Endpoint Security Not Optimized",
              "Infrastructure Configuration"
            ],
            [
              "3",
              "Stale Microsoft Entra ID Account",
              "Threat Intelligence Sweeping",
              "File Integrity Monitoring (FIM)",
              "Non-Compliant Amazon S3"
            ],
            [
              "",
              "",
              "",
              "Settings in Endpoint Security Not",
              "Infrastructure Configuration"
            ],
            [
              "",
              "",
              "",
              "Optimized",
              "(Access Control)"
            ],
            [
              "4",
              "Advanced Spam Protection -",
              "Possible Spear Phishing Attack via",
              "Log Inspection Settings in",
              "Non-Compliant Amazon S3"
            ],
            [
              "",
              "Policy Violation",
              "Link",
              "Endpoint Security Not Optimized",
              "Infrastructure Configuration"
            ]
          ],
          "source_page": 20,
          "source_file": "data/source/Research-Risk-Report-2025.pdf",
          "table_type": "comparison",
          "confidence": 100.0,
          "extractor_method": "camelot",
          "metadata": {
            "whitespace": 38.46153846153847,
            "order": 1,
            "flavor": "stream"
          }
        },
        "source_page": 20,
        "source_file": "data/source/Research-Risk-Report-2025.pdf",
        "table_type": "comparison",
        "confidence": 100.0,
        "extractor_method": "camelot",
        "conversion_date": "2025-07-18T10:36:09.157689"
      }
    },
    {
      "table_id": "table_38_Camelot_Table_21_23",
      "content": "表格標題: Camelot_Table_21_23\n表格類型: comparison\n來源頁面: 第21頁\n資料提取方法: camelot\n信心度: 100.0%\n表格欄位: Top Vision One, Top Cloud Misconfigurations\n表格內容:\n  Top Vision One: misconfigurations in AMEA, Top Cloud Misconfigurations: in AMEA\n  Top Vision One: Web Reputation Settings in Trend, Top Cloud Misconfigurations: Non-Compliant AWS Infrastructure\n  Top Vision One: Vision One™ - Endpoint Security, Top Cloud Misconfigurations: Configuration\n  Top Vision One: Not Optimized\n  Top Vision One: Device Control Settings in, Top Cloud Misconfigurations: Non-Compliant Amazon S3\n  Top Vision One: Endpoint Security Not Optimized, Top Cloud Misconfigurations: Infrastructure Configuration\n搜尋關鍵字: 比較, 對比, 分析, Top Vision One, Top Cloud Misconfigurations, in AMEA",
      "metadata": {
        "original_table_data": {
          "title": "Camelot_Table_21_23",
          "headers": [
            "",
            "",
            "",
            "Top Vision One",
            "Top Cloud Misconfigurations"
          ],
          "rows": [
            [
              "",
              "Top Risky Events in AMEA",
              "Top XDR Model Hits in AMEA",
              "",
              ""
            ],
            [
              "",
              "",
              "",
              "misconfigurations in AMEA",
              "in AMEA"
            ],
            [
              "1",
              "Risky Cloud App Access",
              "Hacking Tool Detection - Blocked",
              "Web Reputation Settings in Trend",
              "Non-Compliant AWS Infrastructure"
            ],
            [
              "",
              "",
              "",
              "Vision One™ - Endpoint Security",
              "Configuration"
            ],
            [
              "",
              "",
              "",
              "Not Optimized",
              ""
            ],
            [
              "2",
              "Stale Microsoft Entra ID Account",
              "Possible Disabling of Antivirus",
              "Device Control Settings in",
              "Non-Compliant Amazon S3"
            ],
            [
              "",
              "",
              "Software",
              "Endpoint Security Not Optimized",
              "Infrastructure Configuration"
            ]
          ],
          "source_page": 21,
          "source_file": "data/source/Research-Risk-Report-2025.pdf",
          "table_type": "comparison",
          "confidence": 100.00000000000001,
          "extractor_method": "camelot",
          "metadata": {
            "whitespace": 45.0,
            "order": 1,
            "flavor": "stream"
          }
        },
        "source_page": 21,
        "source_file": "data/source/Research-Risk-Report-2025.pdf",
        "table_type": "comparison",
        "confidence": 100.00000000000001,
        "extractor_method": "camelot",
        "conversion_date": "2025-07-18T10:36:09.157719"
      }
    },
    {
      "table_id": "table_39_Camelot_Table_22_24",
      "content": "表格標題: Camelot_Table_22_24\n表格類型: comparison\n來源頁面: 第22頁\n資料提取方法: camelot\n信心度: 100.0%\n表格欄位: Top XDR Model Hits in, Top Vision One, Top Cloud Misconfigurations\n表格內容:\n  Top XDR Model Hits in: Americas, Top Vision One: misconfigurations in Americas, Top Cloud Misconfigurations: in Americas\n  Top XDR Model Hits in: Threat Intelligence Sweeping, Top Vision One: Web Reputation Settings in Trend, Top Cloud Misconfigurations: Non-Compliant AWS Infrastructure\n  Top Vision One: Vision One™ - Endpoint Security, Top Cloud Misconfigurations: Configuration\n  Top Vision One: Not Optimized\n  Top XDR Model Hits in: Possible Disabling of Antivirus, Top Vision One: Endpoint Security Agent Not, Top Cloud Misconfigurations: Non-Compliant Azure\n  Top XDR Model Hits in: Software, Top Vision One: Supported, Top Cloud Misconfigurations: Infrastructure Configuration\n  Top XDR Model Hits in: Hacking Tool Detection - Blocked, Top Vision One: Device Control Settings in, Top Cloud Misconfigurations: Non-Compliant Amazon S3\n  Top Vision One: Endpoint Security Not Optimized, Top Cloud Misconfigurations: Infrastructure Configuration\n搜尋關鍵字: 比較, 對比, 分析, Top XDR Model Hits in, Top Vision One, Top Cloud Misconfigurations, Americas, in Americas",
      "metadata": {
        "original_table_data": {
          "title": "Camelot_Table_22_24",
          "headers": [
            "",
            "",
            "Top XDR Model Hits in",
            "Top Vision One",
            "Top Cloud Misconfigurations"
          ],
          "rows": [
            [
              "",
              "Top Risky Events in Americas",
              "",
              "",
              ""
            ],
            [
              "",
              "",
              "Americas",
              "misconfigurations in Americas",
              "in Americas"
            ],
            [
              "1",
              "Risky Cloud App Access",
              "Threat Intelligence Sweeping",
              "Web Reputation Settings in Trend",
              "Non-Compliant AWS Infrastructure"
            ],
            [
              "",
              "",
              "",
              "Vision One™ - Endpoint Security",
              "Configuration"
            ],
            [
              "",
              "",
              "",
              "Not Optimized",
              ""
            ],
            [
              "2",
              "Stale Microsoft Entra ID Account",
              "Possible Disabling of Antivirus",
              "Endpoint Security Agent Not",
              "Non-Compliant Azure"
            ],
            [
              "",
              "",
              "Software",
              "Supported",
              "Infrastructure Configuration"
            ],
            [
              "3",
              "Sandbox Detected Email Threat",
              "Hacking Tool Detection - Blocked",
              "Device Control Settings in",
              "Non-Compliant Amazon S3"
            ],
            [
              "",
              "",
              "",
              "Endpoint Security Not Optimized",
              "Infrastructure Configuration"
            ]
          ],
          "source_page": 22,
          "source_file": "data/source/Research-Risk-Report-2025.pdf",
          "table_type": "comparison",
          "confidence": 99.99999999999997,
          "extractor_method": "camelot",
          "metadata": {
            "whitespace": 40.0,
            "order": 1,
            "flavor": "stream"
          }
        },
        "source_page": 22,
        "source_file": "data/source/Research-Risk-Report-2025.pdf",
        "table_type": "comparison",
        "confidence": 99.99999999999997,
        "extractor_method": "camelot",
        "conversion_date": "2025-07-18T10:36:09.157756"
      }
    },
    {
      "table_id": "table_40_Camelot_Table_23_25",
      "content": "表格標題: Camelot_Table_23_25\n表格類型: comparison\n來源頁面: 第23頁\n資料提取方法: camelot\n信心度: 100.0%\n表格欄位: Top Vision One\n表格內容:\n  Top Vision One: misconfigurations in the\n  Top Vision One: Agriculture Sector\n  Top Vision One: Web Reputation Settings in Trend\n  Top Vision One: Vision One™ - Endpoint Security\n  Top Vision One: Not Optimized\n  Top Vision One: Intrusion Prevention System (IPS)\n  Top Vision One: Settings in Endpoint Security Not\n  Top Vision One: Optimized\n  Top Vision One: Anti-Malware Settings in Endpoint\n  Top Vision One: Security Not Optimized\n搜尋關鍵字: 比較, 對比, 分析, Top Vision One, Agriculture sector, Agriculture Sector",
      "metadata": {
        "original_table_data": {
          "title": "Camelot_Table_23_25",
          "headers": [
            "",
            "",
            "",
            "Top Vision One",
            ""
          ],
          "rows": [
            [
              "",
              "Top Risky Events in the",
              "Top XDR Model Hits in the",
              "",
              "Top Cloud Misconfigurations"
            ],
            [
              "",
              "",
              "",
              "misconfigurations in the",
              ""
            ],
            [
              "",
              "Agriculture sector",
              "Agriculture Sector",
              "",
              "in the Agriculture Sector"
            ],
            [
              "",
              "",
              "",
              "Agriculture Sector",
              ""
            ],
            [
              "1",
              "Risky Cloud App Access",
              "Threat Intelligence Sweeping",
              "Web Reputation Settings in Trend",
              "Non-Compliant AWS Infrastructure"
            ],
            [
              "",
              "",
              "",
              "Vision One™ - Endpoint Security",
              "Configuration"
            ],
            [
              "",
              "",
              "",
              "Not Optimized",
              ""
            ],
            [
              "2",
              "Data Loss Prevention - Email",
              "Hacking Tool Detection - Blocked",
              "Intrusion Prevention System (IPS)",
              "Non-Compliant Azure"
            ],
            [
              "",
              "Violation",
              "",
              "Settings in Endpoint Security Not",
              "Infrastructure Configuration"
            ],
            [
              "",
              "",
              "",
              "Optimized",
              ""
            ],
            [
              "3",
              "Advanced Spam Protection -",
              "Cybercrime Malware Mitigation",
              "Anti-Malware Settings in Endpoint",
              "Non-Compliant Amazon S3"
            ],
            [
              "",
              "Policy Violation",
              "",
              "Security Not Optimized",
              "Infrastructure Configuration"
            ]
          ],
          "source_page": 23,
          "source_file": "data/source/Research-Risk-Report-2025.pdf",
          "table_type": "comparison",
          "confidence": 99.99999999999993,
          "extractor_method": "camelot",
          "metadata": {
            "whitespace": 47.69230769230769,
            "order": 1,
            "flavor": "stream"
          }
        },
        "source_page": 23,
        "source_file": "data/source/Research-Risk-Report-2025.pdf",
        "table_type": "comparison",
        "confidence": 99.99999999999993,
        "extractor_method": "camelot",
        "conversion_date": "2025-07-18T10:36:09.157791"
      }
    },
    {
      "table_id": "table_41_Camelot_Table_24_26",
      "content": "表格標題: Camelot_Table_24_26\n表格類型: comparison\n來源頁面: 第24頁\n資料提取方法: camelot\n信心度: 100.0%\n表格欄位: Top Vision One, Top Cloud Misconfigurations\n表格內容:\n  Top Vision One: misconfigurations in the, Top Cloud Misconfigurations: in the Communications\n  Top Vision One: Communication Industry, Top Cloud Misconfigurations: Industry\n  Top Vision One: Application Control Settings in, Top Cloud Misconfigurations: Non-Compliant AWS Infrastructure\n  Top Vision One: Trend Vision One™ - Endpoint, Top Cloud Misconfigurations: Configuration\n  Top Vision One: Security Not Optimized\n  Top Vision One: Intrusion Prevention System (IPS), Top Cloud Misconfigurations: Non-Compliant Azure\n  Top Vision One: Settings in Endpoint Security Not, Top Cloud Misconfigurations: Infrastructure Configuration\n  Top Vision One: Optimized\n  Top Vision One: Log Inspection Settings in, Top Cloud Misconfigurations: Non-Compliant Amazon S3\n  Top Vision One: Endpoint Security Not Optimized, Top Cloud Misconfigurations: Infrastructure Configuration\n搜尋關鍵字: 比較, 對比, 分析, Top Vision One, Top Cloud Misconfigurations",
      "metadata": {
        "original_table_data": {
          "title": "Camelot_Table_24_26",
          "headers": [
            "",
            "",
            "",
            "Top Vision One",
            "Top Cloud Misconfigurations"
          ],
          "rows": [
            [
              "",
              "Top Risky Events in the",
              "Top XDR Model Hits in the",
              "",
              ""
            ],
            [
              "",
              "",
              "",
              "misconfigurations in the",
              "in the Communications"
            ],
            [
              "",
              "Communications Industry",
              "Communication Industry",
              "",
              ""
            ],
            [
              "",
              "",
              "",
              "Communication Industry",
              "Industry"
            ],
            [
              "1",
              "Sandbox Detected Email Threat",
              "Possible Disabling of Antivirus",
              "Application Control Settings in",
              "Non-Compliant AWS Infrastructure"
            ],
            [
              "",
              "",
              "Software",
              "Trend Vision One™ - Endpoint",
              "Configuration"
            ],
            [
              "",
              "",
              "",
              "Security Not Optimized",
              ""
            ],
            [
              "2",
              "Risky Cloud App Access",
              "Hacking Tool Detection - Blocked",
              "Intrusion Prevention System (IPS)",
              "Non-Compliant Azure"
            ],
            [
              "",
              "",
              "",
              "Settings in Endpoint Security Not",
              "Infrastructure Configuration"
            ],
            [
              "",
              "",
              "",
              "Optimized",
              ""
            ],
            [
              "3",
              "Data Loss Prevention - Email",
              "Threat Intelligence Sweeping",
              "Log Inspection Settings in",
              "Non-Compliant Amazon S3"
            ],
            [
              "",
              "Violation",
              "",
              "Endpoint Security Not Optimized",
              "Infrastructure Configuration"
            ]
          ],
          "source_page": 24,
          "source_file": "data/source/Research-Risk-Report-2025.pdf",
          "table_type": "comparison",
          "confidence": 100.00000000000001,
          "extractor_method": "camelot",
          "metadata": {
            "whitespace": 46.15384615384615,
            "order": 1,
            "flavor": "stream"
          }
        },
        "source_page": 24,
        "source_file": "data/source/Research-Risk-Report-2025.pdf",
        "table_type": "comparison",
        "confidence": 100.00000000000001,
        "extractor_method": "camelot",
        "conversion_date": "2025-07-18T10:36:09.157830"
      }
    },
    {
      "table_id": "table_42_Camelot_Table_25_27",
      "content": "表格標題: Camelot_Table_25_27\n表格類型: comparison\n來源頁面: 第25頁\n資料提取方法: camelot\n信心度: 100.0%\n表格欄位: Top Vision One\n表格內容:\n  Top Vision One: misconfigurations in the\n  Top Vision One: Education Sector\n  Top Vision One: Endpoint Sensor Settings in Trend\n  Top Vision One: Vision One™ - Endpoint Security\n  Top Vision One: Not Optimized\n  Top Vision One: Anti-Malware Scanning Settings in\n  Top Vision One: Endpoint Security Not Optimized\n  Top Vision One: Endpoint Security Agent Not\n  Top Vision One: Supported\n搜尋關鍵字: 比較, 對比, 分析, Top Vision One, Education Sector, Education Sector",
      "metadata": {
        "original_table_data": {
          "title": "Camelot_Table_25_27",
          "headers": [
            "",
            "",
            "",
            "Top Vision One",
            ""
          ],
          "rows": [
            [
              "",
              "Top Risky Events in the",
              "Top XDR Model Hits in the",
              "",
              "Top Cloud Misconfigurations"
            ],
            [
              "",
              "",
              "",
              "misconfigurations in the",
              ""
            ],
            [
              "",
              "Education Sector",
              "Education Sector",
              "",
              "in the Education Sector"
            ],
            [
              "",
              "",
              "",
              "Education Sector",
              ""
            ],
            [
              "1",
              "Stale Microsoft Entra ID Account",
              "Threat Intelligence Sweeping",
              "Endpoint Sensor Settings in Trend",
              "Non-Compliant AWS Infrastructure"
            ],
            [
              "",
              "",
              "",
              "Vision One™ - Endpoint Security",
              "Configuration"
            ],
            [
              "",
              "",
              "",
              "Not Optimized",
              ""
            ],
            [
              "2",
              "Risky Cloud App Access",
              "Hacking Tool Detection - Blocked",
              "Anti-Malware Scanning Settings in",
              "Non-Compliant Azure"
            ],
            [
              "",
              "",
              "",
              "Endpoint Security Not Optimized",
              "Infrastructure Configuration"
            ],
            [
              "3",
              "Microsoft Entra ID Account with",
              "Possible Disabling of Antivirus",
              "Endpoint Security Agent Not",
              "Non-Compliant Amazon S3"
            ],
            [
              "",
              "Weak Sign-In Security Policy -",
              "Software",
              "Supported",
              "Infrastructure Configuration"
            ]
          ],
          "source_page": 25,
          "source_file": "data/source/Research-Risk-Report-2025.pdf",
          "table_type": "comparison",
          "confidence": 100.00000000000001,
          "extractor_method": "camelot",
          "metadata": {
            "whitespace": 45.0,
            "order": 1,
            "flavor": "stream"
          }
        },
        "source_page": 25,
        "source_file": "data/source/Research-Risk-Report-2025.pdf",
        "table_type": "comparison",
        "confidence": 100.00000000000001,
        "extractor_method": "camelot",
        "conversion_date": "2025-07-18T10:36:09.157864"
      }
    },
    {
      "table_id": "table_43_Camelot_Table_26_28",
      "content": "表格標題: Camelot_Table_26_28\n表格類型: comparison\n來源頁面: 第26頁\n資料提取方法: camelot\n信心度: 99.8%\n表格欄位: Top Vision One\n表格內容:\n  Top Vision One: misconfigurations in the\n  Top Vision One: Energy Sector\n  Top Vision One: Behavior Monitoring Settings in\n  Top Vision One: Trend Vision One™ - Endpoint\n  Top Vision One: Security Not Optimized\n  Top Vision One: Predictive Machine Learning\n  Top Vision One: Settings in Endpoint Security Not\n  Top Vision One: Optimized\n  Top Vision One: Firewall Settings in Endpoint\n  Top Vision One: Security Not Optimized\n搜尋關鍵字: 比較, 對比, 分析, Top Vision One, Energy Sector, Energy Sector",
      "metadata": {
        "original_table_data": {
          "title": "Camelot_Table_26_28",
          "headers": [
            "",
            "",
            "",
            "Top Vision One",
            ""
          ],
          "rows": [
            [
              "",
              "Top Risky Events in the",
              "Top XDR Model Hits in the",
              "",
              "Top Cloud Misconfigurations"
            ],
            [
              "",
              "",
              "",
              "misconfigurations in the",
              ""
            ],
            [
              "",
              "Energy Sector",
              "Energy Sector",
              "",
              "in the Energy Sector"
            ],
            [
              "",
              "",
              "",
              "Energy Sector",
              ""
            ],
            [
              "1",
              "Sandbox Detected Email Threat",
              "Hacking Tool Detection - Blocked",
              "Behavior Monitoring Settings in",
              "Non-Compliant AWS Infrastructure"
            ],
            [
              "",
              "",
              "",
              "Trend Vision One™ - Endpoint",
              "Configuration"
            ],
            [
              "",
              "",
              "",
              "Security Not Optimized",
              ""
            ],
            [
              "2",
              "Risky Cloud App Access",
              "Possible Disabling of Antivirus",
              "Predictive Machine Learning",
              "Non-Compliant Azure"
            ],
            [
              "",
              "",
              "Software",
              "Settings in Endpoint Security Not",
              "Infrastructure Configuration"
            ],
            [
              "",
              "",
              "",
              "Optimized",
              ""
            ],
            [
              "3",
              "Stale Microsoft Entra ID Account",
              "[Heuristic Attribute] Trojan Spy",
              "Firewall Settings in Endpoint",
              "Non-Compliant Amazon S3"
            ],
            [
              "",
              "",
              "File Detection",
              "Security Not Optimized",
              "Infrastructure Configuration"
            ]
          ],
          "source_page": 26,
          "source_file": "data/source/Research-Risk-Report-2025.pdf",
          "table_type": "comparison",
          "confidence": 99.84574289393218,
          "extractor_method": "camelot",
          "metadata": {
            "whitespace": 47.69230769230769,
            "order": 1,
            "flavor": "stream"
          }
        },
        "source_page": 26,
        "source_file": "data/source/Research-Risk-Report-2025.pdf",
        "table_type": "comparison",
        "confidence": 99.84574289393218,
        "extractor_method": "camelot",
        "conversion_date": "2025-07-18T10:36:09.157912"
      }
    },
    {
      "table_id": "table_44_Camelot_Table_27_29",
      "content": "表格標題: Camelot_Table_27_29\n表格類型: comparison\n來源頁面: 第27頁\n資料提取方法: camelot\n信心度: 100.0%\n表格欄位: Top Vision One\n表格內容:\n  Top Vision One: misconfigurations in the\n  Top Vision One: Insurance Industry\n  Top Vision One: Anti-Malware Scanning Settings\n  Top Vision One: in Trend Vision One™ - Endpoint\n  Top Vision One: Security Not Optimized\n  Top Vision One: Application Control Settings in\n  Top Vision One: Endpoint Security Not Optimized\n搜尋關鍵字: 比較, 對比, 分析, Top Vision One, Insurance Industry, Insurance Industry",
      "metadata": {
        "original_table_data": {
          "title": "Camelot_Table_27_29",
          "headers": [
            "",
            "",
            "",
            "Top Vision One",
            ""
          ],
          "rows": [
            [
              "",
              "Top Risky Events in the",
              "Top XDR Model Hits in the",
              "",
              "Top Cloud Misconfigurations"
            ],
            [
              "",
              "",
              "",
              "misconfigurations in the",
              ""
            ],
            [
              "",
              "Insurance Industry",
              "Insurance Industry",
              "",
              "in the Insurance Industry"
            ],
            [
              "",
              "",
              "",
              "Insurance Industry",
              ""
            ],
            [
              "1",
              "Risky Cloud App Access",
              "Possible Disabling of Antivirus",
              "Anti-Malware Scanning Settings",
              "Non-Compliant AWS Infrastructure"
            ],
            [
              "",
              "",
              "Software",
              "in Trend Vision One™ - Endpoint",
              "Configuration"
            ],
            [
              "",
              "",
              "",
              "Security Not Optimized",
              ""
            ],
            [
              "2",
              "Microsoft Entra ID Account with",
              "Hacking Tool Detection",
              "Application Control Settings in",
              "Non-Compliant Azure"
            ],
            [
              "",
              "Weak Sign-In Security Policy -",
              "",
              "Endpoint Security Not Optimized",
              "Infrastructure Configuration"
            ]
          ],
          "source_page": 27,
          "source_file": "data/source/Research-Risk-Report-2025.pdf",
          "table_type": "comparison",
          "confidence": 100.00000000000004,
          "extractor_method": "camelot",
          "metadata": {
            "whitespace": 48.0,
            "order": 1,
            "flavor": "stream"
          }
        },
        "source_page": 27,
        "source_file": "data/source/Research-Risk-Report-2025.pdf",
        "table_type": "comparison",
        "confidence": 100.00000000000004,
        "extractor_method": "camelot",
        "conversion_date": "2025-07-18T10:36:09.157946"
      }
    },
    {
      "table_id": "table_45_Camelot_Table_28_30",
      "content": "表格標題: Camelot_Table_28_30\n表格類型: comparison\n來源頁面: 第28頁\n資料提取方法: camelot\n信心度: 100.0%\n表格欄位: Home Network Security Top Events\n表格內容:\n  Home Network Security Top Events: Rule name\n  Home Network Security Top Events: RDP Brute Force Login\n  Home Network Security Top Events: MISC Bitcoin/LiteCoin/Dogecoin Mining Activity -1\n  Home Network Security Top Events: WEB Hikvision Product Web Server Command Injection -1.1 (CVE-2021-36260)\n  Home Network Security Top Events: TELNET Default Password Login -6\n  Home Network Security Top Events: WEB HTTP Invalid Content-Length -2\n  Home Network Security Top Events: MISC Cryptocurrency Monero Mining Activity -1\n  Home Network Security Top Events: SSH Brute Force Login\n  Home Network Security Top Events: WEB Remote Command Execution via Shell Script -1.h\n  Home Network Security Top Events: SMB Microsoft Windows SMB Server SMBv1 CVE-2017-0147 Information Disclosure -1\n  Home Network Security Top Events: MALWARE Suspicious IoT Worm TELNET Activity -1\n搜尋關鍵字: 比較, 對比, 分析, Home Network Security Top Events, Rule name, Rule ID, 1059803, 1059684",
      "metadata": {
        "original_table_data": {
          "title": "Camelot_Table_28_30",
          "headers": [
            "Home Network Security Top Events",
            ""
          ],
          "rows": [
            [
              "Rule name",
              "Rule ID"
            ],
            [
              "RDP Brute Force Login",
              "1059803"
            ],
            [
              "MISC Bitcoin/LiteCoin/Dogecoin Mining Activity -1",
              "1059684"
            ],
            [
              "WEB Hikvision Product Web Server Command Injection -1.1 (CVE-2021-36260)",
              "1139937"
            ],
            [
              "TELNET Default Password Login -6",
              "1133113"
            ],
            [
              "WEB HTTP Invalid Content-Length -2",
              "1139797"
            ],
            [
              "MISC Cryptocurrency Monero Mining Activity -1",
              "1134390"
            ],
            [
              "SSH Brute Force Login",
              "1059418"
            ],
            [
              "WEB Remote Command Execution via Shell Script -1.h",
              "1133253"
            ],
            [
              "SMB Microsoft Windows SMB Server SMBv1 CVE-2017-0147 Information Disclosure -1",
              "1133710"
            ],
            [
              "MALWARE Suspicious IoT Worm TELNET Activity -1",
              "1133148"
            ]
          ],
          "source_page": 28,
          "source_file": "data/source/Research-Risk-Report-2025.pdf",
          "table_type": "comparison",
          "confidence": 99.99999999999997,
          "extractor_method": "camelot",
          "metadata": {
            "whitespace": 4.166666666666666,
            "order": 1,
            "flavor": "stream"
          }
        },
        "source_page": 28,
        "source_file": "data/source/Research-Risk-Report-2025.pdf",
        "table_type": "comparison",
        "confidence": 99.99999999999997,
        "extractor_method": "camelot",
        "conversion_date": "2025-07-18T10:36:09.157977"
      }
    },
    {
      "table_id": "table_46_Camelot_Table_29_31",
      "content": "表格標題: Camelot_Table_29_31\n表格類型: time_series\n來源頁面: 第29頁\n資料提取方法: camelot\n信心度: 75.7%\n表格欄位: Our telemetry shows that attackers continue to rely on time-tested techniques to gain an initial foothold into their victim’s systems\n表格內容:\n  Our telemetry shows that attackers continue to rely on time-tested techniques to gain an initial foothold into their victim’s systems: with the top detected event being brute force login. There is also a significant amount of cryptocurrency mining activity that can\n  Our telemetry shows that attackers continue to rely on time-tested techniques to gain an initial foothold into their victim’s systems: impact enterprises in terms of information disclosure.\n  Our telemetry shows that attackers continue to rely on time-tested techniques to gain an initial foothold into their victim’s systems: The vulnerability found in Hikvision cameras13 (CVE-2021-3626014) is notably high in the detections list; when this vulnerability is\n  Our telemetry shows that attackers continue to rely on time-tested techniques to gain an initial foothold into their victim’s systems: exploited, an attacker can launch a command injection attack by sending messages with malicious commands. Considering that this\n  Our telemetry shows that attackers continue to rely on time-tested techniques to gain an initial foothold into their victim’s systems: vulnerability has been around since 2021, enterprises should allot effort into employee cybersecurity and risk education so they can\n  Our telemetry shows that attackers continue to rely on time-tested techniques to gain an initial foothold into their victim’s systems: maximize tools to secure their personal and home devices. These devices can be an extension of the enterprise’s attack surface if they\n  Our telemetry shows that attackers continue to rely on time-tested techniques to gain an initial foothold into their victim’s systems: connect to the organization’s network.\n  Our telemetry shows that attackers continue to rely on time-tested techniques to gain an initial foothold into their victim’s systems: Trend 2025 Cyber Risk Report\n搜尋關鍵字: Our telemetry shows that attackers continue to rely on time-tested techniques to gain an initial foothold into their victim’s systems",
      "metadata": {
        "original_table_data": {
          "title": "Camelot_Table_29_31",
          "headers": [
            "Our telemetry shows that attackers continue to rely on time-tested techniques to gain an initial foothold into their victim’s systems",
            ""
          ],
          "rows": [
            [
              "with the top detected event being brute force login. There is also a significant amount of cryptocurrency mining activity that can",
              ""
            ],
            [
              "impact enterprises in terms of information disclosure.",
              ""
            ],
            [
              "The vulnerability found in Hikvision cameras13 (CVE-2021-3626014) is notably high in the detections list; when this vulnerability is",
              ""
            ],
            [
              "exploited, an attacker can launch a command injection attack by sending messages with malicious commands. Considering that this",
              ""
            ],
            [
              "vulnerability has been around since 2021, enterprises should allot effort into employee cybersecurity and risk education so they can",
              ""
            ],
            [
              "maximize tools to secure their personal and home devices. These devices can be an extension of the enterprise’s attack surface if they",
              ""
            ],
            [
              "connect to the organization’s network.",
              ""
            ],
            [
              "Trend 2025 Cyber Risk Report",
              "29"
            ]
          ],
          "source_page": 29,
          "source_file": "data/source/Research-Risk-Report-2025.pdf",
          "table_type": "time_series",
          "confidence": 75.71612585124389,
          "extractor_method": "camelot",
          "metadata": {
            "whitespace": 44.44444444444444,
            "order": 1,
            "flavor": "stream"
          }
        },
        "source_page": 29,
        "source_file": "data/source/Research-Risk-Report-2025.pdf",
        "table_type": "time_series",
        "confidence": 75.71612585124389,
        "extractor_method": "camelot",
        "conversion_date": "2025-07-18T10:36:09.158008"
      }
    },
    {
      "table_id": "table_47_Camelot_Table_30_32",
      "content": "表格標題: Camelot_Table_30_32\n表格類型: general\n來源頁面: 第30頁\n資料提取方法: camelot\n信心度: 100.0%\n表格欄位: Vulnerabilities,\n表格內容:\n  Vulnerabilities,: Patch, and\n  Vulnerabilities,: Response Data\n搜尋關鍵字: Vulnerabilities,, Patch, and, Response Data",
      "metadata": {
        "original_table_data": {
          "title": "Camelot_Table_30_32",
          "headers": [
            "Vulnerabilities,"
          ],
          "rows": [
            [
              "Patch, and"
            ],
            [
              "Response Data"
            ]
          ],
          "source_page": 30,
          "source_file": "data/source/Research-Risk-Report-2025.pdf",
          "table_type": "general",
          "confidence": 100.0,
          "extractor_method": "camelot",
          "metadata": {
            "whitespace": 0.0,
            "order": 1,
            "flavor": "stream"
          }
        },
        "source_page": 30,
        "source_file": "data/source/Research-Risk-Report-2025.pdf",
        "table_type": "general",
        "confidence": 100.0,
        "extractor_method": "camelot",
        "conversion_date": "2025-07-18T10:36:09.158024"
      }
    },
    {
      "table_id": "table_48_Camelot_Table_31_33",
      "content": "表格標題: Camelot_Table_31_33\n表格類型: comparison\n來源頁面: 第31頁\n資料提取方法: camelot\n信心度: 100.0%\n表格欄位: Top riskiest CVEs, most, NIST Severity\n表格內容:\n  Top riskiest CVEs, most: detected and unpatched, NIST Severity: Score\n  Top riskiest CVEs, most: CVE-2024-2135715, NIST Severity: 8.1 High\n  Top riskiest CVEs, most: CVE-2024-3008616, NIST Severity: 7\n.8 High\n  Top riskiest CVEs, most: CVE-2024-3008217, NIST Severity: 7\n.8 High\n  Top riskiest CVEs, most: CVE-2024-3008718, NIST Severity: 7\n.8 High\n  Top riskiest CVEs, most: CVE-2024-3525019, NIST Severity: 7\n.8 High\n  Top riskiest CVEs, most: CVE-2024-3009120, NIST Severity: 7\n.8 High\n  Top riskiest CVEs, most: CVE-2024-3004921, NIST Severity: 7\n.8 High\n  Top riskiest CVEs, most: CVE-2024-3008422, NIST Severity: 7\n.0 High\n搜尋關鍵字: 比較, 對比, 分析, Top riskiest CVEs, most, NIST Severity, Score, CVE-2024-2135715, 8.1 High, CVE-2024-3008616, 7\n.8 High",
      "metadata": {
        "original_table_data": {
          "title": "Camelot_Table_31_33",
          "headers": [
            "",
            "Top riskiest CVEs, most",
            "NIST Severity"
          ],
          "rows": [
            [
              "",
              "detected and unpatched",
              "Score"
            ],
            [
              "1",
              "CVE-2024-2135715",
              "8.1 High"
            ],
            [
              "2",
              "CVE-2024-3008616",
              "7\n.8 High"
            ],
            [
              "3",
              "CVE-2024-3008217",
              "7\n.8 High"
            ],
            [
              "4",
              "CVE-2024-3008718",
              "7\n.8 High"
            ],
            [
              "5",
              "CVE-2024-3525019",
              "7\n.8 High"
            ],
            [
              "6",
              "CVE-2024-3009120",
              "7\n.8 High"
            ],
            [
              "7",
              "CVE-2024-3004921",
              "7\n.8 High"
            ],
            [
              "8",
              "CVE-2024-3008422",
              "7\n.0 High"
            ]
          ],
          "source_page": 31,
          "source_file": "data/source/Research-Risk-Report-2025.pdf",
          "table_type": "comparison",
          "confidence": 100.00000000000001,
          "extractor_method": "camelot",
          "metadata": {
            "whitespace": 6.666666666666667,
            "order": 1,
            "flavor": "stream"
          }
        },
        "source_page": 31,
        "source_file": "data/source/Research-Risk-Report-2025.pdf",
        "table_type": "comparison",
        "confidence": 100.00000000000001,
        "extractor_method": "camelot",
        "conversion_date": "2025-07-18T10:36:09.158056"
      }
    },
    {
      "table_id": "table_49_Camelot_Table_32_34",
      "content": "表格標題: Camelot_Table_32_34\n表格類型: general\n來源頁面: 第32頁\n資料提取方法: camelot\n信心度: 100.0%\n表格欄位: 35\n表格內容:\n  35: 30\n  35: 25\n  35: 20\n  35: 15\n  35: 10\n搜尋關鍵字: 35, 29.2, 30, 27.5, 23.5",
      "metadata": {
        "original_table_data": {
          "title": "Camelot_Table_32_34",
          "headers": [
            "35",
            "",
            "",
            ""
          ],
          "rows": [
            [
              "",
              "",
              "",
              "29.2"
            ],
            [
              "30",
              "",
              "27.5",
              ""
            ],
            [
              "",
              "23.5",
              "",
              ""
            ],
            [
              "25",
              "",
              "",
              ""
            ],
            [
              "20",
              "",
              "",
              ""
            ],
            [
              "15",
              "",
              "",
              ""
            ],
            [
              "10",
              "",
              "",
              ""
            ]
          ],
          "source_page": 32,
          "source_file": "data/source/Research-Risk-Report-2025.pdf",
          "table_type": "general",
          "confidence": 100.00000000000001,
          "extractor_method": "camelot",
          "metadata": {
            "whitespace": 75.0,
            "order": 1,
            "flavor": "stream"
          }
        },
        "source_page": 32,
        "source_file": "data/source/Research-Risk-Report-2025.pdf",
        "table_type": "general",
        "confidence": 100.00000000000001,
        "extractor_method": "camelot",
        "conversion_date": "2025-07-18T10:36:09.158081"
      }
    },
    {
      "table_id": "table_50_Camelot_Table_33_35",
      "content": "表格標題: Camelot_Table_33_35\n表格類型: statistical\n來源頁面: 第33頁\n資料提取方法: camelot\n信心度: 100.0%\n表格欄位: Top Industries with the, Top Industries with the\n表格內容:\n  Top Industries with the: fastest average MTTP, Top Industries with the: slowest average MTTP\n  Top Industries with the: 19.0, Top Industries with the: 41.5\n  Top Industries with the: 19.7, Top Industries with the: 38.0\n  Top Industries with the: 22.1, Top Industries with the: 35.1\n  Top Industries with the: 23.7, Top Industries with the: 34.1\n  Top Industries with the: 23.8, Top Industries with the: 30.6\n  Top Industries with the: 24.2, Top Industries with the: 30.4\n  Top Industries with the: 24.6, Top Industries with the: 30.2\n  Top Industries with the: 25.0, Top Industries with the: 29.3\n  Top Industries with the: 26.2, Top Industries with the: 28.7\n  Top Industries with the: 27.0, Top Industries with the: 28.0\n搜尋關鍵字: 統計, 數據, 數字, Top Industries with the, Top Industries with the, Non-proﬁt, 19.0, Healthcare, 41.5",
      "metadata": {
        "original_table_data": {
          "title": "Camelot_Table_33_35",
          "headers": [
            "",
            "Top Industries with the",
            "",
            "Top Industries with the"
          ],
          "rows": [
            [
              "",
              "fastest average MTTP",
              "",
              "slowest average MTTP"
            ],
            [
              "Non-proﬁt",
              "",
              "",
              ""
            ],
            [
              "",
              "19.0",
              "Healthcare",
              "41.5"
            ],
            [
              "Service",
              "",
              "Telecommunications",
              ""
            ],
            [
              "",
              "19.7",
              "",
              "38.0"
            ],
            [
              "Technology",
              "",
              "Financial Services",
              ""
            ],
            [
              "",
              "22.1",
              "",
              "35.1"
            ],
            [
              "Agriculture",
              "",
              "Communications",
              ""
            ],
            [
              "",
              "23.7",
              "",
              "34.1"
            ],
            [
              "Entertainment",
              "",
              "Insurance",
              ""
            ],
            [
              "",
              "23.8",
              "",
              "30.6"
            ],
            [
              "",
              "",
              "Government and",
              ""
            ],
            [
              "Utilities",
              "",
              "",
              ""
            ],
            [
              "",
              "24.2",
              "",
              "30.4"
            ],
            [
              "",
              "",
              "Public Services",
              ""
            ],
            [
              "Construction",
              "",
              "Hospitality and Leisure",
              ""
            ],
            [
              "",
              "24.6",
              "",
              "30.2"
            ],
            [
              "Retail",
              "",
              "Manufacturing",
              ""
            ],
            [
              "",
              "25.0",
              "",
              "29.3"
            ],
            [
              "Transportation",
              "",
              "Education",
              ""
            ],
            [
              "",
              "26.2",
              "",
              "28.7"
            ],
            [
              "Pharmaceuticals",
              "",
              "Energy",
              ""
            ],
            [
              "",
              "27.0",
              "",
              "28.0"
            ]
          ],
          "source_page": 33,
          "source_file": "data/source/Research-Risk-Report-2025.pdf",
          "table_type": "statistical",
          "confidence": 100.00000000000009,
          "extractor_method": "camelot",
          "metadata": {
            "whitespace": 53.125,
            "order": 1,
            "flavor": "stream"
          }
        },
        "source_page": 33,
        "source_file": "data/source/Research-Risk-Report-2025.pdf",
        "table_type": "statistical",
        "confidence": 100.00000000000009,
        "extractor_method": "camelot",
        "conversion_date": "2025-07-18T10:36:09.158132"
      }
    },
    {
      "table_id": "table_51_Camelot_Table_34_36",
      "content": "表格標題: Camelot_Table_34_36\n表格類型: statistical\n來源頁面: 第34頁\n資料提取方法: camelot\n信心度: 81.5%\n表格欄位: Non-profit organizations have the fastest MTTP, followed by the service and technology industries. Other industries, such as the\n表格內容:\n  Non-profit organizations have the fastest MTTP, followed by the service and technology industries. Other industries, such as the: agriculture sector, construction, and transportation industries, also record good average patch time compared to other industries.\n  Non-profit organizations have the fastest MTTP, followed by the service and technology industries. Other industries, such as the: Their inclusion in the sectors with highest risk indices suggest that their risk could be caused by attack risk factors such as risky or\n  Non-profit organizations have the fastest MTTP, followed by the service and technology industries. Other industries, such as the: malicious events detected at endpoints and connected applications, or security configuration risk factors.\n  Non-profit organizations have the fastest MTTP, followed by the service and technology industries. Other industries, such as the: Average MTTP by company size\n  Non-profit organizations have the fastest MTTP, followed by the service and technology industries. Other industries, such as the: Trend 2025 Cyber Risk Report\n搜尋關鍵字: 統計, 數據, 數字, Non-profit organizations have the fastest MTTP, followed by the service and technology industries. Other industries, such as the",
      "metadata": {
        "original_table_data": {
          "title": "Camelot_Table_34_36",
          "headers": [
            "Non-profit organizations have the fastest MTTP, followed by the service and technology industries. Other industries, such as the",
            "",
            "",
            "",
            "",
            "",
            "",
            "",
            "",
            ""
          ],
          "rows": [
            [
              "agriculture sector, construction, and transportation industries, also record good average patch time compared to other industries.",
              "",
              "",
              "",
              "",
              "",
              "",
              "",
              "",
              ""
            ],
            [
              "Their inclusion in the sectors with highest risk indices suggest that their risk could be caused by attack risk factors such as risky or",
              "",
              "",
              "",
              "",
              "",
              "",
              "",
              "",
              ""
            ],
            [
              "malicious events detected at endpoints and connected applications, or security configuration risk factors.",
              "",
              "",
              "",
              "",
              "",
              "",
              "",
              "",
              ""
            ],
            [
              "Average MTTP by company size",
              "",
              "",
              "",
              "",
              "",
              "",
              "",
              "",
              ""
            ],
            [
              "",
              "50",
              "",
              "",
              "",
              "",
              "",
              "",
              "",
              ""
            ],
            [
              "",
              "",
              "",
              "",
              "",
              "",
              "",
              "",
              "41.3",
              ""
            ],
            [
              "",
              "",
              "",
              "",
              "",
              "",
              "36.6",
              "37.3",
              "",
              ""
            ],
            [
              "",
              "40",
              "",
              "",
              "",
              "",
              "",
              "",
              "",
              ""
            ],
            [
              "",
              "",
              "",
              "",
              "28.8",
              "29.3",
              "",
              "",
              "",
              ""
            ],
            [
              "",
              "30",
              "",
              "",
              "",
              "",
              "",
              "",
              "",
              ""
            ],
            [
              "",
              "",
              "22.0",
              "22.5",
              "",
              "",
              "",
              "",
              "",
              ""
            ],
            [
              "",
              "20",
              "",
              "",
              "",
              "",
              "",
              "",
              "",
              ""
            ],
            [
              "",
              "10",
              "",
              "",
              "",
              "",
              "",
              "",
              "",
              ""
            ],
            [
              "",
              "0",
              "",
              "",
              "",
              "",
              "",
              "",
              "",
              ""
            ],
            [
              "",
              "",
              "1 –",
              "101 –",
              "501 –",
              "1,001 –",
              "5,001 –",
              "2,001 –",
              "More than",
              ""
            ],
            [
              "",
              "",
              "100",
              "500",
              "1,000",
              "2,000",
              "10,000",
              "5,000",
              "10,000",
              ""
            ],
            [
              "",
              "",
              "",
              "",
              "",
              "",
              "",
              "(February 2024 - December 2024)",
              "",
              ""
            ],
            [
              "",
              "Larger enterprises often operate with more complex networks, which make for a demanding task of patching vulnerabilities. Trend",
              "",
              "",
              "",
              "",
              "",
              "",
              "",
              ""
            ],
            [
              "",
              "Vision One simplifies this challenge by centralizing cyber risk management, and mitigating risk with automated actions and AI guided",
              "",
              "",
              "",
              "",
              "",
              "",
              "",
              ""
            ],
            [
              "",
              "remediation that allows security teams to act fast with configurable playbooks that can orchestrate across multiple security controls.",
              "",
              "",
              "",
              "",
              "",
              "",
              "",
              ""
            ],
            [
              "Trend 2025 Cyber Risk Report",
              "",
              "",
              "",
              "",
              "",
              "",
              "",
              "",
              "34"
            ]
          ],
          "source_page": 34,
          "source_file": "data/source/Research-Risk-Report-2025.pdf",
          "table_type": "statistical",
          "confidence": 81.53391483846603,
          "extractor_method": "camelot",
          "metadata": {
            "whitespace": 82.72727272727273,
            "order": 1,
            "flavor": "stream"
          }
        },
        "source_page": 34,
        "source_file": "data/source/Research-Risk-Report-2025.pdf",
        "table_type": "statistical",
        "confidence": 81.53391483846603,
        "extractor_method": "camelot",
        "conversion_date": "2025-07-18T10:36:09.158187"
      }
    },
    {
      "table_id": "table_52_Camelot_Table_35_37",
      "content": "表格標題: Camelot_Table_35_37\n表格類型: comparison\n來源頁面: 第35頁\n資料提取方法: camelot\n信心度: 97.8%\n表格欄位: Overall Top Response Playbooks in Use\n表格內容:\n  Overall Top Response Playbooks in Use: 1\n  Overall Top Response Playbooks in Use: 2\n  Overall Top Response Playbooks in Use: 3\n  Overall Top Response Playbooks in Use: 4\n  Overall Top Response Playbooks in Use: 5\n  Overall Top Response Playbooks in Use: 6\n  Overall Top Response Playbooks in Use: 7\n  Overall Top Response Playbooks in Use: 8\n  Overall Top Response Playbooks in Use: 9\n  Overall Top Response Playbooks in Use: 10\n搜尋關鍵字: 比較, 對比, 分析, Overall Top Response Playbooks in Use, Custom",
      "metadata": {
        "original_table_data": {
          "title": "Camelot_Table_35_37",
          "headers": [
            "Overall Top Response Playbooks in Use",
            ""
          ],
          "rows": [
            [
              "1",
              "Automated Response Playbook"
            ],
            [
              "2",
              "Custom"
            ],
            [
              "3",
              "CVEs with Global Exploit Activity - Internal Assets"
            ],
            [
              "4",
              "CVEs with High or Medium Global Exploit Activity"
            ],
            [
              "5",
              "Risk Event Response"
            ],
            [
              "6",
              "Account Response"
            ],
            [
              "7",
              "CVEs with High or Medium Global Exploit Activity - Internet-Facing Assets"
            ],
            [
              "8",
              "CVEs with Global Exploit Activity - Internet-Facing Assets"
            ],
            [
              "9",
              "Account Exposure - Weak Sign-in Policies, Excessive Admin Accounts, and Stale Accounts"
            ],
            [
              "10",
              "Endpoint Response"
            ]
          ],
          "source_page": 35,
          "source_file": "data/source/Research-Risk-Report-2025.pdf",
          "table_type": "comparison",
          "confidence": 97.75656592313815,
          "extractor_method": "camelot",
          "metadata": {
            "whitespace": 4.545454545454546,
            "order": 1,
            "flavor": "stream"
          }
        },
        "source_page": 35,
        "source_file": "data/source/Research-Risk-Report-2025.pdf",
        "table_type": "comparison",
        "confidence": 97.75656592313815,
        "extractor_method": "camelot",
        "conversion_date": "2025-07-18T10:36:09.158214"
      }
    },
    {
      "table_id": "table_53_Camelot_Table_36_38",
      "content": "表格標題: Camelot_Table_36_38\n表格類型: general\n來源頁面: 第36頁\n資料提取方法: camelot\n信心度: 100.0%\n表格欄位: The top response playbook is the automated response to Vision One workbench alerts, followed by custom playbooks; enterprises are\n表格內容:\n  The top response playbook is the automated response to Vision One workbench alerts, followed by custom playbooks; enterprises are: maximizing both the ready-made AI-powered playbooks and the customization capability of the platform in automating response to\n  The top response playbook is the automated response to Vision One workbench alerts, followed by custom playbooks; enterprises are: XDR alerts. The third and fourth playbooks, as well as the seventh and eighth playbooks, are updated versions of each and making it to\n  The top response playbook is the automated response to Vision One workbench alerts, followed by custom playbooks; enterprises are: the top detected playbooks in use indicate that enterprises recognize the importance of patching vulnerabilities and are focusing on\n  The top response playbook is the automated response to Vision One workbench alerts, followed by custom playbooks; enterprises are: automating their detection.\n搜尋關鍵字: The top response playbook is the automated response to Vision One workbench alerts, followed by custom playbooks; enterprises are",
      "metadata": {
        "original_table_data": {
          "title": "Camelot_Table_36_38",
          "headers": [
            "The top response playbook is the automated response to Vision One workbench alerts, followed by custom playbooks; enterprises are"
          ],
          "rows": [
            [
              "maximizing both the ready-made AI-powered playbooks and the customization capability of the platform in automating response to"
            ],
            [
              "XDR alerts. The third and fourth playbooks, as well as the seventh and eighth playbooks, are updated versions of each and making it to"
            ],
            [
              "the top detected playbooks in use indicate that enterprises recognize the importance of patching vulnerabilities and are focusing on"
            ],
            [
              "automating their detection."
            ]
          ],
          "source_page": 36,
          "source_file": "data/source/Research-Risk-Report-2025.pdf",
          "table_type": "general",
          "confidence": 100.0,
          "extractor_method": "camelot",
          "metadata": {
            "whitespace": 0.0,
            "order": 1,
            "flavor": "stream"
          }
        },
        "source_page": 36,
        "source_file": "data/source/Research-Risk-Report-2025.pdf",
        "table_type": "general",
        "confidence": 100.0,
        "extractor_method": "camelot",
        "conversion_date": "2025-07-18T10:36:09.158234"
      }
    },
    {
      "table_id": "table_54_Camelot_Table_37_39",
      "content": "表格標題: Camelot_Table_37_39\n表格類型: general\n來源頁面: 第37頁\n資料提取方法: camelot\n信心度: 100.0%\n表格欄位: External Threat\n表格內容:\n  External Threat: Data Sections\n搜尋關鍵字: External Threat, Data Sections",
      "metadata": {
        "original_table_data": {
          "title": "Camelot_Table_37_39",
          "headers": [
            "External Threat"
          ],
          "rows": [
            [
              "Data Sections"
            ]
          ],
          "source_page": 37,
          "source_file": "data/source/Research-Risk-Report-2025.pdf",
          "table_type": "general",
          "confidence": 100.0,
          "extractor_method": "camelot",
          "metadata": {
            "whitespace": 0.0,
            "order": 1,
            "flavor": "stream"
          }
        },
        "source_page": 37,
        "source_file": "data/source/Research-Risk-Report-2025.pdf",
        "table_type": "general",
        "confidence": 100.0,
        "extractor_method": "camelot",
        "conversion_date": "2025-07-18T10:36:09.158248"
      }
    },
    {
      "table_id": "table_55_Camelot_Table_38_40",
      "content": "表格標題: Camelot_Table_38_40\n表格類型: comparison\n來源頁面: 第38頁\n資料提取方法: camelot\n信心度: 100.0%\n表格欄位: Improved\n表格內容:\n  Improved: Reconnaissance27\n  Improved: After a successful breach,\n  Improved: cybercriminals can use AI to pull a\n  Improved: vast amount of information from\n  Improved: a company to help them identify\n  Improved: potential victims. It can also be used\n  Improved: for reconnaissance tactics and to\n  Improved: expedite the analysis of exfiltrated\n  Improved: data, further increasing the scale and\n  Improved: severity of cyberattacks.\n搜尋關鍵字: 比較, 對比, 分析, Improved, LLM risks25, Rogue AI26, Reconnaissance27",
      "metadata": {
        "original_table_data": {
          "title": "Camelot_Table_38_40",
          "headers": [
            "",
            "",
            "Improved"
          ],
          "rows": [
            [
              "LLM risks25",
              "Rogue AI26",
              ""
            ],
            [
              "",
              "",
              "Reconnaissance27"
            ],
            [
              "The Open Worldwide Application",
              "An artificial intelligence threat",
              "After a successful breach,"
            ],
            [
              "Security Project (OWASP) released",
              "that security experts are focusing",
              "cybercriminals can use AI to pull a"
            ],
            [
              "the Top 10 Risk List for LLMs, which",
              "on in the long-term. Attackers can",
              "vast amount of information from"
            ],
            [
              "includes new additions, such as",
              "deploy malicious rogues or subvert",
              "a company to help them identify"
            ],
            [
              "vector and embedding weaknesses,",
              "AI resources, but rogue AI can also",
              "potential victims. It can also be used"
            ],
            [
              "misinformation, and unbounded",
              "be caused by human error and",
              "for reconnaissance tactics and to"
            ],
            [
              "consumption, to the list.",
              "technology limitations.",
              "expedite the analysis of exfiltrated"
            ],
            [
              "",
              "",
              "data, further increasing the scale and"
            ],
            [
              "",
              "",
              "severity of cyberattacks."
            ]
          ],
          "source_page": 38,
          "source_file": "data/source/Research-Risk-Report-2025.pdf",
          "table_type": "comparison",
          "confidence": 100.00000000000004,
          "extractor_method": "camelot",
          "metadata": {
            "whitespace": 25.0,
            "order": 1,
            "flavor": "stream"
          }
        },
        "source_page": 38,
        "source_file": "data/source/Research-Risk-Report-2025.pdf",
        "table_type": "comparison",
        "confidence": 100.00000000000004,
        "extractor_method": "camelot",
        "conversion_date": "2025-07-18T10:36:09.158278"
      }
    },
    {
      "table_id": "table_56_Camelot_Table_39_41",
      "content": "表格標題: Camelot_Table_39_41\n表格類型: comparison\n來源頁面: 第39頁\n資料提取方法: camelot\n信心度: 100.0%\n表格欄位: Disinformation, phishing schemes\n表格內容:\n  Disinformation: campaigns28, phishing schemes: and malicious\n  phishing schemes: digital twins31\n  Disinformation: Deepfake content is continuously, phishing schemes: Generative AI aids cybercriminals to\n  Disinformation: observed to shape public perceptions., phishing schemes: produce more convincing messages,\n  Disinformation: These campaigns range from low-, phishing schemes: and to scale operations through\n  Disinformation: impact misleading information that, phishing schemes: automation. Breached and leaked\n  Disinformation: make the rounds on social media, phishing schemes: personal information (PII) is used\n  Disinformation: to high-impact and large-scale, phishing schemes: to train LLM, and when deployed in\n  Disinformation: disinformation campaigns that, phishing schemes: combination with deepfake video and\n  Disinformation: can affect events such as national, phishing schemes: audio they could be used for identity\n  Disinformation: elections., phishing schemes: fraud and honey trapping.\n搜尋關鍵字: 比較, 對比, 分析, Disinformation, phishing schemes, and virtual, campaigns28, and malicious, kidnapping30",
      "metadata": {
        "original_table_data": {
          "title": "Camelot_Table_39_41",
          "headers": [
            "Disinformation",
            "",
            "phishing schemes"
          ],
          "rows": [
            [
              "",
              "and virtual",
              ""
            ],
            [
              "campaigns28",
              "",
              "and malicious"
            ],
            [
              "",
              "kidnapping30",
              ""
            ],
            [
              "",
              "",
              "digital twins31"
            ],
            [
              "Deepfake content is continuously",
              "Cybercriminals use deepfake",
              "Generative AI aids cybercriminals to"
            ],
            [
              "observed to shape public perceptions.",
              "technology to manipulate benign",
              "produce more convincing messages,"
            ],
            [
              "These campaigns range from low-",
              "photos and videos in extortion",
              "and to scale operations through"
            ],
            [
              "impact misleading information that",
              "schemes, as in pig butchering.",
              "automation. Breached and leaked"
            ],
            [
              "make the rounds on social media",
              "Scammers can also use deepfake",
              "personal information (PII) is used"
            ],
            [
              "to high-impact and large-scale",
              "audio or voice cloning in extortion",
              "to train LLM, and when deployed in"
            ],
            [
              "disinformation campaigns that",
              "schemes like virtual kidnapping.",
              "combination with deepfake video and"
            ],
            [
              "can affect events such as national",
              "",
              "audio they could be used for identity"
            ],
            [
              "elections.",
              "",
              "fraud and honey trapping."
            ]
          ],
          "source_page": 39,
          "source_file": "data/source/Research-Risk-Report-2025.pdf",
          "table_type": "comparison",
          "confidence": 100.0,
          "extractor_method": "camelot",
          "metadata": {
            "whitespace": 28.888888888888886,
            "order": 1,
            "flavor": "stream"
          }
        },
        "source_page": 39,
        "source_file": "data/source/Research-Risk-Report-2025.pdf",
        "table_type": "comparison",
        "confidence": 100.0,
        "extractor_method": "camelot",
        "conversion_date": "2025-07-18T10:36:09.158315"
      }
    },
    {
      "table_id": "table_57_Camelot_Table_39_42",
      "content": "表格標題: Camelot_Table_39_42\n表格類型: general\n來源頁面: 第39頁\n資料提取方法: camelot\n信心度: 60.2%\n表格欄位: elections., fraud and honey trapping.\n表格內容:\n  elections.: While threat actors are making the most of AI, this innovation can be harnessed for improved and more efficient cybersecurity as\n  elections.: well. Trend Vision One – AI Security balances enterprises’ needs for AI innovation with securing AI initiatives. It uses AI for security\n  elections.: and provides security for AI by eliminating blind spots, preventing AI model poisoning, mitigating AI stack vulnerabilities, using AI-\n  elections.: generated threat protection, proactive threat mitigation, and advanced threat detection and response. Enterprises will also benefit\n  elections.: from its compliance capabilities, as regulatory standards for the use of AI are set by the industry.\n搜尋關鍵字: elections., fraud and honey trapping.",
      "metadata": {
        "original_table_data": {
          "title": "Camelot_Table_39_42",
          "headers": [
            "elections.",
            "fraud and honey trapping."
          ],
          "rows": [
            [
              "While threat actors are making the most of AI, this innovation can be harnessed for improved and more efficient cybersecurity as",
              ""
            ],
            [
              "well. Trend Vision One – AI Security balances enterprises’ needs for AI innovation with securing AI initiatives. It uses AI for security",
              ""
            ],
            [
              "and provides security for AI by eliminating blind spots, preventing AI model poisoning, mitigating AI stack vulnerabilities, using AI-",
              ""
            ],
            [
              "generated threat protection, proactive threat mitigation, and advanced threat detection and response. Enterprises will also benefit",
              ""
            ],
            [
              "from its compliance capabilities, as regulatory standards for the use of AI are set by the industry.",
              ""
            ]
          ],
          "source_page": 39,
          "source_file": "data/source/Research-Risk-Report-2025.pdf",
          "table_type": "general",
          "confidence": 60.24051108102966,
          "extractor_method": "camelot",
          "metadata": {
            "whitespace": 41.66666666666667,
            "order": 2,
            "flavor": "stream"
          }
        },
        "source_page": 39,
        "source_file": "data/source/Research-Risk-Report-2025.pdf",
        "table_type": "general",
        "confidence": 60.24051108102966,
        "extractor_method": "camelot",
        "conversion_date": "2025-07-18T10:36:09.158337"
      }
    },
    {
      "table_id": "table_58_Camelot_Table_40_43",
      "content": "表格標題: Camelot_Table_40_43\n表格類型: statistical\n來源頁面: 第40頁\n資料提取方法: camelot\n信心度: 88.7%\n表格欄位: Ransomware\n表格內容:\n  Ransomware: Top Ransomware Intrusion Sets\n  Ransomware: Our monitoring of the cybercriminal underground monitors data uploaded on ransomware groups’ leak sites. In the Top Ransomware\n  Ransomware: Intrusion Sets table, “breaches” refer to successful ransomware attacks on enterprises that chose not to pay ransom. This means that\n  Ransomware: the actual number of successful attacks might be higher as some companies might have paid the ransom.\n  Ransomware: Trend 2025 Cyber Risk Report\n搜尋關鍵字: 統計, 數據, 數字, Ransomware, 300, 266",
      "metadata": {
        "original_table_data": {
          "title": "Camelot_Table_40_43",
          "headers": [
            "Ransomware",
            "",
            "",
            "",
            ""
          ],
          "rows": [
            [
              "Top Ransomware Intrusion Sets",
              "",
              "",
              "",
              ""
            ],
            [
              "",
              "300",
              "",
              "",
              ""
            ],
            [
              "",
              "266",
              "",
              "",
              ""
            ],
            [
              "",
              "249",
              "",
              "",
              ""
            ],
            [
              "",
              "187",
              "",
              "",
              ""
            ],
            [
              "",
              "",
              "176",
              "",
              ""
            ],
            [
              "",
              "",
              "",
              "133",
              ""
            ],
            [
              "",
              "150",
              "",
              "",
              ""
            ],
            [
              "",
              "",
              "",
              "119",
              ""
            ],
            [
              "",
              "",
              "",
              "106",
              ""
            ],
            [
              "",
              "",
              "",
              "95\n95\n92",
              ""
            ],
            [
              "",
              "0",
              "",
              "",
              ""
            ],
            [
              "",
              "RansomHub",
              "Akira",
              "Medusa\n8Base\nQilin",
              ""
            ],
            [
              "",
              "LockBit\nPlay",
              "",
              "Hunters\nBianLian\nBlack Basta",
              ""
            ],
            [
              "",
              "",
              "International",
              "",
              ""
            ],
            [
              "Our monitoring of the cybercriminal underground monitors data uploaded on ransomware groups’ leak sites. In the Top Ransomware",
              "",
              "",
              "",
              ""
            ],
            [
              "Intrusion Sets table, “breaches” refer to successful ransomware attacks on enterprises that chose not to pay ransom. This means that",
              "",
              "",
              "",
              ""
            ],
            [
              "the actual number of successful attacks might be higher as some companies might have paid the ransom.",
              "",
              "",
              "",
              ""
            ],
            [
              "Trend 2025 Cyber Risk Report",
              "",
              "",
              "",
              "40"
            ]
          ],
          "source_page": 40,
          "source_file": "data/source/Research-Risk-Report-2025.pdf",
          "table_type": "statistical",
          "confidence": 88.69782915513258,
          "extractor_method": "camelot",
          "metadata": {
            "whitespace": 76.0,
            "order": 1,
            "flavor": "stream"
          }
        },
        "source_page": 40,
        "source_file": "data/source/Research-Risk-Report-2025.pdf",
        "table_type": "statistical",
        "confidence": 88.69782915513258,
        "extractor_method": "camelot",
        "conversion_date": "2025-07-18T10:36:09.158378"
      }
    },
    {
      "table_id": "table_59_Camelot_Table_41_44",
      "content": "表格標題: Camelot_Table_41_44\n表格類型: general\n來源頁面: 第41頁\n資料提取方法: camelot\n信心度: 100.0%\n表格欄位: Our leak site monitoring shows that ransomware groups have the most victim enterprises from North America, with 369 successful\n表格內容:\n  Our leak site monitoring shows that ransomware groups have the most victim enterprises from North America, with 369 successful: breaches on companies that did not pay ransom in that region. Leak sites also published 104 successful breaches from enterprises\n  Our leak site monitoring shows that ransomware groups have the most victim enterprises from North America, with 369 successful: in Europe and 47 from Asia. Companies in retail, wholesale, and distribution make up most of the breaches published in leak sites\n  Our leak site monitoring shows that ransomware groups have the most victim enterprises from North America, with 369 successful: (13.9%), followed by enterprises from industrial products and services (9.4%). Ransomware groups also published that they have\n  Our leak site monitoring shows that ransomware groups have the most victim enterprises from North America, with 369 successful: victims from the transportation industry, information technology, and technology industries which make up the top five industries\n  Our leak site monitoring shows that ransomware groups have the most victim enterprises from North America, with 369 successful: affected by ransomware attacks.\n搜尋關鍵字: Our leak site monitoring shows that ransomware groups have the most victim enterprises from North America, with 369 successful",
      "metadata": {
        "original_table_data": {
          "title": "Camelot_Table_41_44",
          "headers": [
            "Our leak site monitoring shows that ransomware groups have the most victim enterprises from North America, with 369 successful"
          ],
          "rows": [
            [
              "breaches on companies that did not pay ransom in that region. Leak sites also published 104 successful breaches from enterprises"
            ],
            [
              "in Europe and 47 from Asia. Companies in retail, wholesale, and distribution make up most of the breaches published in leak sites"
            ],
            [
              "(13.9%), followed by enterprises from industrial products and services (9.4%). Ransomware groups also published that they have"
            ],
            [
              "victims from the transportation industry, information technology, and technology industries which make up the top five industries"
            ],
            [
              "affected by ransomware attacks."
            ]
          ],
          "source_page": 41,
          "source_file": "data/source/Research-Risk-Report-2025.pdf",
          "table_type": "general",
          "confidence": 100.00000000000001,
          "extractor_method": "camelot",
          "metadata": {
            "whitespace": 0.0,
            "order": 1,
            "flavor": "stream"
          }
        },
        "source_page": 41,
        "source_file": "data/source/Research-Risk-Report-2025.pdf",
        "table_type": "general",
        "confidence": 100.00000000000001,
        "extractor_method": "camelot",
        "conversion_date": "2025-07-18T10:36:09.158399"
      }
    },
    {
      "table_id": "table_60_Camelot_Table_42_45",
      "content": "表格標題: Camelot_Table_42_45\n表格類型: general\n來源頁面: 第42頁\n資料提取方法: camelot\n信心度: 91.7%\n表格欄位: Notable APT campaigns\n表格內容:\n  Notable APT campaigns: This section includes highlights from the Trend Micro APT Research Report from December 2024 that contains independently\n  Notable APT campaigns: collected information, as well as excerpts from publicly available information issued by security vendors or public institutions. Our\n  Notable APT campaigns: researchers have analyzed and provided insights on topics that are deemed particularly noteworthy.\n  Notable APT campaigns: Earth Kurma\n  Notable APT campaigns: Famous Chollima\n  Notable APT campaigns: KONNI Group\n  Notable APT campaigns: Earth Koshchei\n  Notable APT campaigns: Pawn Storm\n  Notable APT campaigns: Earth Dahu\n  Notable APT campaigns: Matryoshka\n  Notable APT campaigns: Trend 2025 Cyber Risk Report\n搜尋關鍵字: Notable APT campaigns",
      "metadata": {
        "original_table_data": {
          "title": "Camelot_Table_42_45",
          "headers": [
            "Notable APT campaigns",
            "",
            "",
            "",
            "",
            "",
            "",
            "",
            "",
            "",
            "",
            "",
            "",
            "",
            "",
            "",
            "",
            "",
            "",
            "",
            "",
            "",
            "",
            "",
            ""
          ],
          "rows": [
            [
              "This section includes highlights from the Trend Micro APT Research Report from December 2024 that contains independently",
              "",
              "",
              "",
              "",
              "",
              "",
              "",
              "",
              "",
              "",
              "",
              "",
              "",
              "",
              "",
              "",
              "",
              "",
              "",
              "",
              "",
              "",
              "",
              ""
            ],
            [
              "collected information, as well as excerpts from publicly available information issued by security vendors or public institutions. Our",
              "",
              "",
              "",
              "",
              "",
              "",
              "",
              "",
              "",
              "",
              "",
              "",
              "",
              "",
              "",
              "",
              "",
              "",
              "",
              "",
              "",
              "",
              "",
              ""
            ],
            [
              "researchers have analyzed and provided insights on topics that are deemed particularly noteworthy.",
              "",
              "",
              "",
              "",
              "",
              "",
              "",
              "",
              "",
              "",
              "",
              "",
              "",
              "",
              "",
              "",
              "",
              "",
              "",
              "",
              "",
              "",
              "",
              ""
            ],
            [
              "",
              "NOV",
              "DEC",
              "2021",
              "2022",
              "JAN",
              "FEB MAR",
              "APR MAY",
              "JUN",
              "JUL",
              "AUG",
              "SEP",
              "OCT",
              "NOV",
              "DEC",
              "JAN",
              "FEB MAR",
              "APR MAY",
              "JUN",
              "JUL",
              "AUG",
              "SEP",
              "OCT",
              "NOV",
              "DEC 2025"
            ],
            [
              "",
              "2020",
              "",
              "",
              "",
              "2023",
              "",
              "",
              "",
              "",
              "",
              "",
              "",
              "",
              "",
              "2024",
              "",
              "",
              "",
              "",
              "",
              "",
              "",
              "",
              ""
            ],
            [
              "Earth Kurma",
              "",
              "",
              "",
              "",
              "",
              "",
              "",
              "",
              "",
              "",
              "",
              "",
              "",
              "",
              "",
              "",
              "",
              "",
              "",
              "",
              "",
              "",
              "",
              ""
            ],
            [
              "Famous Chollima",
              "",
              "",
              "",
              "",
              "",
              "",
              "",
              "",
              "",
              "",
              "",
              "",
              "",
              "",
              "",
              "",
              "",
              "",
              "",
              "",
              "",
              "",
              "",
              ""
            ],
            [
              "KONNI Group",
              "",
              "",
              "",
              "",
              "",
              "",
              "",
              "",
              "",
              "",
              "",
              "",
              "",
              "",
              "",
              "",
              "",
              "",
              "",
              "",
              "",
              "",
              "",
              ""
            ],
            [
              "Earth Koshchei",
              "",
              "",
              "",
              "",
              "",
              "",
              "",
              "",
              "",
              "",
              "",
              "",
              "",
              "",
              "",
              "",
              "",
              "",
              "",
              "",
              "",
              "",
              "",
              ""
            ],
            [
              "Pawn Storm",
              "",
              "",
              "",
              "",
              "",
              "",
              "",
              "",
              "",
              "",
              "",
              "",
              "",
              "",
              "",
              "",
              "",
              "",
              "",
              "",
              "",
              "",
              "",
              ""
            ],
            [
              "Earth Dahu",
              "",
              "",
              "",
              "",
              "",
              "",
              "",
              "",
              "",
              "",
              "",
              "",
              "",
              "",
              "",
              "",
              "",
              "",
              "",
              "",
              "",
              "",
              "",
              ""
            ],
            [
              "Matryoshka",
              "",
              "",
              "",
              "",
              "",
              "",
              "",
              "",
              "",
              "",
              "",
              "",
              "",
              "",
              "",
              "",
              "",
              "",
              "",
              "",
              "",
              "",
              "",
              ""
            ],
            [
              "Trend 2025 Cyber Risk Report",
              "",
              "",
              "",
              "",
              "",
              "",
              "",
              "",
              "",
              "",
              "",
              "",
              "",
              "",
              "",
              "",
              "",
              "",
              "",
              "",
              "",
              "",
              "",
              "42"
            ]
          ],
          "source_page": 42,
          "source_file": "data/source/Research-Risk-Report-2025.pdf",
          "table_type": "general",
          "confidence": 91.71131496557682,
          "extractor_method": "camelot",
          "metadata": {
            "whitespace": 88.57142857142857,
            "order": 1,
            "flavor": "stream"
          }
        },
        "source_page": 42,
        "source_file": "data/source/Research-Risk-Report-2025.pdf",
        "table_type": "general",
        "confidence": 91.71131496557682,
        "extractor_method": "camelot",
        "conversion_date": "2025-07-18T10:36:09.158461"
      }
    },
    {
      "table_id": "table_61_Camelot_Table_43_46",
      "content": "表格標題: Camelot_Table_43_46\n表格類型: general\n來源頁面: 第43頁\n資料提取方法: camelot\n信心度: 100.0%\n表格欄位: Earth Kurma targets Southeast Asia governments\n表格內容:\n  Earth Kurma targets Southeast Asia governments: November 2020 - ongoing\n  Earth Kurma targets Southeast Asia governments: Targets:\n  Earth Kurma targets Southeast Asia governments: • Government sectors and government-related telecommunication sectors in the Philippines,\n  Earth Kurma targets Southeast Asia governments: Vietnam, Malaysia, Brunei, Thailand\n  Earth Kurma targets Southeast Asia governments: Motivation:\n  Earth Kurma targets Southeast Asia governments: •\nEspionage\n  Earth Kurma targets Southeast Asia governments: •\nEarth Kurma targets multiple government sectors as well as government-related\n  Earth Kurma targets Southeast Asia governments: telecommunication sectors.\n  Earth Kurma targets Southeast Asia governments: •\nEarth Kurma’s primary focus is data exﬁltration, with a tendency to leverage public cloud\n  Earth Kurma targets Southeast Asia governments: services. The group reuses the same code base from the previous known campaigns to\n  Earth Kurma targets Southeast Asia governments: customize their toolsets and can even leverage the victim’s infrastructure to achieve their goals.\n  Earth Kurma targets Southeast Asia governments: They have customized toolsets like TESDAT and SIMPOBOXSPY, and developed rootkits to cover\n  Earth Kurma targets Southeast Asia governments: their tracks like KRNRAT, and MORIYA.\n  Earth Kurma targets Southeast Asia governments: Trend 2025 Cyber Risk Report\n搜尋關鍵字: Earth Kurma targets Southeast Asia governments, Targets:",
      "metadata": {
        "original_table_data": {
          "title": "Camelot_Table_43_46",
          "headers": [
            "Earth Kurma targets Southeast Asia governments",
            ""
          ],
          "rows": [
            [
              "November 2020 - ongoing",
              ""
            ],
            [
              "Targets:",
              ""
            ],
            [
              "• Government sectors and government-related telecommunication sectors in the Philippines,",
              ""
            ],
            [
              "Vietnam, Malaysia, Brunei, Thailand",
              ""
            ],
            [
              "Motivation:",
              ""
            ],
            [
              "•\nEspionage",
              ""
            ],
            [
              "•\nEarth Kurma targets multiple government sectors as well as government-related",
              ""
            ],
            [
              "telecommunication sectors.",
              ""
            ],
            [
              "•\nEarth Kurma’s primary focus is data exﬁltration, with a tendency to leverage public cloud",
              ""
            ],
            [
              "services. The group reuses the same code base from the previous known campaigns to",
              ""
            ],
            [
              "customize their toolsets and can even leverage the victim’s infrastructure to achieve their goals.",
              ""
            ],
            [
              "They have customized toolsets like TESDAT and SIMPOBOXSPY, and developed rootkits to cover",
              ""
            ],
            [
              "their tracks like KRNRAT, and MORIYA.",
              ""
            ],
            [
              "Trend 2025 Cyber Risk Report",
              "43"
            ]
          ],
          "source_page": 43,
          "source_file": "data/source/Research-Risk-Report-2025.pdf",
          "table_type": "general",
          "confidence": 100.00000000000006,
          "extractor_method": "camelot",
          "metadata": {
            "whitespace": 46.666666666666664,
            "order": 1,
            "flavor": "stream"
          }
        },
        "source_page": 43,
        "source_file": "data/source/Research-Risk-Report-2025.pdf",
        "table_type": "general",
        "confidence": 100.00000000000006,
        "extractor_method": "camelot",
        "conversion_date": "2025-07-18T10:36:09.158495"
      }
    },
    {
      "table_id": "table_62_Camelot_Table_44_47",
      "content": "表格標題: Camelot_Table_44_47\n表格類型: general\n來源頁面: 第44頁\n資料提取方法: camelot\n信心度: 100.0%\n表格欄位: Famous Chollima exploits job listings to propagate\n表格內容:\n  Famous Chollima exploits job listings to propagate: malware\n  Famous Chollima exploits job listings to propagate: October 2023 – ongoing\n  Famous Chollima exploits job listings to propagate: Targets:\n  Famous Chollima exploits job listings to propagate: • Developers\n  Famous Chollima exploits job listings to propagate: Motivation:\n  Famous Chollima exploits job listings to propagate: • Acquisition of foreign currency for arms development, possibly also conﬁdential information\n  Famous Chollima exploits job listings to propagate: theft\n  Famous Chollima exploits job listings to propagate: •\nIn this campaign, attackers post job listings for system developers for cryptocurrency-related\n  Famous Chollima exploits job listings to propagate: organizations on job sites, along with GitHub URLs of the code they claimed to be currently\n  Famous Chollima exploits job listings to propagate: using. Additional payloads are downloaded along with the code packages. If a cryptocurrency\n  Famous Chollima exploits job listings to propagate: wallet is found in the developer’s environment, Famous Chollima steals it, and if executed in a\n  Famous Chollima exploits job listings to propagate: corporate environment, they inﬁltrate the company and steal conﬁdential information as\n  Famous Chollima exploits job listings to propagate: needed.\n  Famous Chollima exploits job listings to propagate: Trend 2025 Cyber Risk Report\n搜尋關鍵字: Famous Chollima exploits job listings to propagate, malware, Targets:",
      "metadata": {
        "original_table_data": {
          "title": "Camelot_Table_44_47",
          "headers": [
            "Famous Chollima exploits job listings to propagate",
            ""
          ],
          "rows": [
            [
              "malware",
              ""
            ],
            [
              "October 2023 – ongoing",
              ""
            ],
            [
              "Targets:",
              ""
            ],
            [
              "• Developers",
              ""
            ],
            [
              "Motivation:",
              ""
            ],
            [
              "• Acquisition of foreign currency for arms development, possibly also conﬁdential information",
              ""
            ],
            [
              "theft",
              ""
            ],
            [
              "•\nIn this campaign, attackers post job listings for system developers for cryptocurrency-related",
              ""
            ],
            [
              "organizations on job sites, along with GitHub URLs of the code they claimed to be currently",
              ""
            ],
            [
              "using. Additional payloads are downloaded along with the code packages. If a cryptocurrency",
              ""
            ],
            [
              "wallet is found in the developer’s environment, Famous Chollima steals it, and if executed in a",
              ""
            ],
            [
              "corporate environment, they inﬁltrate the company and steal conﬁdential information as",
              ""
            ],
            [
              "needed.",
              ""
            ],
            [
              "Trend 2025 Cyber Risk Report",
              "44"
            ]
          ],
          "source_page": 44,
          "source_file": "data/source/Research-Risk-Report-2025.pdf",
          "table_type": "general",
          "confidence": 99.99999999999997,
          "extractor_method": "camelot",
          "metadata": {
            "whitespace": 46.666666666666664,
            "order": 1,
            "flavor": "stream"
          }
        },
        "source_page": 44,
        "source_file": "data/source/Research-Risk-Report-2025.pdf",
        "table_type": "general",
        "confidence": 99.99999999999997,
        "extractor_method": "camelot",
        "conversion_date": "2025-07-18T10:36:09.158528"
      }
    },
    {
      "table_id": "table_63_Camelot_Table_45_48",
      "content": "表格標題: Camelot_Table_45_48\n表格類型: general\n來源頁面: 第45頁\n資料提取方法: camelot\n信心度: 96.7%\n表格欄位: Attacks targeting Russia potentially by KONNI Group\n表格內容:\n  Attacks targeting Russia potentially by KONNI Group: October 2024 – ongoing\n  Attacks targeting Russia potentially by KONNI Group: Targets:\n  Attacks targeting Russia potentially by KONNI Group: • Russia\n  Attacks targeting Russia potentially by KONNI Group: Motivation:\n  Attacks targeting Russia potentially by KONNI Group: •\nEspionage aimed at gathering diplomatic information\n  Attacks targeting Russia potentially by KONNI Group: • Continued activity from the KONNI group consistently use LNK ﬁles. Our recent investigation\n  Attacks targeting Russia potentially by KONNI Group: reveals decoy PDF ﬁles with metadata that can be linked to APT37 attacks in the past. The same\n  Attacks targeting Russia potentially by KONNI Group: decoy ﬁles seem to target Russians, as they contain text in Russian.\n  Attacks targeting Russia potentially by KONNI Group: Trend 2025 Cyber Risk Report\n搜尋關鍵字: Attacks targeting Russia potentially by KONNI Group, Targets:, • Russia",
      "metadata": {
        "original_table_data": {
          "title": "Camelot_Table_45_48",
          "headers": [
            "Attacks targeting Russia potentially by KONNI Group",
            ""
          ],
          "rows": [
            [
              "October 2024 – ongoing",
              ""
            ],
            [
              "Targets:",
              ""
            ],
            [
              "• Russia",
              ""
            ],
            [
              "Motivation:",
              ""
            ],
            [
              "•\nEspionage aimed at gathering diplomatic information",
              ""
            ],
            [
              "• Continued activity from the KONNI group consistently use LNK ﬁles. Our recent investigation",
              ""
            ],
            [
              "reveals decoy PDF ﬁles with metadata that can be linked to APT37 attacks in the past. The same",
              ""
            ],
            [
              "decoy ﬁles seem to target Russians, as they contain text in Russian.",
              ""
            ],
            [
              "Trend 2025 Cyber Risk Report",
              "45"
            ]
          ],
          "source_page": 45,
          "source_file": "data/source/Research-Risk-Report-2025.pdf",
          "table_type": "general",
          "confidence": 96.68030591908902,
          "extractor_method": "camelot",
          "metadata": {
            "whitespace": 45.0,
            "order": 1,
            "flavor": "stream"
          }
        },
        "source_page": 45,
        "source_file": "data/source/Research-Risk-Report-2025.pdf",
        "table_type": "general",
        "confidence": 96.68030591908902,
        "extractor_method": "camelot",
        "conversion_date": "2025-07-18T10:36:09.158555"
      }
    },
    {
      "table_id": "table_64_Camelot_Table_46_49",
      "content": "表格標題: Camelot_Table_46_49\n表格類型: general\n來源頁面: 第46頁\n資料提取方法: camelot\n信心度: 100.0%\n表格欄位: Earth Koshchei’s rogue RDP campaign\n表格內容:\n  Earth Koshchei’s rogue RDP campaign: August - October 2024\n  Earth Koshchei’s rogue RDP campaign: Targets:\n  Earth Koshchei’s rogue RDP campaign: • Governments, military organizations, think tanks, cybersecurity companies, IT and cloud\n  Earth Koshchei’s rogue RDP campaign: providers, academic researchers, and other Ukrainian targets\n  Earth Koshchei’s rogue RDP campaign: Motivation:\n  Earth Koshchei’s rogue RDP campaign: •\nEspionage\n  Earth Koshchei’s rogue RDP campaign: •\nEarth Koshschei (Midnight Blizzard, APT29) launched yet another massive spear-phishing\n  Earth Koshchei’s rogue RDP campaign: campaign that used a rogue Remote Desktop Protocol (RDP) attack methodology; it involves an\n  Earth Koshchei’s rogue RDP campaign: RDP relay, a rogue RDP server and a malicious RDP conﬁguration ﬁle. This attack gives partial\n  Earth Koshchei’s rogue RDP campaign: control of victim machines to the attacker, potentially leading to data leakage and malware\n  Earth Koshchei’s rogue RDP campaign: installation.\n  Earth Koshchei’s rogue RDP campaign: Trend 2025 Cyber Risk Report\n搜尋關鍵字: Earth Koshchei’s rogue RDP campaign, Targets:",
      "metadata": {
        "original_table_data": {
          "title": "Camelot_Table_46_49",
          "headers": [
            "Earth Koshchei’s rogue RDP campaign",
            ""
          ],
          "rows": [
            [
              "August - October 2024",
              ""
            ],
            [
              "Targets:",
              ""
            ],
            [
              "• Governments, military organizations, think tanks, cybersecurity companies, IT and cloud",
              ""
            ],
            [
              "providers, academic researchers, and other Ukrainian targets",
              ""
            ],
            [
              "Motivation:",
              ""
            ],
            [
              "•\nEspionage",
              ""
            ],
            [
              "•\nEarth Koshschei (Midnight Blizzard, APT29) launched yet another massive spear-phishing",
              ""
            ],
            [
              "campaign that used a rogue Remote Desktop Protocol (RDP) attack methodology; it involves an",
              ""
            ],
            [
              "RDP relay, a rogue RDP server and a malicious RDP conﬁguration ﬁle. This attack gives partial",
              ""
            ],
            [
              "control of victim machines to the attacker, potentially leading to data leakage and malware",
              ""
            ],
            [
              "installation.",
              ""
            ],
            [
              "Trend 2025 Cyber Risk Report",
              "46"
            ]
          ],
          "source_page": 46,
          "source_file": "data/source/Research-Risk-Report-2025.pdf",
          "table_type": "general",
          "confidence": 100.0,
          "extractor_method": "camelot",
          "metadata": {
            "whitespace": 46.15384615384615,
            "order": 1,
            "flavor": "stream"
          }
        },
        "source_page": 46,
        "source_file": "data/source/Research-Risk-Report-2025.pdf",
        "table_type": "general",
        "confidence": 100.0,
        "extractor_method": "camelot",
        "conversion_date": "2025-07-18T10:36:09.158587"
      }
    },
    {
      "table_id": "table_65_Camelot_Table_47_50",
      "content": "表格標題: Camelot_Table_47_50\n表格類型: general\n來源頁面: 第47頁\n資料提取方法: camelot\n信心度: 100.0%\n表格欄位: Clipboard and reCAPTCHA abuse attributed to Pawn\n表格內容:\n  Clipboard and reCAPTCHA abuse attributed to Pawn: Storm\n  Clipboard and reCAPTCHA abuse attributed to Pawn: August 2024 - ongoing\n  Clipboard and reCAPTCHA abuse attributed to Pawn: Targets:\n  Clipboard and reCAPTCHA abuse attributed to Pawn: • Ukranian government organizations\n  Clipboard and reCAPTCHA abuse attributed to Pawn: Motivation:\n  Clipboard and reCAPTCHA abuse attributed to Pawn: •\nEspionage\n  Clipboard and reCAPTCHA abuse attributed to Pawn: •\nThis campaign saw the use of a web page mimicking reCAPTCHA’s bot prevention mechanism as\n  Clipboard and reCAPTCHA abuse attributed to Pawn: a point of entry. The site used JavaScript to place a malicious PowerShell command in the\n  Clipboard and reCAPTCHA abuse attributed to Pawn: clipboard and prompted the user to press Windows + R, followed by Ctrl + V, and then the enter\n  Clipboard and reCAPTCHA abuse attributed to Pawn: key, to execute the clipboard contents under the guise of a reCAPTCHA screen. Additionally, in\n  Clipboard and reCAPTCHA abuse attributed to Pawn: September, CERT-UA observed emails exploiting a vulnerability in Roundcube (CVE-2023-43770).\n  Clipboard and reCAPTCHA abuse attributed to Pawn: In both attacks, the infrastructure mail[.]zhblz[.]com (203[.]161[.]50[.]145) was used, and were\n  Clipboard and reCAPTCHA abuse attributed to Pawn: attributed to Pawn Storm.\n  Clipboard and reCAPTCHA abuse attributed to Pawn: Trend 2025 Cyber Risk Report\n搜尋關鍵字: Clipboard and reCAPTCHA abuse attributed to Pawn, Storm, Targets:",
      "metadata": {
        "original_table_data": {
          "title": "Camelot_Table_47_50",
          "headers": [
            "Clipboard and reCAPTCHA abuse attributed to Pawn",
            ""
          ],
          "rows": [
            [
              "Storm",
              ""
            ],
            [
              "August 2024 - ongoing",
              ""
            ],
            [
              "Targets:",
              ""
            ],
            [
              "• Ukranian government organizations",
              ""
            ],
            [
              "Motivation:",
              ""
            ],
            [
              "•\nEspionage",
              ""
            ],
            [
              "•\nThis campaign saw the use of a web page mimicking reCAPTCHA’s bot prevention mechanism as",
              ""
            ],
            [
              "a point of entry. The site used JavaScript to place a malicious PowerShell command in the",
              ""
            ],
            [
              "clipboard and prompted the user to press Windows + R, followed by Ctrl + V, and then the enter",
              ""
            ],
            [
              "key, to execute the clipboard contents under the guise of a reCAPTCHA screen. Additionally, in",
              ""
            ],
            [
              "September, CERT-UA observed emails exploiting a vulnerability in Roundcube (CVE-2023-43770).",
              ""
            ],
            [
              "In both attacks, the infrastructure mail[.]zhblz[.]com (203[.]161[.]50[.]145) was used, and were",
              ""
            ],
            [
              "attributed to Pawn Storm.",
              ""
            ],
            [
              "Trend 2025 Cyber Risk Report",
              "47"
            ]
          ],
          "source_page": 47,
          "source_file": "data/source/Research-Risk-Report-2025.pdf",
          "table_type": "general",
          "confidence": 100.00000000000001,
          "extractor_method": "camelot",
          "metadata": {
            "whitespace": 46.666666666666664,
            "order": 1,
            "flavor": "stream"
          }
        },
        "source_page": 47,
        "source_file": "data/source/Research-Risk-Report-2025.pdf",
        "table_type": "general",
        "confidence": 100.00000000000001,
        "extractor_method": "camelot",
        "conversion_date": "2025-07-18T10:36:09.158629"
      }
    },
    {
      "table_id": "table_66_Camelot_Table_48_51",
      "content": "表格標題: Camelot_Table_48_51\n表格類型: general\n來源頁面: 第48頁\n資料提取方法: camelot\n信心度: 100.0%\n表格欄位: Earth Dahu abuses TryCloudFlare\n表格內容:\n  Earth Dahu abuses TryCloudFlare: Ongoing\n  Earth Dahu abuses TryCloudFlare: Targets:\n  Earth Dahu abuses TryCloudFlare: • Ukrainian central and local government and military organizations\n  Earth Dahu abuses TryCloudFlare: Motivation:\n  Earth Dahu abuses TryCloudFlare: •\nEspionage, particularly military intelligence activities\n  Earth Dahu abuses TryCloudFlare: •\nEarth Dahu is observed to use remote template injection, drop compressed ﬁles from HTA and\n  Earth Dahu abuses TryCloudFlare: executing LNK ﬁles within them using mshta.exe to run resources via TryCloudFlare as C&C, and\n  Earth Dahu abuses TryCloudFlare: execute resources on the HTAC2 also using mshta.exe.\n  Earth Dahu abuses TryCloudFlare: Trend 2025 Cyber Risk Report\n搜尋關鍵字: Earth Dahu abuses TryCloudFlare, Ongoing, Targets:",
      "metadata": {
        "original_table_data": {
          "title": "Camelot_Table_48_51",
          "headers": [
            "Earth Dahu abuses TryCloudFlare",
            ""
          ],
          "rows": [
            [
              "Ongoing",
              ""
            ],
            [
              "Targets:",
              ""
            ],
            [
              "• Ukrainian central and local government and military organizations",
              ""
            ],
            [
              "Motivation:",
              ""
            ],
            [
              "•\nEspionage, particularly military intelligence activities",
              ""
            ],
            [
              "•\nEarth Dahu is observed to use remote template injection, drop compressed ﬁles from HTA and",
              ""
            ],
            [
              "executing LNK ﬁles within them using mshta.exe to run resources via TryCloudFlare as C&C, and",
              ""
            ],
            [
              "execute resources on the HTAC2 also using mshta.exe.",
              ""
            ],
            [
              "Trend 2025 Cyber Risk Report",
              "48"
            ]
          ],
          "source_page": 48,
          "source_file": "data/source/Research-Risk-Report-2025.pdf",
          "table_type": "general",
          "confidence": 100.0,
          "extractor_method": "camelot",
          "metadata": {
            "whitespace": 45.0,
            "order": 1,
            "flavor": "stream"
          }
        },
        "source_page": 48,
        "source_file": "data/source/Research-Risk-Report-2025.pdf",
        "table_type": "general",
        "confidence": 100.0,
        "extractor_method": "camelot",
        "conversion_date": "2025-07-18T10:36:09.158691"
      }
    },
    {
      "table_id": "table_67_Camelot_Table_49_52",
      "content": "表格標題: Camelot_Table_49_52\n表格類型: general\n來源頁面: 第49頁\n資料提取方法: camelot\n信心度: 100.0%\n表格欄位: Matyoshka campaign related to the US presidential\n表格內容:\n  Matyoshka campaign related to the US presidential: elections\n  Matyoshka campaign related to the US presidential: September 2023 - November 2024\n  Matyoshka campaign related to the US presidential: Targets:\n  Matyoshka campaign related to the US presidential: • US, Ukraine, Europe\n  Matyoshka campaign related to the US presidential: Motivation:\n  Matyoshka campaign related to the US presidential: • Disinformation and inﬂuencing public opinion\n  Matyoshka campaign related to the US presidential: •\nThis campaign is characterized by the creation and dissemination of videos and images that\n  Matyoshka campaign related to the US presidential: misuse the logos of major media outlets, spread primarily through Telegram and X (formerly\n  Matyoshka campaign related to the US presidential: Twitter). Fact-checking organizations and media outlets have also reported receiving emails with\n  Matyoshka campaign related to the US presidential: links to this content.\n  Matyoshka campaign related to the US presidential: Trend 2025 Cyber Risk Report\n搜尋關鍵字: Matyoshka campaign related to the US presidential, elections, Targets:",
      "metadata": {
        "original_table_data": {
          "title": "Camelot_Table_49_52",
          "headers": [
            "Matyoshka campaign related to the US presidential",
            ""
          ],
          "rows": [
            [
              "elections",
              ""
            ],
            [
              "September 2023 - November 2024",
              ""
            ],
            [
              "Targets:",
              ""
            ],
            [
              "• US, Ukraine, Europe",
              ""
            ],
            [
              "Motivation:",
              ""
            ],
            [
              "• Disinformation and inﬂuencing public opinion",
              ""
            ],
            [
              "•\nThis campaign is characterized by the creation and dissemination of videos and images that",
              ""
            ],
            [
              "misuse the logos of major media outlets, spread primarily through Telegram and X (formerly",
              ""
            ],
            [
              "Twitter). Fact-checking organizations and media outlets have also reported receiving emails with",
              ""
            ],
            [
              "links to this content.",
              ""
            ],
            [
              "Trend 2025 Cyber Risk Report",
              "49"
            ]
          ],
          "source_page": 49,
          "source_file": "data/source/Research-Risk-Report-2025.pdf",
          "table_type": "general",
          "confidence": 99.99999999999999,
          "extractor_method": "camelot",
          "metadata": {
            "whitespace": 45.83333333333333,
            "order": 1,
            "flavor": "stream"
          }
        },
        "source_page": 49,
        "source_file": "data/source/Research-Risk-Report-2025.pdf",
        "table_type": "general",
        "confidence": 99.99999999999999,
        "extractor_method": "camelot",
        "conversion_date": "2025-07-18T10:36:09.158728"
      }
    },
    {
      "table_id": "table_68_Camelot_Table_50_53",
      "content": "表格標題: Camelot_Table_50_53\n表格類型: general\n來源頁面: 第50頁\n資料提取方法: camelot\n信心度: 100.0%\n表格欄位: Chinese threat actor targeting sensitive industries\n表格內容:\n  Chinese threat actor targeting sensitive industries: September 2023 - November 2024\n  Chinese threat actor targeting sensitive industries: Targets:\n  Chinese threat actor targeting sensitive industries: • Manufacturing, technology and other industries in Austria, Italy, Argentina, Kazakhstan, France,\n  Chinese threat actor targeting sensitive industries: Philippines, Israel, Czech Republic, Spain, and Turkey\n  Chinese threat actor targeting sensitive industries: Motivation:\n  Chinese threat actor targeting sensitive industries: •\nPossibly intellectual property theft\n  Chinese threat actor targeting sensitive industries: •\nIn November 2024, we had two incident response cases in Europe with similar C&C and TTPs,\n  Chinese threat actor targeting sensitive industries: suggesting a single threat actor behind both operations. Both incidents involved Shadowpad, a\n  Chinese threat actor targeting sensitive industries: malware family used by advanced Chinese threat actors performing espionage. In both cases, a\n  Chinese threat actor targeting sensitive industries: malicious DLL was sideloaded by legitimate executables signed by SentinelOne, Microsoft and\n  Chinese threat actor targeting sensitive industries: Nvidia. We could not attribute with high conﬁdence these incidents to a known threat actor as of\n  Chinese threat actor targeting sensitive industries: writing but found low conﬁdence links to Teleboyi.\n  Chinese threat actor targeting sensitive industries: Trend 2025 Cyber Risk Report\n搜尋關鍵字: Chinese threat actor targeting sensitive industries, Targets:",
      "metadata": {
        "original_table_data": {
          "title": "Camelot_Table_50_53",
          "headers": [
            "Chinese threat actor targeting sensitive industries",
            ""
          ],
          "rows": [
            [
              "September 2023 - November 2024",
              ""
            ],
            [
              "Targets:",
              ""
            ],
            [
              "• Manufacturing, technology and other industries in Austria, Italy, Argentina, Kazakhstan, France,",
              ""
            ],
            [
              "Philippines, Israel, Czech Republic, Spain, and Turkey",
              ""
            ],
            [
              "Motivation:",
              ""
            ],
            [
              "•\nPossibly intellectual property theft",
              ""
            ],
            [
              "•\nIn November 2024, we had two incident response cases in Europe with similar C&C and TTPs,",
              ""
            ],
            [
              "suggesting a single threat actor behind both operations. Both incidents involved Shadowpad, a",
              ""
            ],
            [
              "malware family used by advanced Chinese threat actors performing espionage. In both cases, a",
              ""
            ],
            [
              "malicious DLL was sideloaded by legitimate executables signed by SentinelOne, Microsoft and",
              ""
            ],
            [
              "Nvidia. We could not attribute with high conﬁdence these incidents to a known threat actor as of",
              ""
            ],
            [
              "writing but found low conﬁdence links to Teleboyi.",
              ""
            ],
            [
              "Trend 2025 Cyber Risk Report",
              "50"
            ]
          ],
          "source_page": 50,
          "source_file": "data/source/Research-Risk-Report-2025.pdf",
          "table_type": "general",
          "confidence": 99.99999999999997,
          "extractor_method": "camelot",
          "metadata": {
            "whitespace": 46.42857142857143,
            "order": 1,
            "flavor": "stream"
          }
        },
        "source_page": 50,
        "source_file": "data/source/Research-Risk-Report-2025.pdf",
        "table_type": "general",
        "confidence": 99.99999999999997,
        "extractor_method": "camelot",
        "conversion_date": "2025-07-18T10:36:09.158759"
      }
    },
    {
      "table_id": "table_69_Camelot_Table_51_54",
      "content": "表格標題: Camelot_Table_51_54\n表格類型: general\n來源頁面: 第51頁\n資料提取方法: camelot\n信心度: 89.0%\n表格欄位: Malware\n表格內容:\n  Malware: Top malware families\n  Malware: 60K\n  Malware: 30K\n  Malware: This section shows the top detected malware families in Trend customer environments. Trend Vision One – Endpoint Security provides\n  Malware: prevention and protection capabilities across every stage of the attack chain. Industry-leading intrusion prevention empowers\n  Malware: enterprises to mitigate known but unpatched threats, predict if files are malicious, and detect indicators of attack before they get a\n  Malware: chance to execute.\n  Malware: Trend 2025 Cyber Risk Report\n搜尋關鍵字: Malware, 60K, 51,040",
      "metadata": {
        "original_table_data": {
          "title": "Camelot_Table_51_54",
          "headers": [
            "Malware",
            "",
            ""
          ],
          "rows": [
            [
              "Top malware families",
              "",
              ""
            ],
            [
              "60K",
              "",
              ""
            ],
            [
              "",
              "51,040",
              ""
            ],
            [
              "",
              "45,821",
              ""
            ],
            [
              "",
              "42,418",
              ""
            ],
            [
              "",
              "35,883",
              ""
            ],
            [
              "",
              "33,188\n32,752\n32,208\n31,918",
              ""
            ],
            [
              "",
              "30,856",
              ""
            ],
            [
              "",
              "29,689",
              ""
            ],
            [
              "30K",
              "",
              ""
            ],
            [
              "",
              "0",
              ""
            ],
            [
              "",
              "CoinMiner34 \nPrometei38 \nDownAd40 \nNegasteal36 \nNemucod32",
              ""
            ],
            [
              "",
              "Bondat35 \nPowload37 \nGamarue33 \nDloader39 \nWebShell41",
              ""
            ],
            [
              "This section shows the top detected malware families in Trend customer environments. Trend Vision One – Endpoint Security provides",
              "",
              ""
            ],
            [
              "prevention and protection capabilities across every stage of the attack chain. Industry-leading intrusion prevention empowers",
              "",
              ""
            ],
            [
              "enterprises to mitigate known but unpatched threats, predict if files are malicious, and detect indicators of attack before they get a",
              "",
              ""
            ],
            [
              "chance to execute.",
              "",
              ""
            ],
            [
              "Trend 2025 Cyber Risk Report",
              "",
              "51"
            ]
          ],
          "source_page": 51,
          "source_file": "data/source/Research-Risk-Report-2025.pdf",
          "table_type": "general",
          "confidence": 89.03720181270822,
          "extractor_method": "camelot",
          "metadata": {
            "whitespace": 64.91228070175438,
            "order": 1,
            "flavor": "stream"
          }
        },
        "source_page": 51,
        "source_file": "data/source/Research-Risk-Report-2025.pdf",
        "table_type": "general",
        "confidence": 89.03720181270822,
        "extractor_method": "camelot",
        "conversion_date": "2025-07-18T10:36:09.158789"
      }
    },
    {
      "table_id": "table_70_Camelot_Table_52_55",
      "content": "表格標題: Camelot_Table_52_55\n表格類型: statistical\n來源頁面: 第52頁\n資料提取方法: camelot\n信心度: 93.5%\n表格欄位: Total vulnerabilities and monthly breakdown\n表格內容:\n  Total vulnerabilities and monthly breakdown: 350\n  Total vulnerabilities and monthly breakdown: 300\n  Total vulnerabilities and monthly breakdown: 250\n  Total vulnerabilities and monthly breakdown: 200\n  Total vulnerabilities and monthly breakdown: 150\n  Total vulnerabilities and monthly breakdown: 84\n  Total vulnerabilities and monthly breakdown: 100\n  Total vulnerabilities and monthly breakdown: 50\n搜尋關鍵字: 統計, 數據, 數字, Total vulnerabilities and monthly breakdown, 321, 350, 1,500, 300",
      "metadata": {
        "original_table_data": {
          "title": "Camelot_Table_52_55",
          "headers": [
            "Total vulnerabilities and monthly breakdown",
            "",
            "",
            "",
            "",
            "",
            "",
            "",
            ""
          ],
          "rows": [
            [
              "",
              "",
              "",
              "321",
              "",
              "",
              "",
              "",
              ""
            ],
            [
              "350",
              "",
              "",
              "",
              "",
              "",
              "",
              "",
              "1,500"
            ],
            [
              "300",
              "",
              "",
              "",
              "",
              "",
              "",
              "",
              ""
            ],
            [
              "",
              "",
              "",
              "",
              "",
              "",
              "",
              "",
              "1,200"
            ],
            [
              "250",
              "",
              "",
              "",
              "",
              "",
              "",
              "",
              ""
            ],
            [
              "",
              "",
              "",
              "",
              "",
              "",
              "",
              "179",
              "900"
            ],
            [
              "200",
              "",
              "",
              "",
              "",
              "",
              "",
              "",
              ""
            ],
            [
              "",
              "142",
              "146",
              "157",
              "152",
              "",
              "141",
              "",
              ""
            ],
            [
              "",
              "130",
              "",
              "",
              "",
              "",
              "",
              "",
              ""
            ],
            [
              "150",
              "",
              "",
              "",
              "",
              "",
              "",
              "",
              ""
            ],
            [
              "",
              "",
              "",
              "",
              "",
              "118",
              "",
              "",
              ""
            ],
            [
              "",
              "",
              "",
              "",
              "",
              "",
              "",
              "111",
              "600"
            ],
            [
              "84",
              "",
              "",
              "",
              "",
              "",
              "",
              "",
              ""
            ],
            [
              "100",
              "",
              "",
              "",
              "",
              "",
              "",
              "",
              ""
            ],
            [
              "",
              "",
              "60",
              "",
              "",
              "",
              "",
              "",
              "258"
            ],
            [
              "",
              "",
              "",
              "",
              "",
              "",
              "",
              "",
              "300\n146"
            ],
            [
              "50",
              "",
              "",
              "",
              "",
              "",
              "",
              "",
              ""
            ],
            [
              "",
              "",
              "",
              "",
              "",
              "",
              "",
              "",
              "27"
            ]
          ],
          "source_page": 52,
          "source_file": "data/source/Research-Risk-Report-2025.pdf",
          "table_type": "statistical",
          "confidence": 93.51802447787034,
          "extractor_method": "camelot",
          "metadata": {
            "whitespace": 85.71428571428571,
            "order": 1,
            "flavor": "stream"
          }
        },
        "source_page": 52,
        "source_file": "data/source/Research-Risk-Report-2025.pdf",
        "table_type": "statistical",
        "confidence": 93.51802447787034,
        "extractor_method": "camelot",
        "conversion_date": "2025-07-18T10:36:09.158833"
      }
    },
    {
      "table_id": "table_71_Camelot_Table_53_56",
      "content": "表格標題: Camelot_Table_53_56\n表格類型: general\n來源頁面: 第53頁\n資料提取方法: camelot\n信心度: 100.0%\n表格欄位: Our ZDI monitoring shows an increase in the use of zero-day exploits (a vulnerability exploited before a patch is made available) by\n表格內容:\n  Our ZDI monitoring shows an increase in the use of zero-day exploits (a vulnerability exploited before a patch is made available) by: ransomware groups. Prior to 2020, the use of zero-day exploits by ransomware groups was extremely rare, but there have been 59\n  Our ZDI monitoring shows an increase in the use of zero-day exploits (a vulnerability exploited before a patch is made available) by: zero-day exploits leveraged by ransomware attacks since then. It’s possible that ransomware attacks have become profitable enough\n  Our ZDI monitoring shows an increase in the use of zero-day exploits (a vulnerability exploited before a patch is made available) by: that groups can now pay for zero-days instead of relying on N-day exploits (vulnerabilities exploited after a patch is available). The\n  Our ZDI monitoring shows an increase in the use of zero-day exploits (a vulnerability exploited before a patch is made available) by: lack of alternative markets might also be an influence, in that exploit developers lean more toward taking their wares to underground\n  Our ZDI monitoring shows an increase in the use of zero-day exploits (a vulnerability exploited before a patch is made available) by: auctions.\n搜尋關鍵字: Our ZDI monitoring shows an increase in the use of zero-day exploits (a vulnerability exploited before a patch is made available) by",
      "metadata": {
        "original_table_data": {
          "title": "Camelot_Table_53_56",
          "headers": [
            "Our ZDI monitoring shows an increase in the use of zero-day exploits (a vulnerability exploited before a patch is made available) by"
          ],
          "rows": [
            [
              "ransomware groups. Prior to 2020, the use of zero-day exploits by ransomware groups was extremely rare, but there have been 59"
            ],
            [
              "zero-day exploits leveraged by ransomware attacks since then. It’s possible that ransomware attacks have become profitable enough"
            ],
            [
              "that groups can now pay for zero-days instead of relying on N-day exploits (vulnerabilities exploited after a patch is available). The"
            ],
            [
              "lack of alternative markets might also be an influence, in that exploit developers lean more toward taking their wares to underground"
            ],
            [
              "auctions."
            ]
          ],
          "source_page": 53,
          "source_file": "data/source/Research-Risk-Report-2025.pdf",
          "table_type": "general",
          "confidence": 100.00000000000001,
          "extractor_method": "camelot",
          "metadata": {
            "whitespace": 0.0,
            "order": 1,
            "flavor": "stream"
          }
        },
        "source_page": 53,
        "source_file": "data/source/Research-Risk-Report-2025.pdf",
        "table_type": "general",
        "confidence": 100.00000000000001,
        "extractor_method": "camelot",
        "conversion_date": "2025-07-18T10:36:09.158866"
      }
    },
    {
      "table_id": "table_72_Camelot_Table_54_57",
      "content": "表格標題: Camelot_Table_54_57\n表格類型: general\n來源頁面: 第54頁\n資料提取方法: camelot\n信心度: 81.3%\n表格欄位: External threat monitoring heatmap\n表格內容:\n  External threat monitoring heatmap: Top countries with the most ransomware attacks\n  External threat monitoring heatmap: Trend 2025 Cyber Risk Report\n搜尋關鍵字: External threat monitoring heatmap, 240,117, Germany",
      "metadata": {
        "original_table_data": {
          "title": "Camelot_Table_54_57",
          "headers": [
            "External threat monitoring heatmap",
            "",
            "",
            "",
            "",
            "",
            "",
            ""
          ],
          "rows": [
            [
              "Top countries with the most ransomware attacks",
              "",
              "",
              "",
              "",
              "",
              "",
              ""
            ],
            [
              "",
              "",
              "",
              "240,117",
              "",
              "",
              "",
              ""
            ],
            [
              "",
              "",
              "",
              "Germany",
              "",
              "",
              "",
              ""
            ],
            [
              "",
              "1,347,243",
              "",
              "",
              "",
              "",
              "394,351",
              ""
            ],
            [
              "",
              "",
              "",
              "",
              "",
              "181,573",
              "",
              ""
            ],
            [
              "",
              "United States",
              "",
              "",
              "514,019",
              "",
              "Japan",
              ""
            ],
            [
              "",
              "",
              "",
              "",
              "",
              "South Korea",
              "",
              ""
            ],
            [
              "",
              "",
              "",
              "",
              "Turkey",
              "",
              "",
              ""
            ],
            [
              "",
              "",
              "",
              "",
              "",
              "1,134,833",
              "",
              ""
            ],
            [
              "",
              "",
              "",
              "",
              "",
              "Thailand",
              "",
              ""
            ],
            [
              "",
              "",
              "",
              "",
              "",
              "",
              "474,488",
              ""
            ],
            [
              "",
              "",
              "",
              "",
              "",
              "Taiwan\n209,282",
              "",
              ""
            ],
            [
              "",
              "",
              "",
              "",
              "",
              "India",
              "",
              ""
            ],
            [
              "",
              "",
              "241,511",
              "",
              "",
              "",
              "",
              ""
            ],
            [
              "",
              "",
              "Brazil",
              "",
              "",
              "",
              "",
              ""
            ],
            [
              "",
              "",
              "",
              "",
              "",
              "169,211",
              "",
              ""
            ],
            [
              "",
              "",
              "",
              "",
              "",
              "Singapore",
              "",
              ""
            ],
            [
              "",
              "This heatmap presents the regions and countries that our telemetry tracked as having the most ransomware threat activity.",
              "",
              "",
              "",
              "",
              "",
              ""
            ],
            [
              "",
              "Figures in each map represent ransomware threats that have been detected and blocked by our sensors. It’s important to note that",
              "",
              "",
              "",
              "",
              "",
              ""
            ],
            [
              "",
              "cybercriminals do not target any country or region specifically. However, these numbers show areas that should take extra precautions",
              "",
              "",
              "",
              "",
              "",
              ""
            ],
            [
              "",
              "to make enterprise systems more resilient against ransomware attacks.",
              "",
              "",
              "",
              "",
              "",
              ""
            ],
            [
              "Trend 2025 Cyber Risk Report",
              "",
              "",
              "",
              "",
              "",
              "",
              "54"
            ]
          ],
          "source_page": 54,
          "source_file": "data/source/Research-Risk-Report-2025.pdf",
          "table_type": "general",
          "confidence": 81.30217695914645,
          "extractor_method": "camelot",
          "metadata": {
            "whitespace": 86.5,
            "order": 1,
            "flavor": "stream"
          }
        },
        "source_page": 54,
        "source_file": "data/source/Research-Risk-Report-2025.pdf",
        "table_type": "general",
        "confidence": 81.30217695914645,
        "extractor_method": "camelot",
        "conversion_date": "2025-07-18T10:36:09.158926"
      }
    },
    {
      "table_id": "table_73_Camelot_Table_55_58",
      "content": "表格標題: Camelot_Table_55_58\n表格類型: general\n來源頁面: 第55頁\n資料提取方法: camelot\n信心度: 87.5%\n表格欄位: Top countries with the most malware detections\n表格內容:\n  Top countries with the most malware detections: 661,026,169\n  Top countries with the most malware detections: United States\n搜尋關鍵字: Top countries with the most malware detections, 101,644,979, 188,554,351, United Kingdom",
      "metadata": {
        "original_table_data": {
          "title": "Camelot_Table_55_58",
          "headers": [
            "",
            "Top countries with the most malware detections",
            "",
            "",
            "",
            "",
            "",
            ""
          ],
          "rows": [
            [
              "",
              "",
              "",
              "101,644,979",
              "",
              "",
              "",
              ""
            ],
            [
              "",
              "",
              "",
              "",
              "188,554,351",
              "",
              "",
              ""
            ],
            [
              "",
              "",
              "",
              "United Kingdom",
              "",
              "",
              "",
              ""
            ],
            [
              "",
              "",
              "",
              "",
              "Germany",
              "",
              "",
              ""
            ],
            [
              "",
              "661,026,169",
              "",
              "",
              "",
              "",
              "1,008,580,748",
              ""
            ],
            [
              "",
              "United States",
              "",
              "",
              "",
              "",
              "Japan",
              ""
            ],
            [
              "",
              "",
              "",
              "149,799,897",
              "",
              "193,155,280",
              "",
              ""
            ],
            [
              "",
              "",
              "",
              "France",
              "129,207,144",
              "India",
              "",
              ""
            ],
            [
              "",
              "",
              "",
              "",
              "Italy",
              "",
              "",
              ""
            ],
            [
              "",
              "",
              "",
              "",
              "",
              "",
              "176,754,704",
              ""
            ],
            [
              "",
              "",
              "",
              "",
              "",
              "",
              "Taiwan",
              ""
            ],
            [
              "",
              "",
              "168,021,421",
              "",
              "",
              "",
              "",
              ""
            ],
            [
              "",
              "",
              "Brazil",
              "",
              "",
              "",
              "",
              ""
            ],
            [
              "",
              "",
              "",
              "",
              "",
              "",
              "98,987,181",
              ""
            ],
            [
              "",
              "",
              "",
              "",
              "",
              "",
              "Australia",
              ""
            ],
            [
              "This heatmap presents the regions and countries that our telemetry tracked as having the most malware threats detected and blocked",
              "",
              "",
              "",
              "",
              "",
              "",
              ""
            ],
            [
              "by our sensors. It’s important to note that cybercriminals do not target any country or region specifically. However, these numbers",
              "",
              "",
              "",
              "",
              "",
              "",
              ""
            ],
            [
              "show areas that should take extra precautions to make enterprise systems more resilient against malware attack campaigns.",
              "",
              "",
              "",
              "",
              "",
              "",
              ""
            ],
            [
              "Trend 2025 Cyber Risk Report",
              "",
              "",
              "",
              "",
              "",
              "",
              "55"
            ]
          ],
          "source_page": 55,
          "source_file": "data/source/Research-Risk-Report-2025.pdf",
          "table_type": "general",
          "confidence": 87.5131702463703,
          "extractor_method": "camelot",
          "metadata": {
            "whitespace": 83.75,
            "order": 1,
            "flavor": "stream"
          }
        },
        "source_page": 55,
        "source_file": "data/source/Research-Risk-Report-2025.pdf",
        "table_type": "general",
        "confidence": 87.5131702463703,
        "extractor_method": "camelot",
        "conversion_date": "2025-07-18T10:36:09.158979"
      }
    },
    {
      "table_id": "table_74_Camelot_Table_56_59",
      "content": "表格標題: Camelot_Table_56_59\n表格類型: general\n來源頁面: 第56頁\n資料提取方法: camelot\n信心度: 91.9%\n表格欄位: Top countries with the most detected email threats\n表格內容:\n  Top countries with the most detected email threats: This heatmap presents regions and countries where our telemetry tracked email threats originated from. Email threats detected by\n  Top countries with the most detected email threats: our sensors deployed globally scan for their originating IP addresses and reveal where they come from.\n  Top countries with the most detected email threats: Trend 2025 Cyber Risk Report\n搜尋關鍵字: Top countries with the most detected email threats, 732,679,789, 395,609,663, Canada",
      "metadata": {
        "original_table_data": {
          "title": "Camelot_Table_56_59",
          "headers": [
            "Top countries with the most detected email threats",
            "",
            "",
            "",
            ""
          ],
          "rows": [
            [
              "",
              "732,679,789",
              "",
              "",
              ""
            ],
            [
              "",
              "",
              "",
              "395,609,663",
              ""
            ],
            [
              "",
              "Canada",
              "",
              "",
              ""
            ],
            [
              "",
              "",
              "",
              "Russia",
              ""
            ],
            [
              "",
              "",
              "644,570,215",
              "",
              ""
            ],
            [
              "",
              "",
              "",
              "534,517,762",
              ""
            ],
            [
              "",
              "",
              "United Kingdom",
              "",
              ""
            ],
            [
              "",
              "",
              "",
              "Netherlands",
              ""
            ],
            [
              "",
              "4,095,791,263",
              "",
              "",
              ""
            ],
            [
              "",
              "United States",
              "",
              "",
              ""
            ],
            [
              "",
              "",
              "",
              "947,614,419",
              ""
            ],
            [
              "",
              "",
              "",
              "China\n827,350,062",
              ""
            ],
            [
              "",
              "",
              "",
              "Germany",
              ""
            ],
            [
              "",
              "",
              "1,022,307,312",
              "",
              ""
            ],
            [
              "",
              "",
              "France",
              "",
              ""
            ],
            [
              "",
              "",
              "",
              "398,001,086",
              ""
            ],
            [
              "",
              "",
              "",
              "1,030,130,818",
              ""
            ],
            [
              "",
              "",
              "",
              "Indonesia",
              ""
            ],
            [
              "",
              "",
              "",
              "India",
              ""
            ],
            [
              "This heatmap presents regions and countries where our telemetry tracked email threats originated from. Email threats detected by",
              "",
              "",
              "",
              ""
            ],
            [
              "our sensors deployed globally scan for their originating IP addresses and reveal where they come from.",
              "",
              "",
              "",
              ""
            ],
            [
              "Trend 2025 Cyber Risk Report",
              "",
              "",
              "",
              "56"
            ]
          ],
          "source_page": 56,
          "source_file": "data/source/Research-Risk-Report-2025.pdf",
          "table_type": "general",
          "confidence": 91.85138661279406,
          "extractor_method": "camelot",
          "metadata": {
            "whitespace": 80.0,
            "order": 1,
            "flavor": "stream"
          }
        },
        "source_page": 56,
        "source_file": "data/source/Research-Risk-Report-2025.pdf",
        "table_type": "general",
        "confidence": 91.85138661279406,
        "extractor_method": "camelot",
        "conversion_date": "2025-07-18T10:36:09.159015"
      }
    },
    {
      "table_id": "table_75_Camelot_Table_57_60",
      "content": "表格標題: Camelot_Table_57_60\n表格類型: general\n來源頁面: 第57頁\n資料提取方法: camelot\n信心度: 100.0%\n表格欄位: From Reactive\n表格內容:\n  From Reactive: to Proactive\n搜尋關鍵字: From Reactive, to Proactive",
      "metadata": {
        "original_table_data": {
          "title": "Camelot_Table_57_60",
          "headers": [
            "From Reactive"
          ],
          "rows": [
            [
              "to Proactive"
            ]
          ],
          "source_page": 57,
          "source_file": "data/source/Research-Risk-Report-2025.pdf",
          "table_type": "general",
          "confidence": 100.0,
          "extractor_method": "camelot",
          "metadata": {
            "whitespace": 0.0,
            "order": 1,
            "flavor": "stream"
          }
        },
        "source_page": 57,
        "source_file": "data/source/Research-Risk-Report-2025.pdf",
        "table_type": "general",
        "confidence": 100.0,
        "extractor_method": "camelot",
        "conversion_date": "2025-07-18T10:36:09.159028"
      }
    },
    {
      "table_id": "table_76_Camelot_Table_58_61",
      "content": "表格標題: Camelot_Table_58_61\n表格類型: general\n來源頁面: 第58頁\n資料提取方法: camelot\n信心度: 100.0%\n表格欄位: A risk-based approach to cybersecurity will shift an enterprise’s strategy from being reactive to proactive. By identifying the\n表格內容:\n  A risk-based approach to cybersecurity will shift an enterprise’s strategy from being reactive to proactive. By identifying the: weaknesses in the defenses and by understanding how cybercriminals are using these exposures to their benefit, enterprises can take\n  A risk-based approach to cybersecurity will shift an enterprise’s strategy from being reactive to proactive. By identifying the: the necessary countermeasures to create a more secure defense before the inevitable next cyberattack happens. When an enterprise\n  A risk-based approach to cybersecurity will shift an enterprise’s strategy from being reactive to proactive. By identifying the: recalibrates to be more proactive, it can make its time and resource allocation more efficient even as it expands and demands more\n  A risk-based approach to cybersecurity will shift an enterprise’s strategy from being reactive to proactive. By identifying the: security coverage.\n搜尋關鍵字: A risk-based approach to cybersecurity will shift an enterprise’s strategy from being reactive to proactive. By identifying the",
      "metadata": {
        "original_table_data": {
          "title": "Camelot_Table_58_61",
          "headers": [
            "A risk-based approach to cybersecurity will shift an enterprise’s strategy from being reactive to proactive. By identifying the"
          ],
          "rows": [
            [
              "weaknesses in the defenses and by understanding how cybercriminals are using these exposures to their benefit, enterprises can take"
            ],
            [
              "the necessary countermeasures to create a more secure defense before the inevitable next cyberattack happens. When an enterprise"
            ],
            [
              "recalibrates to be more proactive, it can make its time and resource allocation more efficient even as it expands and demands more"
            ],
            [
              "security coverage."
            ]
          ],
          "source_page": 58,
          "source_file": "data/source/Research-Risk-Report-2025.pdf",
          "table_type": "general",
          "confidence": 100.0,
          "extractor_method": "camelot",
          "metadata": {
            "whitespace": 0.0,
            "order": 1,
            "flavor": "stream"
          }
        },
        "source_page": 58,
        "source_file": "data/source/Research-Risk-Report-2025.pdf",
        "table_type": "general",
        "confidence": 100.0,
        "extractor_method": "camelot",
        "conversion_date": "2025-07-18T10:36:09.159048"
      }
    },
    {
      "table_id": "table_77_Camelot_Table_59_62",
      "content": "表格標題: Camelot_Table_59_62\n表格類型: general\n來源頁面: 第59頁\n資料提取方法: camelot\n信心度: 84.6%\n表格欄位: 4. Apply the latest patches or upgrade the version of applications regularly.\n表格內容:\n  4. Apply the latest patches or upgrade the version of applications regularly.: 5. Apply the latest patches or upgrade the operating system version regularly.\n  4. Apply the latest patches or upgrade the version of applications regularly.: Adopt a risk-based approach to anticipate threats, strategize resource allocation, tailor security measures, and enhance situational\n  4. Apply the latest patches or upgrade the version of applications regularly.: awareness with the continuous discovery, assessment and mitigation of an enterprise’s IT ecosystem. By identifying high, medium, and\n  4. Apply the latest patches or upgrade the version of applications regularly.: low risk components of the attack surface, organizations can create an action plan to prevent attacks before they even happen and\n  4. Apply the latest patches or upgrade the version of applications regularly.: lower their overall risk in the near, medium, and long term.\n  4. Apply the latest patches or upgrade the version of applications regularly.: Trend 2025 Cyber Risk Report\n搜尋關鍵字: 4. Apply the latest patches or upgrade the version of applications regularly.",
      "metadata": {
        "original_table_data": {
          "title": "Camelot_Table_59_62",
          "headers": [
            "4. Apply the latest patches or upgrade the version of applications regularly.",
            ""
          ],
          "rows": [
            [
              "5. Apply the latest patches or upgrade the operating system version regularly.",
              ""
            ],
            [
              "Adopt a risk-based approach to anticipate threats, strategize resource allocation, tailor security measures, and enhance situational",
              ""
            ],
            [
              "awareness with the continuous discovery, assessment and mitigation of an enterprise’s IT ecosystem. By identifying high, medium, and",
              ""
            ],
            [
              "low risk components of the attack surface, organizations can create an action plan to prevent attacks before they even happen and",
              ""
            ],
            [
              "lower their overall risk in the near, medium, and long term.",
              ""
            ],
            [
              "Trend 2025 Cyber Risk Report",
              "59"
            ]
          ],
          "source_page": 59,
          "source_file": "data/source/Research-Risk-Report-2025.pdf",
          "table_type": "general",
          "confidence": 84.5822890834793,
          "extractor_method": "camelot",
          "metadata": {
            "whitespace": 42.857142857142854,
            "order": 1,
            "flavor": "stream"
          }
        },
        "source_page": 59,
        "source_file": "data/source/Research-Risk-Report-2025.pdf",
        "table_type": "general",
        "confidence": 84.5822890834793,
        "extractor_method": "camelot",
        "conversion_date": "2025-07-18T10:36:09.159069"
      }
    },
    {
      "table_id": "table_78_Camelot_Table_60_63",
      "content": "表格標題: Camelot_Table_60_63\n表格類型: time_series\n來源頁面: 第60頁\n資料提取方法: camelot\n信心度: 98.5%\n表格欄位: Endnotes\n表格內容:\n  Endnotes: 1 \nTrend Micro. (n.d.). Trend Micro. “Cyber Risk Exposure Management”. Accessed on Mar. 21, 2025, at: Link.\n  Endnotes: 2  Trend Micro. (n.d.). Trend Micro. “One Platform”. Accessed on Mar. 21, 2025, at: Link.\n  Endnotes: 3  Trend Micro. (n.d.). Trend Micro. “XDR (Extended Detection and Response)”. Accessed on Mar. 21, 2025, at: Link.\n  Endnotes: 4  Trend Micro. (February 10, 2025). Trend Micro. “From Vulnerable to Resilient: Cutting Ransomware Risk with Proactive Attack Surface\n  Endnotes: Management”. Accessed on Mar. 21, 2025, at: Link.\n  Endnotes: 5  Trend Micro. (n.d.). Trend Micro. “Trend Vision One Risk Index Overview”. Accessed on Mar. 21, 2025, at: Link.\n  Endnotes: 6  Trend Micro. (n.d.). Trend Micro. “More Than a Number: Your Risk Score Explained”. Accessed on Mar. 21, 2025, at: Link.\n  Endnotes: 7  Digital Operational Resilience Act. (n.d.). Digital Operational Resilience Act. “Official Website”. Accessed on Mar. 21, 2025, at: Link.\n  Endnotes: 8  European Commission. (n.d.). Digital Strategy - European Commission. “Cyber Resilience Act”. Accessed on Mar. 21, 2025, at: Link.\n  Endnotes: 9  Trend Micro. (n.d.). Trend Micro. “Email and Collaboration Security”. Accessed on Mar. 21, 2025, at: Link.\n  Endnotes: 10 Trend Micro. (n.d.). Trend Micro. “Identity and Access Management”. Accessed on Mar. 21, 2025, at: Link.\n  Endnotes: 11  Trend Micro. (n.d.). Trend Micro. “Endpoint Security”. Accessed on Mar. 21, 2025, at: Link.\n  Endnotes: 12  Trend Micro. (n.d.). Trend Micro. “Hybrid Cloud Security”. Accessed on Mar. 21, 2025, at: Link.\n  Endnotes: 13  CISA. (Sep. 28, 2021). Cybersecurity & Infrastructure Security Agency (CISA). “RCE Vulnerability in Hikvision Cameras (CVE-2021-36260)”. Accessed\n  Endnotes: on Mar. 21, 2025, at: Link.\n  Endnotes: Trend 2025 Cyber Risk Report\n搜尋關鍵字: Endnotes",
      "metadata": {
        "original_table_data": {
          "title": "Camelot_Table_60_63",
          "headers": [
            "Endnotes",
            ""
          ],
          "rows": [
            [
              "1 \nTrend Micro. (n.d.). Trend Micro. “Cyber Risk Exposure Management”. Accessed on Mar. 21, 2025, at: Link.",
              ""
            ],
            [
              "2  Trend Micro. (n.d.). Trend Micro. “One Platform”. Accessed on Mar. 21, 2025, at: Link.",
              ""
            ],
            [
              "3  Trend Micro. (n.d.). Trend Micro. “XDR (Extended Detection and Response)”. Accessed on Mar. 21, 2025, at: Link.",
              ""
            ],
            [
              "4  Trend Micro. (February 10, 2025). Trend Micro. “From Vulnerable to Resilient: Cutting Ransomware Risk with Proactive Attack Surface",
              ""
            ],
            [
              "Management”. Accessed on Mar. 21, 2025, at: Link.",
              ""
            ],
            [
              "5  Trend Micro. (n.d.). Trend Micro. “Trend Vision One Risk Index Overview”. Accessed on Mar. 21, 2025, at: Link.",
              ""
            ],
            [
              "6  Trend Micro. (n.d.). Trend Micro. “More Than a Number: Your Risk Score Explained”. Accessed on Mar. 21, 2025, at: Link.",
              ""
            ],
            [
              "7  Digital Operational Resilience Act. (n.d.). Digital Operational Resilience Act. “Official Website”. Accessed on Mar. 21, 2025, at: Link.",
              ""
            ],
            [
              "8  European Commission. (n.d.). Digital Strategy - European Commission. “Cyber Resilience Act”. Accessed on Mar. 21, 2025, at: Link.",
              ""
            ],
            [
              "9  Trend Micro. (n.d.). Trend Micro. “Email and Collaboration Security”. Accessed on Mar. 21, 2025, at: Link.",
              ""
            ],
            [
              "10 Trend Micro. (n.d.). Trend Micro. “Identity and Access Management”. Accessed on Mar. 21, 2025, at: Link.",
              ""
            ],
            [
              "11  Trend Micro. (n.d.). Trend Micro. “Endpoint Security”. Accessed on Mar. 21, 2025, at: Link.",
              ""
            ],
            [
              "12  Trend Micro. (n.d.). Trend Micro. “Hybrid Cloud Security”. Accessed on Mar. 21, 2025, at: Link.",
              ""
            ],
            [
              "13  CISA. (Sep. 28, 2021). Cybersecurity & Infrastructure Security Agency (CISA). “RCE Vulnerability in Hikvision Cameras (CVE-2021-36260)”. Accessed",
              ""
            ],
            [
              "on Mar. 21, 2025, at: Link.",
              ""
            ],
            [
              "Trend 2025 Cyber Risk Report",
              "60"
            ]
          ],
          "source_page": 60,
          "source_file": "data/source/Research-Risk-Report-2025.pdf",
          "table_type": "time_series",
          "confidence": 98.49551096643066,
          "extractor_method": "camelot",
          "metadata": {
            "whitespace": 47.05882352941176,
            "order": 1,
            "flavor": "stream"
          }
        },
        "source_page": 60,
        "source_file": "data/source/Research-Risk-Report-2025.pdf",
        "table_type": "time_series",
        "confidence": 98.49551096643066,
        "extractor_method": "camelot",
        "conversion_date": "2025-07-18T10:36:09.159112"
      }
    },
    {
      "table_id": "table_79_Camelot_Table_61_64",
      "content": "表格標題: Camelot_Table_61_64\n表格類型: time_series\n來源頁面: 第61頁\n資料提取方法: camelot\n信心度: 100.0%\n表格欄位: 14 NIST. (Sep. 22, 2021). National Institute of Standards and Technology (NIST). “CVE-2021-36260 Detail”. Accessed on Mar. 21, 2025, at: Link.\n表格內容:\n  14 NIST. (Sep. 22, 2021). National Institute of Standards and Technology (NIST). “CVE-2021-36260 Detail”. Accessed on Mar. 21, 2025, at: Link.: 15 NIST. (Feb. 13, 2024)”. National Vulnerability Database (NVD). “CVE-2024-21357”. Accessed on Mar. 21, 2025, at: Link.\n  14 NIST. (Sep. 22, 2021). National Institute of Standards and Technology (NIST). “CVE-2021-36260 Detail”. Accessed on Mar. 21, 2025, at: Link.: 16 NIST. (June 11, 2024). National Vulnerability Database (NVD). “CVE-2024-30086”. Accessed on Mar. 21, 2025, at: Link.\n  14 NIST. (Sep. 22, 2021). National Institute of Standards and Technology (NIST). “CVE-2021-36260 Detail”. Accessed on Mar. 21, 2025, at: Link.: 17  NIST. (June 11, 2024). National Vulnerability Database (NVD). “CVE-2024-30082”. Accessed on Mar. 21, 2025, at: Link.\n  14 NIST. (Sep. 22, 2021). National Institute of Standards and Technology (NIST). “CVE-2021-36260 Detail”. Accessed on Mar. 21, 2025, at: Link.: 18 NIST. (June 11, 2024). National Vulnerability Database (NVD). “CVE-2024-30087”. Accessed on Mar. 21, 2025, at: Link.\n  14 NIST. (Sep. 22, 2021). National Institute of Standards and Technology (NIST). “CVE-2021-36260 Detail”. Accessed on Mar. 21, 2025, at: Link.: 19 NIST. (June 11, 2024). National Vulnerability Database (NVD). “CVE-2024-35250”. Accessed on Mar. 21, 2025, at: Link.\n  14 NIST. (Sep. 22, 2021). National Institute of Standards and Technology (NIST). “CVE-2021-36260 Detail”. Accessed on Mar. 21, 2025, at: Link.: 20 NIST. (June 11, 2024). National Vulnerability Database (NVD). “CVE-2024-30091”. Accessed on Mar. 21, 2025, at: Link.\n  14 NIST. (Sep. 22, 2021). National Institute of Standards and Technology (NIST). “CVE-2021-36260 Detail”. Accessed on Mar. 21, 2025, at: Link.: 21  NIST. (May 14, 2024). National Vulnerability Database (NVD). “CVE-2024-30049”. Accessed on Mar. 21, 2025, at: Link.\n  14 NIST. (Sep. 22, 2021). National Institute of Standards and Technology (NIST). “CVE-2021-36260 Detail”. Accessed on Mar. 21, 2025, at: Link.: 22 NIST. (June 11, 2024). National Vulnerability Database (NVD). “CVE-2024-30084”. Accessed on Mar. 21, 2025, at: Link.\n  14 NIST. (Sep. 22, 2021). National Institute of Standards and Technology (NIST). “CVE-2021-36260 Detail”. Accessed on Mar. 21, 2025, at: Link.: 23 NIST. (May 14, 2024). National Vulnerability Database (NVD). “CVE-2024-30050”. Accessed on Mar. 21, 2025, at: Link.\n  14 NIST. (Sep. 22, 2021). National Institute of Standards and Technology (NIST). “CVE-2021-36260 Detail”. Accessed on Mar. 21, 2025, at: Link.: 24 NIST. (May 14, 2024). National Vulnerability Database (NVD). “CVE-2024-30037”. Accessed on Mar 21, 2025, at: Link.\n  14 NIST. (Sep. 22, 2021). National Institute of Standards and Technology (NIST). “CVE-2021-36260 Detail”. Accessed on Mar. 21, 2025, at: Link.: 25 Gennai Security Project. (Nov. 17, 2024). Gennai Security Project. “OWASP Top 10 for LLM Applications 2025”. Accessed on Mar. 21, 2025, at: Link.\n  14 NIST. (Sep. 22, 2021). National Institute of Standards and Technology (NIST). “CVE-2021-36260 Detail”. Accessed on Mar. 21, 2025, at: Link.: 26 AI Team. (Aug. 15, 2024). Trend Micro. “Rogue AI: Part 1”. Accessed on Mar. 21, 2025, at: Link.\n  14 NIST. (Sep. 22, 2021). National Institute of Standards and Technology (NIST). “CVE-2021-36260 Detail”. Accessed on Mar. 21, 2025, at: Link.: 27 Nada Elrayes. (Sep. 26, 2024). Trend Micro. “Countering AI-Driven Threats with AI-Powered Defense”. Accessed on Mar. 21, 2025, at: Link.\n  14 NIST. (Sep. 22, 2021). National Institute of Standards and Technology (NIST). “CVE-2021-36260 Detail”. Accessed on Mar. 21, 2025, at: Link.: 28 Trend Micro. (Sep. 19, 2024). Trend Micro. “The Illusion of Choice: Uncovering Electoral Deceptions in the Age of AI”. Accessed on Mar. 21, 2025, at:\n搜尋關鍵字: 14 NIST. (Sep. 22, 2021). National Institute of Standards and Technology (NIST). “CVE-2021-36260 Detail”. Accessed on Mar. 21, 2025, at: Link.",
      "metadata": {
        "original_table_data": {
          "title": "Camelot_Table_61_64",
          "headers": [
            "14 NIST. (Sep. 22, 2021). National Institute of Standards and Technology (NIST). “CVE-2021-36260 Detail”. Accessed on Mar. 21, 2025, at: Link."
          ],
          "rows": [
            [
              "15 NIST. (Feb. 13, 2024)”. National Vulnerability Database (NVD). “CVE-2024-21357”. Accessed on Mar. 21, 2025, at: Link."
            ],
            [
              "16 NIST. (June 11, 2024). National Vulnerability Database (NVD). “CVE-2024-30086”. Accessed on Mar. 21, 2025, at: Link."
            ],
            [
              "17  NIST. (June 11, 2024). National Vulnerability Database (NVD). “CVE-2024-30082”. Accessed on Mar. 21, 2025, at: Link."
            ],
            [
              "18 NIST. (June 11, 2024). National Vulnerability Database (NVD). “CVE-2024-30087”. Accessed on Mar. 21, 2025, at: Link."
            ],
            [
              "19 NIST. (June 11, 2024). National Vulnerability Database (NVD). “CVE-2024-35250”. Accessed on Mar. 21, 2025, at: Link."
            ],
            [
              "20 NIST. (June 11, 2024). National Vulnerability Database (NVD). “CVE-2024-30091”. Accessed on Mar. 21, 2025, at: Link."
            ],
            [
              "21  NIST. (May 14, 2024). National Vulnerability Database (NVD). “CVE-2024-30049”. Accessed on Mar. 21, 2025, at: Link."
            ],
            [
              "22 NIST. (June 11, 2024). National Vulnerability Database (NVD). “CVE-2024-30084”. Accessed on Mar. 21, 2025, at: Link."
            ],
            [
              "23 NIST. (May 14, 2024). National Vulnerability Database (NVD). “CVE-2024-30050”. Accessed on Mar. 21, 2025, at: Link."
            ],
            [
              "24 NIST. (May 14, 2024). National Vulnerability Database (NVD). “CVE-2024-30037”. Accessed on Mar 21, 2025, at: Link."
            ],
            [
              "25 Gennai Security Project. (Nov. 17, 2024). Gennai Security Project. “OWASP Top 10 for LLM Applications 2025”. Accessed on Mar. 21, 2025, at: Link."
            ],
            [
              "26 AI Team. (Aug. 15, 2024). Trend Micro. “Rogue AI: Part 1”. Accessed on Mar. 21, 2025, at: Link."
            ],
            [
              "27 Nada Elrayes. (Sep. 26, 2024). Trend Micro. “Countering AI-Driven Threats with AI-Powered Defense”. Accessed on Mar. 21, 2025, at: Link."
            ],
            [
              "28 Trend Micro. (Sep. 19, 2024). Trend Micro. “The Illusion of Choice: Uncovering Electoral Deceptions in the Age of AI”. Accessed on Mar. 21, 2025, at:"
            ]
          ],
          "source_page": 61,
          "source_file": "data/source/Research-Risk-Report-2025.pdf",
          "table_type": "time_series",
          "confidence": 100.00000000000001,
          "extractor_method": "camelot",
          "metadata": {
            "whitespace": 0.0,
            "order": 1,
            "flavor": "stream"
          }
        },
        "source_page": 61,
        "source_file": "data/source/Research-Risk-Report-2025.pdf",
        "table_type": "time_series",
        "confidence": 100.00000000000001,
        "extractor_method": "camelot",
        "conversion_date": "2025-07-18T10:36:09.159147"
      }
    },
    {
      "table_id": "table_80_Camelot_Table_62_65",
      "content": "表格標題: Camelot_Table_62_65\n表格類型: time_series\n來源頁面: 第62頁\n資料提取方法: camelot\n信心度: 87.8%\n表格欄位: 29 Trend Research. (n.d.). Trend Micro. “Unmasking Pig Butchering Scams and Protecting Your Financial Future”. Accessed on Mar. 21, 2025, at: Link.\n表格內容:\n  29 Trend Research. (n.d.). Trend Micro. “Unmasking Pig Butchering Scams and Protecting Your Financial Future”. Accessed on Mar. 21, 2025, at: Link.: 30 Craig Gibson, Josiah Hagen. (June 28, 2023). Trend Micro. “How Cybercriminals Can Perform Virtual Kidnapping Scams Using AI Voice Cloning\n  29 Trend Research. (n.d.). Trend Micro. “Unmasking Pig Butchering Scams and Protecting Your Financial Future”. Accessed on Mar. 21, 2025, at: Link.: Tools and ChatGPT”. Accessed on Mar. 21, 2025, at: Link.\n  29 Trend Research. (n.d.). Trend Micro. “Unmasking Pig Butchering Scams and Protecting Your Financial Future”. Accessed on Mar. 21, 2025, at: Link.: 31  Trend Micro. (Dec. 16, 2024). Trend Micro. “Trend Micro Predicts Emergence of Deepfake-Powered Malicious Digital Twins”. Accessed on Mar. 21,\n  29 Trend Research. (n.d.). Trend Micro. “Unmasking Pig Butchering Scams and Protecting Your Financial Future”. Accessed on Mar. 21, 2025, at: Link.: 2025, at: Link.\n  29 Trend Research. (n.d.). Trend Micro. “Unmasking Pig Butchering Scams and Protecting Your Financial Future”. Accessed on Mar. 21, 2025, at: Link.: 32 Trend Micro. (n.d.). Trend Micro. “Coinminer.Win32.MalXMR.Ads”. Accessed on Mar. 21, 2025, at: Link.\n  29 Trend Research. (n.d.). Trend Micro. “Unmasking Pig Butchering Scams and Protecting Your Financial Future”. Accessed on Mar. 21, 2025, at: Link.: 33 Trend Micro. (n.d.). Trend Micro. “LNK_Bondat.SM”. Accessed on Mar. 21, 2025, at: Link.\n  29 Trend Research. (n.d.). Trend Micro. “Unmasking Pig Butchering Scams and Protecting Your Financial Future”. Accessed on Mar. 21, 2025, at: Link.: 34 Trend Micro. (n.d.). Trend Micro. “Tspy_Negasteal”. Accessed on Mar. 21, 2025, at: Link.\n  29 Trend Research. (n.d.). Trend Micro. “Unmasking Pig Butchering Scams and Protecting Your Financial Future”. Accessed on Mar. 21, 2025, at: Link.: 35 Trend Micro. (n.d.). Trend Micro. “Trojan.PS1.Powload.JKP”. Accessed on Mar. 21, 2025, at: Link.\n  29 Trend Research. (n.d.). Trend Micro. “Unmasking Pig Butchering Scams and Protecting Your Financial Future”. Accessed on Mar. 21, 2025, at: Link.: 36 Trend Micro. (n.d.). Trend Micro. “JS_Nemucod.SMC”. Accessed on Mar. 21, 2025, at: Link.\n  29 Trend Research. (n.d.). Trend Micro. “Unmasking Pig Butchering Scams and Protecting Your Financial Future”. Accessed on Mar. 21, 2025, at: Link.: 37 Trend Micro. (n.d.). Trend Micro. “Worm_Gamarue.SMJA”. Accessed on Mar. 21, 2025, at: Link.\n  29 Trend Research. (n.d.). Trend Micro. “Unmasking Pig Butchering Scams and Protecting Your Financial Future”. Accessed on Mar. 21, 2025, at: Link.: 38 Trend Micro. (n.d.). Trend Micro. “Trojan.Win32.Prometei.E”. Accessed on Mar. 21, 2025, at: Link.\n  29 Trend Research. (n.d.). Trend Micro. “Unmasking Pig Butchering Scams and Protecting Your Financial Future”. Accessed on Mar. 21, 2025, at: Link.: 39 Trend Micro. (n.d.). Trend Micro. “Worm.Win32.Dloader.LGA”. Accessed on Mar. 21, 2025, at: Link.\n  29 Trend Research. (n.d.). Trend Micro. “Unmasking Pig Butchering Scams and Protecting Your Financial Future”. Accessed on Mar. 21, 2025, at: Link.: 40 Trend Micro. (n.d.).Trend Micro. “Troj_Downad.E”. Accessed on Mar. 21, 2025, at: Link.\n  29 Trend Research. (n.d.). Trend Micro. “Unmasking Pig Butchering Scams and Protecting Your Financial Future”. Accessed on Mar. 21, 2025, at: Link.: 41 Trend Micro. (n.d.). Trend Micro. “Trojan.PHP.Webshell.SBJKUC”. Accessed on Mar. 21, 2025, at: Link.\n  29 Trend Research. (n.d.). Trend Micro. “Unmasking Pig Butchering Scams and Protecting Your Financial Future”. Accessed on Mar. 21, 2025, at: Link.: Trend 2025 Cyber Risk Report\n搜尋關鍵字: 29 Trend Research. (n.d.). Trend Micro. “Unmasking Pig Butchering Scams and Protecting Your Financial Future”. Accessed on Mar. 21, 2025, at: Link.",
      "metadata": {
        "original_table_data": {
          "title": "Camelot_Table_62_65",
          "headers": [
            "29 Trend Research. (n.d.). Trend Micro. “Unmasking Pig Butchering Scams and Protecting Your Financial Future”. Accessed on Mar. 21, 2025, at: Link.",
            ""
          ],
          "rows": [
            [
              "30 Craig Gibson, Josiah Hagen. (June 28, 2023). Trend Micro. “How Cybercriminals Can Perform Virtual Kidnapping Scams Using AI Voice Cloning",
              ""
            ],
            [
              "Tools and ChatGPT”. Accessed on Mar. 21, 2025, at: Link.",
              ""
            ],
            [
              "31  Trend Micro. (Dec. 16, 2024). Trend Micro. “Trend Micro Predicts Emergence of Deepfake-Powered Malicious Digital Twins”. Accessed on Mar. 21,",
              ""
            ],
            [
              "2025, at: Link.",
              ""
            ],
            [
              "32 Trend Micro. (n.d.). Trend Micro. “Coinminer.Win32.MalXMR.Ads”. Accessed on Mar. 21, 2025, at: Link.",
              ""
            ],
            [
              "33 Trend Micro. (n.d.). Trend Micro. “LNK_Bondat.SM”. Accessed on Mar. 21, 2025, at: Link.",
              ""
            ],
            [
              "34 Trend Micro. (n.d.). Trend Micro. “Tspy_Negasteal”. Accessed on Mar. 21, 2025, at: Link.",
              ""
            ],
            [
              "35 Trend Micro. (n.d.). Trend Micro. “Trojan.PS1.Powload.JKP”. Accessed on Mar. 21, 2025, at: Link.",
              ""
            ],
            [
              "36 Trend Micro. (n.d.). Trend Micro. “JS_Nemucod.SMC”. Accessed on Mar. 21, 2025, at: Link.",
              ""
            ],
            [
              "37 Trend Micro. (n.d.). Trend Micro. “Worm_Gamarue.SMJA”. Accessed on Mar. 21, 2025, at: Link.",
              ""
            ],
            [
              "38 Trend Micro. (n.d.). Trend Micro. “Trojan.Win32.Prometei.E”. Accessed on Mar. 21, 2025, at: Link.",
              ""
            ],
            [
              "39 Trend Micro. (n.d.). Trend Micro. “Worm.Win32.Dloader.LGA”. Accessed on Mar. 21, 2025, at: Link.",
              ""
            ],
            [
              "40 Trend Micro. (n.d.).Trend Micro. “Troj_Downad.E”. Accessed on Mar. 21, 2025, at: Link.",
              ""
            ],
            [
              "41 Trend Micro. (n.d.). Trend Micro. “Trojan.PHP.Webshell.SBJKUC”. Accessed on Mar. 21, 2025, at: Link.",
              ""
            ],
            [
              "Trend 2025 Cyber Risk Report",
              "62"
            ]
          ],
          "source_page": 62,
          "source_file": "data/source/Research-Risk-Report-2025.pdf",
          "table_type": "time_series",
          "confidence": 87.75687363229503,
          "extractor_method": "camelot",
          "metadata": {
            "whitespace": 46.875,
            "order": 1,
            "flavor": "stream"
          }
        },
        "source_page": 62,
        "source_file": "data/source/Research-Risk-Report-2025.pdf",
        "table_type": "time_series",
        "confidence": 87.75687363229503,
        "extractor_method": "camelot",
        "conversion_date": "2025-07-18T10:36:09.159187"
      }
    },
    {
      "table_id": "table_81_Camelot_Table_63_66",
      "content": "表格標題: Camelot_Table_63_66\n表格類型: general\n來源頁面: 第63頁\n資料提取方法: camelot\n信心度: 100.0%\n表格欄位: Trend Micro, a global cybersecurity leader, helps make the world safe for exchanging digital information. Fueled by decades of security expertise, global threat\n表格內容:\n  Trend Micro, a global cybersecurity leader, helps make the world safe for exchanging digital information. Fueled by decades of security expertise, global threat: research, and continuous innovation, Trend’s AI-powered cybersecurity platform protects over 500,000 organizations and millions of individuals across clouds,\n  Trend Micro, a global cybersecurity leader, helps make the world safe for exchanging digital information. Fueled by decades of security expertise, global threat: networks, devices, and endpoints.\n  Trend Micro, a global cybersecurity leader, helps make the world safe for exchanging digital information. Fueled by decades of security expertise, global threat: Trend’s platform delivers advanced threat defense techniques, extended detection and response (XDR), attack surface management (ASM), and integration across the\n  Trend Micro, a global cybersecurity leader, helps make the world safe for exchanging digital information. Fueled by decades of security expertise, global threat: IT ecosystem, including AWS, Microsoft, and Google. This enables organizations to better understand, communicate, and mitigate cyber risk.\n  Trend Micro, a global cybersecurity leader, helps make the world safe for exchanging digital information. Fueled by decades of security expertise, global threat: Trend’s global threat research team delivers unparalleled intelligence and insights that power the platform and help protect organizations around the world from\n  Trend Micro, a global cybersecurity leader, helps make the world safe for exchanging digital information. Fueled by decades of security expertise, global threat: hundreds of millions of threats daily.\n  Trend Micro, a global cybersecurity leader, helps make the world safe for exchanging digital information. Fueled by decades of security expertise, global threat: With 7,000 employees across 70 countries, Trend is singularly focused on cybersecurity by enabling organizations to simplify their connected world. TrendMicro.com.\n  Trend Micro, a global cybersecurity leader, helps make the world safe for exchanging digital information. Fueled by decades of security expertise, global threat: Trend Micro Standard Copyright Notice\n  Trend Micro, a global cybersecurity leader, helps make the world safe for exchanging digital information. Fueled by decades of security expertise, global threat: Copyright ©2025 Trend Micro Incorporated. All rights reserved. Trend Micro, the Trend Micro logo, and the t-ball logo are trademarks or registered trademarks of Trend\n  Trend Micro, a global cybersecurity leader, helps make the world safe for exchanging digital information. Fueled by decades of security expertise, global threat: Micro Incorporated. All other company and/or product names may be trademarks or registered trademarks of their owners. Information contained in this document is\n  Trend Micro, a global cybersecurity leader, helps make the world safe for exchanging digital information. Fueled by decades of security expertise, global threat: subject to change without notice. Trend Micro, the Trend Micro logo, and the t-ball logo Reg. U.S. Pat. & Tm. Off.\n  Trend Micro, a global cybersecurity leader, helps make the world safe for exchanging digital information. Fueled by decades of security expertise, global threat: For details about what personal information we collect and why, please see our Privacy Notice on our website at: trendmicro.com/privacy\n搜尋關鍵字: Trend Micro, a global cybersecurity leader, helps make the world safe for exchanging digital information. Fueled by decades of security expertise, global threat",
      "metadata": {
        "original_table_data": {
          "title": "Camelot_Table_63_66",
          "headers": [
            "Trend Micro, a global cybersecurity leader, helps make the world safe for exchanging digital information. Fueled by decades of security expertise, global threat"
          ],
          "rows": [
            [
              "research, and continuous innovation, Trend’s AI-powered cybersecurity platform protects over 500,000 organizations and millions of individuals across clouds,"
            ],
            [
              "networks, devices, and endpoints."
            ],
            [
              "Trend’s platform delivers advanced threat defense techniques, extended detection and response (XDR), attack surface management (ASM), and integration across the"
            ],
            [
              "IT ecosystem, including AWS, Microsoft, and Google. This enables organizations to better understand, communicate, and mitigate cyber risk."
            ],
            [
              "Trend’s global threat research team delivers unparalleled intelligence and insights that power the platform and help protect organizations around the world from"
            ],
            [
              "hundreds of millions of threats daily."
            ],
            [
              "With 7,000 employees across 70 countries, Trend is singularly focused on cybersecurity by enabling organizations to simplify their connected world. TrendMicro.com."
            ],
            [
              "Trend Micro Standard Copyright Notice"
            ],
            [
              "Copyright ©2025 Trend Micro Incorporated. All rights reserved. Trend Micro, the Trend Micro logo, and the t-ball logo are trademarks or registered trademarks of Trend"
            ],
            [
              "Micro Incorporated. All other company and/or product names may be trademarks or registered trademarks of their owners. Information contained in this document is"
            ],
            [
              "subject to change without notice. Trend Micro, the Trend Micro logo, and the t-ball logo Reg. U.S. Pat. & Tm. Off."
            ],
            [
              "For details about what personal information we collect and why, please see our Privacy Notice on our website at: trendmicro.com/privacy"
            ]
          ],
          "source_page": 63,
          "source_file": "data/source/Research-Risk-Report-2025.pdf",
          "table_type": "general",
          "confidence": 100.0,
          "extractor_method": "camelot",
          "metadata": {
            "whitespace": 0.0,
            "order": 1,
            "flavor": "stream"
          }
        },
        "source_page": 63,
        "source_file": "data/source/Research-Risk-Report-2025.pdf",
        "table_type": "general",
        "confidence": 100.0,
        "extractor_method": "camelot",
        "conversion_date": "2025-07-18T10:36:09.159216"
      }
    },
    {
      "table_id": "table_82_PDFPlumber_Table_9_2",
      "content": "表格標題: PDFPlumber_Table_9_2\n表格類型: comparison\n來源頁面: 第9頁\n資料提取方法: pdfplumber\n信心度: 0.8%\n表格欄位: 43.9, 42.3, 40.0, 39, .5\n表格內容:\n  43.9: 44.5, 42.3: 42.6, 40.0: 41.0, .5: .3\n  43.9: 43.9, 42.3: 41.3, 40.0: 40.0, 39: 38.\n  43.9: 45.1, 42.3: 43.1, 40.0: 41.1, .5: .8\n  43.9: 43.7, 42.3: 41.6, 40.0: 41.2, 39: 39, .5: .6\n  43.9: 42.6, 42.3: 40.7, 40.0: 8.8\n  43.9: 42.9, 42.3: 40.7, 40.0: 9.5, .5: 1\n  43.9: 43.7, 42.3: 41.4, 40.0: 40.3, 39: 39., .5: 4\n  43.9: 43.7, 42.3: 41.4, 40.0: 40.3, 39: 39., .5: 7\n  43.9: 42.6, 42.3: 40.8, 40.0: 9.4\n搜尋關鍵字: 比較, 對比, 分析, 43.9, 42.3, 40.0, 39, .5, 44.5, 42.6",
      "metadata": {
        "original_table_data": {
          "title": "PDFPlumber_Table_9_2",
          "headers": [
            "43.9",
            "",
            "42.3",
            "",
            "",
            "40.0",
            "",
            "39",
            "",
            ".5"
          ],
          "rows": [
            [
              "44.5",
              "",
              "42.6",
              "",
              "",
              "41.0",
              "",
              "",
              "39",
              ".3"
            ],
            [
              "43.9",
              "",
              "41.3",
              "",
              "",
              "40.0",
              "",
              "38.",
              "",
              ""
            ],
            [
              "45.1",
              "",
              "43.1",
              "",
              "",
              "41.1",
              "",
              "",
              "39",
              ".8"
            ],
            [
              "43.7",
              "",
              "41.6",
              "",
              "",
              "41.2",
              "",
              "39",
              "",
              ".6"
            ],
            [
              "42.6",
              "",
              "40.7",
              "3",
              "",
              "8.8",
              "37.9",
              "",
              "",
              ""
            ],
            [
              "42.9",
              "",
              "40.7",
              "3",
              "",
              "9.5",
              "39.",
              "",
              "",
              "1"
            ],
            [
              "43.7",
              "",
              "41.4",
              "",
              "",
              "40.3",
              "",
              "39.",
              "",
              "4"
            ],
            [
              "43.7",
              "",
              "41.4",
              "",
              "",
              "40.3",
              "",
              "39.",
              "",
              "7"
            ],
            [
              "42.6",
              "",
              "40.8",
              "3",
              "",
              "9.4",
              "37.8",
              "",
              "",
              ""
            ]
          ],
          "source_page": 9,
          "source_file": "data/source/Research-Risk-Report-2025.pdf",
          "table_type": "comparison",
          "confidence": 0.8,
          "extractor_method": "pdfplumber",
          "metadata": {
            "page_width": 1920.0,
            "page_height": 1080.0
          }
        },
        "source_page": 9,
        "source_file": "data/source/Research-Risk-Report-2025.pdf",
        "table_type": "comparison",
        "confidence": 0.8,
        "extractor_method": "pdfplumber",
        "conversion_date": "2025-07-18T10:36:09.159259"
      }
    },
    {
      "table_id": "table_83_PDFPlumber_Table_52_1",
      "content": "表格標題: PDFPlumber_Table_52_1\n表格類型: general\n來源頁面: 第52頁\n資料提取方法: pdfplumber\n信心度: 0.8%\n表格欄位: 118\n表格內容:\n搜尋關鍵字: 118, 60",
      "metadata": {
        "original_table_data": {
          "title": "PDFPlumber_Table_52_1",
          "headers": [
            "",
            "",
            "",
            "",
            "",
            "",
            "",
            "",
            "",
            "",
            "",
            "",
            "",
            "",
            "",
            "118",
            "",
            "",
            "",
            "",
            "",
            "",
            ""
          ],
          "rows": [
            [
              "",
              "",
              "",
              "",
              "",
              "60",
              "",
              "",
              "",
              "",
              "",
              "",
              "",
              "",
              "",
              "",
              "",
              "",
              "",
              "",
              "",
              "",
              ""
            ]
          ],
          "source_page": 52,
          "source_file": "data/source/Research-Risk-Report-2025.pdf",
          "table_type": "general",
          "confidence": 0.8,
          "extractor_method": "pdfplumber",
          "metadata": {
            "page_width": 1920.0,
            "page_height": 1080.0
          }
        },
        "source_page": 52,
        "source_file": "data/source/Research-Risk-Report-2025.pdf",
        "table_type": "general",
        "confidence": 0.8,
        "extractor_method": "pdfplumber",
        "conversion_date": "2025-07-18T10:36:09.159275"
      }
    },
    {
      "table_id": "table_84_PyMuPDF_Table_8_1",
      "content": "表格標題: PyMuPDF_Table_8_1\n表格類型: comparison\n來源頁面: 第8頁\n資料提取方法: pymupdf\n信心度: 0.8%\n表格欄位: Europe:, 37.9\n表格內容:\n  Europe:: AMEA:, 37.9: 37.9\n  Europe:: Americas:, 37.9: 39.8\n  Europe:: Japan:, 37.9: 34.3\n搜尋關鍵字: 比較, 對比, 分析, Europe:, 37.9, AMEA:, 37.9, Americas:, 39.8, Japan:",
      "metadata": {
        "original_table_data": {
          "title": "PyMuPDF_Table_8_1",
          "headers": [
            "Europe:",
            "37.9"
          ],
          "rows": [
            [
              "AMEA:",
              "37.9"
            ],
            [
              "Americas:",
              "39.8"
            ],
            [
              "Japan:",
              "34.3"
            ]
          ],
          "source_page": 8,
          "source_file": "data/source/Research-Risk-Report-2025.pdf",
          "table_type": "comparison",
          "confidence": 0.85,
          "extractor_method": "pymupdf",
          "metadata": {
            "extraction_method": "text_pattern",
            "pattern_type": "text_pattern"
          }
        },
        "source_page": 8,
        "source_file": "data/source/Research-Risk-Report-2025.pdf",
        "table_type": "comparison",
        "confidence": 0.85,
        "extractor_method": "pymupdf",
        "conversion_date": "2025-07-18T10:36:09.159294"
      }
    },
    {
      "table_id": "table_85_PyMuPDF_Table_60_1",
      "content": "表格標題: PyMuPDF_Table_60_1\n表格類型: comparison\n來源頁面: 第60頁\n資料提取方法: pymupdf\n信心度: 1.0%\n表格欄位: 1, Trend Micro. (n.d.). Trend Micro. “Cyber Risk Exposure Management”. Accessed on Mar. 21, 2025, at: Link.\n表格內容:\n  1: 2, Trend Micro. (n.d.). Trend Micro. “Cyber Risk Exposure Management”. Accessed on Mar. 21, 2025, at: Link.: Trend Micro. (n.d.). Trend Micro. “One Platform”. Accessed on Mar. 21, 2025, at: Link.\n  1: 3, Trend Micro. (n.d.). Trend Micro. “Cyber Risk Exposure Management”. Accessed on Mar. 21, 2025, at: Link.: Trend Micro. (n.d.). Trend Micro. “XDR (Extended Detection and Response)”. Accessed on Mar. 21, 2025, at: Link.\n  1: 4, Trend Micro. (n.d.). Trend Micro. “Cyber Risk Exposure Management”. Accessed on Mar. 21, 2025, at: Link.: Trend Micro. (February 10, 2025). Trend Micro. “From Vulnerable to Resilient: Cutting Ransomware Risk with Proactive Attack Surface\n搜尋關鍵字: 比較, 對比, 分析, Trend Micro. (n.d.). Trend Micro. “Cyber Risk Exposure Management”. Accessed on Mar. 21, 2025, at: Link.",
      "metadata": {
        "original_table_data": {
          "title": "PyMuPDF_Table_60_1",
          "headers": [
            "1",
            "Trend Micro. (n.d.). Trend Micro. “Cyber Risk Exposure Management”. Accessed on Mar. 21, 2025, at: Link."
          ],
          "rows": [
            [
              "2",
              "Trend Micro. (n.d.). Trend Micro. “One Platform”. Accessed on Mar. 21, 2025, at: Link."
            ],
            [
              "3",
              "Trend Micro. (n.d.). Trend Micro. “XDR (Extended Detection and Response)”. Accessed on Mar. 21, 2025, at: Link."
            ],
            [
              "4",
              "Trend Micro. (February 10, 2025). Trend Micro. “From Vulnerable to Resilient: Cutting Ransomware Risk with Proactive Attack Surface"
            ]
          ],
          "source_page": 60,
          "source_file": "data/source/Research-Risk-Report-2025.pdf",
          "table_type": "comparison",
          "confidence": 1.0,
          "extractor_method": "pymupdf",
          "metadata": {
            "extraction_method": "text_pattern",
            "pattern_type": "text_pattern"
          }
        },
        "source_page": 60,
        "source_file": "data/source/Research-Risk-Report-2025.pdf",
        "table_type": "comparison",
        "confidence": 1.0,
        "extractor_method": "pymupdf",
        "conversion_date": "2025-07-18T10:36:09.159315"
      }
    },
    {
      "table_id": "table_86_PyMuPDF_Table_60_2",
      "content": "表格標題: PyMuPDF_Table_60_2\n表格類型: comparison\n來源頁面: 第60頁\n資料提取方法: pymupdf\n信心度: 1.0%\n表格欄位: 5, Trend Micro. (n.d.). Trend Micro. “Trend Vision One Risk Index Overview”. Accessed on Mar. 21, 2025, at: Link.\n表格內容:\n  5: 6, Trend Micro. (n.d.). Trend Micro. “Trend Vision One Risk Index Overview”. Accessed on Mar. 21, 2025, at: Link.: Trend Micro. (n.d.). Trend Micro. “More Than a Number: Your Risk Score Explained”. Accessed on Mar. 21, 2025, at: Link.\n  5: 7, Trend Micro. (n.d.). Trend Micro. “Trend Vision One Risk Index Overview”. Accessed on Mar. 21, 2025, at: Link.: Digital Operational Resilience Act. (n.d.). Digital Operational Resilience Act. “Official Website”. Accessed on Mar. 21, 2025, at: Link.\n  5: 8, Trend Micro. (n.d.). Trend Micro. “Trend Vision One Risk Index Overview”. Accessed on Mar. 21, 2025, at: Link.: European Commission. (n.d.). Digital Strategy - European Commission. “Cyber Resilience Act”. Accessed on Mar. 21, 2025, at: Link.\n  5: 9, Trend Micro. (n.d.). Trend Micro. “Trend Vision One Risk Index Overview”. Accessed on Mar. 21, 2025, at: Link.: Trend Micro. (n.d.). Trend Micro. “Email and Collaboration Security”. Accessed on Mar. 21, 2025, at: Link.\n  5: 10, Trend Micro. (n.d.). Trend Micro. “Trend Vision One Risk Index Overview”. Accessed on Mar. 21, 2025, at: Link.: Trend Micro. (n.d.). Trend Micro. “Identity and Access Management”. Accessed on Mar. 21, 2025, at: Link.\n  5: 11, Trend Micro. (n.d.). Trend Micro. “Trend Vision One Risk Index Overview”. Accessed on Mar. 21, 2025, at: Link.: Trend Micro. (n.d.). Trend Micro. “Endpoint Security”. Accessed on Mar. 21, 2025, at: Link.\n  5: 12, Trend Micro. (n.d.). Trend Micro. “Trend Vision One Risk Index Overview”. Accessed on Mar. 21, 2025, at: Link.: Trend Micro. (n.d.). Trend Micro. “Hybrid Cloud Security”. Accessed on Mar. 21, 2025, at: Link.\n  5: 13, Trend Micro. (n.d.). Trend Micro. “Trend Vision One Risk Index Overview”. Accessed on Mar. 21, 2025, at: Link.: CISA. (Sep. 28, 2021). Cybersecurity & Infrastructure Security Agency (CISA). “RCE Vulnerability in Hikvision Cameras (CVE-2021-36260)”. Accessed\n搜尋關鍵字: 比較, 對比, 分析, Trend Micro. (n.d.). Trend Micro. “Trend Vision One Risk Index Overview”. Accessed on Mar. 21, 2025, at: Link.",
      "metadata": {
        "original_table_data": {
          "title": "PyMuPDF_Table_60_2",
          "headers": [
            "5",
            "Trend Micro. (n.d.). Trend Micro. “Trend Vision One Risk Index Overview”. Accessed on Mar. 21, 2025, at: Link."
          ],
          "rows": [
            [
              "6",
              "Trend Micro. (n.d.). Trend Micro. “More Than a Number: Your Risk Score Explained”. Accessed on Mar. 21, 2025, at: Link."
            ],
            [
              "7",
              "Digital Operational Resilience Act. (n.d.). Digital Operational Resilience Act. “Official Website”. Accessed on Mar. 21, 2025, at: Link."
            ],
            [
              "8",
              "European Commission. (n.d.). Digital Strategy - European Commission. “Cyber Resilience Act”. Accessed on Mar. 21, 2025, at: Link."
            ],
            [
              "9",
              "Trend Micro. (n.d.). Trend Micro. “Email and Collaboration Security”. Accessed on Mar. 21, 2025, at: Link."
            ],
            [
              "10",
              "Trend Micro. (n.d.). Trend Micro. “Identity and Access Management”. Accessed on Mar. 21, 2025, at: Link."
            ],
            [
              "11",
              "Trend Micro. (n.d.). Trend Micro. “Endpoint Security”. Accessed on Mar. 21, 2025, at: Link."
            ],
            [
              "12",
              "Trend Micro. (n.d.). Trend Micro. “Hybrid Cloud Security”. Accessed on Mar. 21, 2025, at: Link."
            ],
            [
              "13",
              "CISA. (Sep. 28, 2021). Cybersecurity & Infrastructure Security Agency (CISA). “RCE Vulnerability in Hikvision Cameras (CVE-2021-36260)”. Accessed"
            ]
          ],
          "source_page": 60,
          "source_file": "data/source/Research-Risk-Report-2025.pdf",
          "table_type": "comparison",
          "confidence": 1.0,
          "extractor_method": "pymupdf",
          "metadata": {
            "extraction_method": "text_pattern",
            "pattern_type": "text_pattern"
          }
        },
        "source_page": 60,
        "source_file": "data/source/Research-Risk-Report-2025.pdf",
        "table_type": "comparison",
        "confidence": 1.0,
        "extractor_method": "pymupdf",
        "conversion_date": "2025-07-18T10:36:09.159344"
      }
    },
    {
      "table_id": "table_87_PyMuPDF_Table_61_1",
      "content": "表格標題: PyMuPDF_Table_61_1\n表格類型: comparison\n來源頁面: 第61頁\n資料提取方法: pymupdf\n信心度: 1.0%\n表格欄位: 14, NIST. (Sep. 22, 2021). National Institute of Standards and Technology (NIST). “CVE-2021-36260 Detail”. Accessed on Mar. 21, 2025, at: Link.\n表格內容:\n  14: 15, NIST. (Sep. 22, 2021). National Institute of Standards and Technology (NIST). “CVE-2021-36260 Detail”. Accessed on Mar. 21, 2025, at: Link.: NIST. (Feb. 13, 2024)”. National Vulnerability Database (NVD). “CVE-2024-21357”. Accessed on Mar. 21, 2025, at: Link.\n  14: 16, NIST. (Sep. 22, 2021). National Institute of Standards and Technology (NIST). “CVE-2021-36260 Detail”. Accessed on Mar. 21, 2025, at: Link.: NIST. (June 11, 2024). National Vulnerability Database (NVD). “CVE-2024-30086”. Accessed on Mar. 21, 2025, at: Link.\n  14: 17, NIST. (Sep. 22, 2021). National Institute of Standards and Technology (NIST). “CVE-2021-36260 Detail”. Accessed on Mar. 21, 2025, at: Link.: NIST. (June 11, 2024). National Vulnerability Database (NVD). “CVE-2024-30082”. Accessed on Mar. 21, 2025, at: Link.\n  14: 18, NIST. (Sep. 22, 2021). National Institute of Standards and Technology (NIST). “CVE-2021-36260 Detail”. Accessed on Mar. 21, 2025, at: Link.: NIST. (June 11, 2024). National Vulnerability Database (NVD). “CVE-2024-30087”. Accessed on Mar. 21, 2025, at: Link.\n  14: 19, NIST. (Sep. 22, 2021). National Institute of Standards and Technology (NIST). “CVE-2021-36260 Detail”. Accessed on Mar. 21, 2025, at: Link.: NIST. (June 11, 2024). National Vulnerability Database (NVD). “CVE-2024-35250”. Accessed on Mar. 21, 2025, at: Link.\n  14: 20, NIST. (Sep. 22, 2021). National Institute of Standards and Technology (NIST). “CVE-2021-36260 Detail”. Accessed on Mar. 21, 2025, at: Link.: NIST. (June 11, 2024). National Vulnerability Database (NVD). “CVE-2024-30091”. Accessed on Mar. 21, 2025, at: Link.\n  14: 21, NIST. (Sep. 22, 2021). National Institute of Standards and Technology (NIST). “CVE-2021-36260 Detail”. Accessed on Mar. 21, 2025, at: Link.: NIST. (May 14, 2024). National Vulnerability Database (NVD). “CVE-2024-30049”. Accessed on Mar. 21, 2025, at: Link.\n  14: 22, NIST. (Sep. 22, 2021). National Institute of Standards and Technology (NIST). “CVE-2021-36260 Detail”. Accessed on Mar. 21, 2025, at: Link.: NIST. (June 11, 2024). National Vulnerability Database (NVD). “CVE-2024-30084”. Accessed on Mar. 21, 2025, at: Link.\n  14: 23, NIST. (Sep. 22, 2021). National Institute of Standards and Technology (NIST). “CVE-2021-36260 Detail”. Accessed on Mar. 21, 2025, at: Link.: NIST. (May 14, 2024). National Vulnerability Database (NVD). “CVE-2024-30050”. Accessed on Mar. 21, 2025, at: Link.\n  14: 24, NIST. (Sep. 22, 2021). National Institute of Standards and Technology (NIST). “CVE-2021-36260 Detail”. Accessed on Mar. 21, 2025, at: Link.: NIST. (May 14, 2024). National Vulnerability Database (NVD). “CVE-2024-30037”. Accessed on Mar 21, 2025, at: Link.\n  14: 25, NIST. (Sep. 22, 2021). National Institute of Standards and Technology (NIST). “CVE-2021-36260 Detail”. Accessed on Mar. 21, 2025, at: Link.: Gennai Security Project. (Nov. 17, 2024). Gennai Security Project. “OWASP Top 10 for LLM Applications 2025”. Accessed on Mar. 21, 2025, at: Link.\n  14: 26, NIST. (Sep. 22, 2021). National Institute of Standards and Technology (NIST). “CVE-2021-36260 Detail”. Accessed on Mar. 21, 2025, at: Link.: AI Team. (Aug. 15, 2024). Trend Micro. “Rogue AI: Part 1”. Accessed on Mar. 21, 2025, at: Link.\n  14: 27, NIST. (Sep. 22, 2021). National Institute of Standards and Technology (NIST). “CVE-2021-36260 Detail”. Accessed on Mar. 21, 2025, at: Link.: Nada Elrayes. (Sep. 26, 2024). Trend Micro. “Countering AI-Driven Threats with AI-Powered Defense”. Accessed on Mar. 21, 2025, at: Link.\n  14: 28, NIST. (Sep. 22, 2021). National Institute of Standards and Technology (NIST). “CVE-2021-36260 Detail”. Accessed on Mar. 21, 2025, at: Link.: Trend Micro. (Sep. 19, 2024). Trend Micro. “The Illusion of Choice: Uncovering Electoral Deceptions in the Age of AI”. Accessed on Mar. 21, 2025, at:\n搜尋關鍵字: 比較, 對比, 分析, 14, NIST. (Sep. 22, 2021). National Institute of Standards and Technology (NIST). “CVE-2021-36260 Detail”. Accessed on Mar. 21, 2025, at: Link., 15, 16, 17",
      "metadata": {
        "original_table_data": {
          "title": "PyMuPDF_Table_61_1",
          "headers": [
            "14",
            "NIST. (Sep. 22, 2021). National Institute of Standards and Technology (NIST). “CVE-2021-36260 Detail”. Accessed on Mar. 21, 2025, at: Link."
          ],
          "rows": [
            [
              "15",
              "NIST. (Feb. 13, 2024)”. National Vulnerability Database (NVD). “CVE-2024-21357”. Accessed on Mar. 21, 2025, at: Link."
            ],
            [
              "16",
              "NIST. (June 11, 2024). National Vulnerability Database (NVD). “CVE-2024-30086”. Accessed on Mar. 21, 2025, at: Link."
            ],
            [
              "17",
              "NIST. (June 11, 2024). National Vulnerability Database (NVD). “CVE-2024-30082”. Accessed on Mar. 21, 2025, at: Link."
            ],
            [
              "18",
              "NIST. (June 11, 2024). National Vulnerability Database (NVD). “CVE-2024-30087”. Accessed on Mar. 21, 2025, at: Link."
            ],
            [
              "19",
              "NIST. (June 11, 2024). National Vulnerability Database (NVD). “CVE-2024-35250”. Accessed on Mar. 21, 2025, at: Link."
            ],
            [
              "20",
              "NIST. (June 11, 2024). National Vulnerability Database (NVD). “CVE-2024-30091”. Accessed on Mar. 21, 2025, at: Link."
            ],
            [
              "21",
              "NIST. (May 14, 2024). National Vulnerability Database (NVD). “CVE-2024-30049”. Accessed on Mar. 21, 2025, at: Link."
            ],
            [
              "22",
              "NIST. (June 11, 2024). National Vulnerability Database (NVD). “CVE-2024-30084”. Accessed on Mar. 21, 2025, at: Link."
            ],
            [
              "23",
              "NIST. (May 14, 2024). National Vulnerability Database (NVD). “CVE-2024-30050”. Accessed on Mar. 21, 2025, at: Link."
            ],
            [
              "24",
              "NIST. (May 14, 2024). National Vulnerability Database (NVD). “CVE-2024-30037”. Accessed on Mar 21, 2025, at: Link."
            ],
            [
              "25",
              "Gennai Security Project. (Nov. 17, 2024). Gennai Security Project. “OWASP Top 10 for LLM Applications 2025”. Accessed on Mar. 21, 2025, at: Link."
            ],
            [
              "26",
              "AI Team. (Aug. 15, 2024). Trend Micro. “Rogue AI: Part 1”. Accessed on Mar. 21, 2025, at: Link."
            ],
            [
              "27",
              "Nada Elrayes. (Sep. 26, 2024). Trend Micro. “Countering AI-Driven Threats with AI-Powered Defense”. Accessed on Mar. 21, 2025, at: Link."
            ],
            [
              "28",
              "Trend Micro. (Sep. 19, 2024). Trend Micro. “The Illusion of Choice: Uncovering Electoral Deceptions in the Age of AI”. Accessed on Mar. 21, 2025, at:"
            ]
          ],
          "source_page": 61,
          "source_file": "data/source/Research-Risk-Report-2025.pdf",
          "table_type": "comparison",
          "confidence": 1.0,
          "extractor_method": "pymupdf",
          "metadata": {
            "extraction_method": "text_pattern",
            "pattern_type": "text_pattern"
          }
        },
        "source_page": 61,
        "source_file": "data/source/Research-Risk-Report-2025.pdf",
        "table_type": "comparison",
        "confidence": 1.0,
        "extractor_method": "pymupdf",
        "conversion_date": "2025-07-18T10:36:09.159387"
      }
    },
    {
      "table_id": "table_88_PyMuPDF_Table_62_1",
      "content": "表格標題: PyMuPDF_Table_62_1\n表格類型: comparison\n來源頁面: 第62頁\n資料提取方法: pymupdf\n信心度: 1.0%\n表格欄位: 32, Trend Micro. (n.d.). Trend Micro. “Coinminer.Win32.MalXMR.Ads”. Accessed on Mar. 21, 2025, at: Link.\n表格內容:\n  32: 33, Trend Micro. (n.d.). Trend Micro. “Coinminer.Win32.MalXMR.Ads”. Accessed on Mar. 21, 2025, at: Link.: Trend Micro. (n.d.). Trend Micro. “LNK_Bondat.SM”. Accessed on Mar. 21, 2025, at: Link.\n  32: 34, Trend Micro. (n.d.). Trend Micro. “Coinminer.Win32.MalXMR.Ads”. Accessed on Mar. 21, 2025, at: Link.: Trend Micro. (n.d.). Trend Micro. “Tspy_Negasteal”. Accessed on Mar. 21, 2025, at: Link.\n  32: 35, Trend Micro. (n.d.). Trend Micro. “Coinminer.Win32.MalXMR.Ads”. Accessed on Mar. 21, 2025, at: Link.: Trend Micro. (n.d.). Trend Micro. “Trojan.PS1.Powload.JKP”. Accessed on Mar. 21, 2025, at: Link.\n  32: 36, Trend Micro. (n.d.). Trend Micro. “Coinminer.Win32.MalXMR.Ads”. Accessed on Mar. 21, 2025, at: Link.: Trend Micro. (n.d.). Trend Micro. “JS_Nemucod.SMC”. Accessed on Mar. 21, 2025, at: Link.\n  32: 37, Trend Micro. (n.d.). Trend Micro. “Coinminer.Win32.MalXMR.Ads”. Accessed on Mar. 21, 2025, at: Link.: Trend Micro. (n.d.). Trend Micro. “Worm_Gamarue.SMJA”. Accessed on Mar. 21, 2025, at: Link.\n  32: 38, Trend Micro. (n.d.). Trend Micro. “Coinminer.Win32.MalXMR.Ads”. Accessed on Mar. 21, 2025, at: Link.: Trend Micro. (n.d.). Trend Micro. “Trojan.Win32.Prometei.E”. Accessed on Mar. 21, 2025, at: Link.\n  32: 39, Trend Micro. (n.d.). Trend Micro. “Coinminer.Win32.MalXMR.Ads”. Accessed on Mar. 21, 2025, at: Link.: Trend Micro. (n.d.). Trend Micro. “Worm.Win32.Dloader.LGA”. Accessed on Mar. 21, 2025, at: Link.\n  32: 40, Trend Micro. (n.d.). Trend Micro. “Coinminer.Win32.MalXMR.Ads”. Accessed on Mar. 21, 2025, at: Link.: Trend Micro. (n.d.).Trend Micro. “Troj_Downad.E”. Accessed on Mar. 21, 2025, at: Link.\n  32: 41, Trend Micro. (n.d.). Trend Micro. “Coinminer.Win32.MalXMR.Ads”. Accessed on Mar. 21, 2025, at: Link.: Trend Micro. (n.d.). Trend Micro. “Trojan.PHP.Webshell.SBJKUC”. Accessed on Mar. 21, 2025, at: Link.\n搜尋關鍵字: 比較, 對比, 分析, 32, Trend Micro. (n.d.). Trend Micro. “Coinminer.Win32.MalXMR.Ads”. Accessed on Mar. 21, 2025, at: Link., 33, 34, 35",
      "metadata": {
        "original_table_data": {
          "title": "PyMuPDF_Table_62_1",
          "headers": [
            "32",
            "Trend Micro. (n.d.). Trend Micro. “Coinminer.Win32.MalXMR.Ads”. Accessed on Mar. 21, 2025, at: Link."
          ],
          "rows": [
            [
              "33",
              "Trend Micro. (n.d.). Trend Micro. “LNK_Bondat.SM”. Accessed on Mar. 21, 2025, at: Link."
            ],
            [
              "34",
              "Trend Micro. (n.d.). Trend Micro. “Tspy_Negasteal”. Accessed on Mar. 21, 2025, at: Link."
            ],
            [
              "35",
              "Trend Micro. (n.d.). Trend Micro. “Trojan.PS1.Powload.JKP”. Accessed on Mar. 21, 2025, at: Link."
            ],
            [
              "36",
              "Trend Micro. (n.d.). Trend Micro. “JS_Nemucod.SMC”. Accessed on Mar. 21, 2025, at: Link."
            ],
            [
              "37",
              "Trend Micro. (n.d.). Trend Micro. “Worm_Gamarue.SMJA”. Accessed on Mar. 21, 2025, at: Link."
            ],
            [
              "38",
              "Trend Micro. (n.d.). Trend Micro. “Trojan.Win32.Prometei.E”. Accessed on Mar. 21, 2025, at: Link."
            ],
            [
              "39",
              "Trend Micro. (n.d.). Trend Micro. “Worm.Win32.Dloader.LGA”. Accessed on Mar. 21, 2025, at: Link."
            ],
            [
              "40",
              "Trend Micro. (n.d.).Trend Micro. “Troj_Downad.E”. Accessed on Mar. 21, 2025, at: Link."
            ],
            [
              "41",
              "Trend Micro. (n.d.). Trend Micro. “Trojan.PHP.Webshell.SBJKUC”. Accessed on Mar. 21, 2025, at: Link."
            ]
          ],
          "source_page": 62,
          "source_file": "data/source/Research-Risk-Report-2025.pdf",
          "table_type": "comparison",
          "confidence": 1.0,
          "extractor_method": "pymupdf",
          "metadata": {
            "extraction_method": "text_pattern",
            "pattern_type": "text_pattern"
          }
        },
        "source_page": 62,
        "source_file": "data/source/Research-Risk-Report-2025.pdf",
        "table_type": "comparison",
        "confidence": 1.0,
        "extractor_method": "pymupdf",
        "conversion_date": "2025-07-18T10:36:09.159419"
      }
    }
  ]
}